Workbook

Sheet Start here
B1: AI Vendor Due-Diligence Questionnaire
B2: By John Bommeraveni Joseph | linkedin.com/in/john-bj | Free every weekday: GRC Made Simple Daily
B5: What this is
B6: A due-diligence questionnaire and scoring workbook for buying or renewing any product with AI features - 74 questions in 14 sections covering training use of your data, retention, the model provider behind the product, certifications (scope and period, not the logo), silent model updates, testing, agent permissions, output handling, human oversight, logging, incident notification, regulatory position, IP and exit. Built for CISOs, GRC, procurement and privacy teams; supports third-party AI risk work under ISO/IEC 42001 (Annex A.10 Third-party and customer relationships), the NIST AI RMF and the EU AI Act.
B7: How to use it (one workbook per vendor)
B8: 1. Save a copy for the vendor first. The workbook ships filled with a worked example for a fictional vendor so you can see every formula working. To start a real review, clear the yellow cells on Vendor Profile, the yellow columns F, G, H and O on Questionnaire, and rows 6-7 of Follow-up Tracker.
B9: 2. Vendor Profile: record the product, AI features in scope, model provider(s), data shared and the criticality tier. The sheet suggests a minimum tier from the data and use you describe.
B10: 3. Send the Questionnaire to the vendor (columns A to G). Ask for evidence, not marketing: the 'What good evidence looks like' column tells both sides what will be accepted.
B11: 4. Score every answered question 0-3 on the evidence you received, not on the vendor's answer. Adjust the weight (1-3) and the Critical flag to your risk appetite before scoring, and record that decision.
B12: 5. Scoring Summary gives section scores, the overall rating, red flags and a recommendation using the thresholds shown on that sheet. Change the thresholds there (yellow cells) to match your TPRM policy.
B13: 6. Follow-up Tracker: log every gap, condition or evidence request with an owner and due date. 'Approve with conditions' only makes sense if the conditions are tracked here and in the contract.
B14: 7. Dashboard: the one-page result for the approver or the third-party risk committee.
... B22: Version 1.0 - 27 October 2026. Free to use and share with this credit kept.

Sheet Dashboard
B1: AI Vendor Risk Dashboard
B2: By John Bommeraveni Joseph | linkedin.com/in/john-bj | Free every weekday: GRC Made Simple Daily
B5: Measure | C5: Value | E5: Section | F5: Score % | G5: Red flags
B6: Vendor | C6: =IF('Vendor Profile'!C6="","",'Vendor Profile'!C6) -> Example Vendor Ltd (fictional) | E6: ='Scoring Summary'!B6 -> 1. Training and model improvement | F6: ='Scoring Summary'!I6 -> 0.75 | G6: ='Scoring Summary'!K6 -> 0
B7: Product / plan | C7: =IF('Vendor Profile'!C7="","",'Vendor Profile'!C7) -> Example Support Copilot - Enterprise plan | E7: ='Scoring Summary'!B7 -> 2. Retention of prompts, outputs and logs | F7: ='Scoring Summary'!I7 -> 0.66666667 | G7: ='Scoring Summary'!K7 -> 0
B8: Criticality tier | C8: =IF('Vendor Profile'!C21="","",'Vendor Profile'!C21) -> Tier 2 - High | E8: ='Scoring Summary'!B8 -> 3. Data residency and sub-processors (including the model provider) | F8: ='Scoring Summary'!I8 -> 0.87179487 | G8: ='Scoring Summary'!K8 -> 0
B9: Tier check | C9: ='Vendor Profile'!C22 -> OK | E9: ='Scoring Summary'!B9 -> 4. Security controls and certifications | F9: ='Scoring Summary'!I9 -> 0.76470588 | G9: ='Scoring Summary'!K9 -> 0
B10: RECOMMENDATION | C10: ='Scoring Summary'!$J$30 -> Escalate | E10: ='Scoring Summary'!B10 -> 5. Model change management | F10: ='Scoring Summary'!I10 -> 0.45454545 | G10: ='Scoring Summary'!K10 -> 1
B11: Recommendation on the scores so far | C11: ='Scoring Summary'!$J$29 -> Escalate | E11: ='Scoring Summary'!B11 -> 6. Evaluation and testing | F11: ='Scoring Summary'!I11 -> 0.66666667 | G11: ='Scoring Summary'!K11 -> 0
B12: Overall score | C12: ='Scoring Summary'!$J$24 -> 0.73837209 | E12: ='Scoring Summary'!B12 -> 7. Agent and tool permissions (excessive agency) | F12: ='Scoring Summary'!I12 -> 0.84444444 | G12: ='Scoring Summary'!K12 -> 0
B13: Overall rating | C13: ='Scoring Summary'!$J$25 -> Adequate | E13: ='Scoring Summary'!B13 -> 8. Output handling and hallucination controls | F13: ='Scoring Summary'!I13 -> 0.75 | G13: ='Scoring Summary'!K13 -> 0
B14: Red flags | C14: ='Scoring Summary'!$J$26 -> 1 | E14: ='Scoring Summary'!B14 -> 9. Human oversight | F14: ='Scoring Summary'!I14 -> 0.86666667 | G14: ='Scoring Summary'!K14 -> 0
B15: Lowest section score | C15: ='Scoring Summary'!$J$27 -> 0.45454545 | E15: ='Scoring Summary'!B15 -> 10. Logging and audit trail (customer-accessible) | F15: ='Scoring Summary'!I15 -> 0.7 | G15: ='Scoring Summary'!K15 -> 0
B16: Questions answered | C16: =COUNTIFS(Questionnaire!$A$6:$A$93,"<>",Questionnaire!$F$6:$F$93,"<>")&" of "&COUNTIF(Questionnaire!$B$6:$B$93,"?*") -> 74 of 74 | E16: ='Scoring Summary'!B16 -> 11. Incident response and AI-incident notification | F16: ='Scoring Summary'!I16 -> 0.72222222 | G16: ='Scoring Summary'!K16 -> 0
B17: Answered 'No' | C17: =COUNTIF(Questionnaire!$F$6:$F$93,"No") -> 2 | E17: ='Scoring Summary'!B17 -> 12. Regulatory position (EU AI Act, GDPR, DPDP) | F17: ='Scoring Summary'!I17 -> 0.78571429 | G17: ='Scoring Summary'!K17 -> 0
B18: Yes / Partial without an evidence reference | C18: =COUNTIF(Questionnaire!$N$6:$N$93,"Evidence missing") -> 1 | E18: ='Scoring Summary'!B18 -> 13. IP and indemnity for generated output | F18: ='Scoring Summary'!I18 -> 0.74074074 | G18: ='Scoring Summary'!K18 -> 0
B19: Vendor said Yes but evidence scored 0-1 | C19: =COUNTIF(Questionnaire!$N$6:$N$93,"Claim not supported") -> 0 | E19: ='Scoring Summary'!B19 -> 14. Continuity and exit | F19: ='Scoring Summary'!I19 -> 0.6969697 | G19: ='Scoring Summary'!K19 -> 0
B20: Follow-ups open | C20: =COUNTIFS('Follow-up Tracker'!$A$6:$A$105,"<>",'Follow-up Tracker'!$L$6:$L$105,"<>Closed",'Follow-up Tracker'!$L$6:$L$105,"<>Risk accepted") -> 2
B21: Follow-ups overdue | C21: =COUNTIF('Follow-up Tracker'!$O$6:$O$105,"OVERDUE") -> 1
B22: Open follow-ups that block approval | C22: =COUNTIFS('Follow-up Tracker'!$A$6:$A$105,"<>",'Follow-up Tracker'!$L$6:$L$105,"<>Closed",'Follow-up Tracker'!$L$6:$L$105,"<>Risk accepted",'Follow-up Tracker'!$N$6:$N$105,"Yes") -> 2
B23: Reassessment due | C23: =IF('Vendor Profile'!C29="","",'Vendor Profile'!C29) -> 46680
B25: Red = needs action. The workbook ships with a worked example for a fictional vendor; the figures above are calculated from it until you clear the yellow cells.

Sheet Vendor Profile
B1: Vendor Profile
B2: By John Bommeraveni Joseph | linkedin.com/in/john-bj | Free every weekday: GRC Made Simple Daily
B5: Field | C5: Value | D5: Guidance
B6: Vendor (legal entity) | C6: Example Vendor Ltd (fictional) | D6: The contracting entity, not the brand.
B7: Product / service and plan assessed | C7: Example Support Copilot - Enterprise plan | D7: Terms often differ by plan; record the one you will buy.
B8: AI features in scope | C8: Drafts replies to customer tickets; searches our knowledge base; can update ticket fields | D8: List each AI feature you will switch on. Features left off should stay off by contract or setting.
B9: Our use case and business owner | C9: Customer support - Head of Customer Service | D9: What the business will use it for, and who owns that decision.
B10: Underlying model provider(s) | C10: Third-party hosted LLM API (named in sub-processor list v14) | D10: Every model provider behind the product, including fallbacks (see RES-01).
B11: Hosting and model arrangement | C11: Vendor-hosted, third-party model API
B12: Processing regions (storage and inference) | C12: EU storage; inference EU and US | D12: Where data is stored and where the model runs.
B13: Data categories shared | C13: Customer names, emails, order history, ticket text; internal KB articles | D13: Be specific: this drives the tier and the privacy questions.
B14: Personal data shared? | C14: Yes
B15: Special-category or sensitive personal data shared? | C15: No | D15: Health, biometric, financial account, children's data and similar.
B16: Confidential business data, IP or source code shared? | C16: Yes
B17: Outputs used to make or support decisions about people? | C17: No | D17: Eligibility, hiring, credit, access to services.
B18: Can the AI take actions in our systems (tools / agents)? | C18: Yes | D18: Write, send, delete or execute - not just read.
B19: Our EU AI Act role for this use | C19: Deployer | D19: Check Art. 25 before branding, fine-tuning or repurposing it.
B20: Suggested minimum tier (calculated) | C20: =IF(C14="","",IF(OR(C15="Yes",C17="Yes"),"Tier 1 - Critical",IF(OR(C14="Yes",C18="Yes"),"Tier 2 - High","Tier 3 - Moderate"))) -> Tier 2 - High | D20: Tier 1 if sensitive data or decisions about people; Tier 2 if personal data or actions in our systems; otherwise Tier 3.
B21: Criticality tier (your decision) | C21: Tier 2 - High | D21: Set by the business owner with risk; record the reason if below the suggestion.
B22: Tier check (calculated) | C22: =IF(OR(C21="",C20=""),"Set the tier",IF(VALUE(MID(C21,6,1))>VALUE(MID(C20,6,1)),"Below suggested tier - record the justification","OK")) -> OK
B23: Reviewer (GRC / security) | C23: A. Reviewer
B24: Approver | C24: Head of Third-Party Risk | D24: Someone independent of the business owner.
B25: Questionnaire sent | C25: 46280
B26: Response received | C26: 46301
B27: Vendor response time, days (calculated) | C27: =IF(OR(C25="",C26=""),"",C26-C25) -> 21
B28: Review completed | C28: 46315
B29: Reassessment due (calculated) | C29: =IF(OR(C28="",C21=""),"",IFERROR(DATE(YEAR(C28),MONTH(C28)+INDEX($C$32:$C$35,MATCH(C21,$B$32:$B$35,0)),DAY(C28)),"")) -> 46680 | D29: Review completed + the interval for the tier (table below), or sooner on any material change.
B31: Reassessment interval by tier (months) - edit to match your policy
B32: Tier 1 - Critical | C32: 12
B33: Tier 2 - High | C33: 12
B34: Tier 3 - Moderate | C34: 24
B35: Tier 4 - Low | C35: 36

Sheet Questionnaire
B1: AI Vendor Questionnaire
B2: By John Bommeraveni Joseph | linkedin.com/in/john-bj | Free every weekday: GRC Made Simple Daily
A5: ID | B5: Section | C5: Question | D5: Why it matters | E5: What good evidence looks like | F5: Vendor answer | G5: Evidence reference | H5: Reviewer score 0-3 | I5: Weight 1-3 | J5: Critical? | K5: Weighted score | L5: Max possible | M5: Red flag | N5: Check | O5: Reviewer notes
A6: 1. Training and model improvement
A7: TRN-01 | B7: 1. Training and model improvement | C7: Does the signed contract (not only the privacy policy or a web page) state that our inputs, outputs and files are not used to train, fine-tune or improve any model - the vendor's or its model provider's? | D7: Web-page promises can change without notice; only a contract term binds the vendor. | E7: Clause reference in the MSA, DPA or AI addendum, with document version and date. | F7: Yes | G7: AI Addendum v2.1 cl. 4.2 | H7: 3 | I7: 3 | J7: Yes | K7: =IF(OR(A7="",F7="N/A",H7=""),"",H7*I7) -> 9 | L7: =IF(OR(A7="",F7="N/A",H7=""),"",3*I7) -> 9 | M7: =IF(AND(J7="Yes",OR(F7="No",AND(F7<>"N/A",H7<>"",N(H7)<=1))),"RED FLAG","") | N7: =IF(A7="","",IF(F7="","Awaiting answer",IF(AND(F7<>"N/A",H7=""),"Score it",IF(AND(OR(F7="Yes",F7="Partial"),G7=""),"Evidence missing",IF(AND(F7="N/A",J7="Yes"),"Critical N/A - justify",IF(AND(F7="Yes",H7<>"",N(H7)<=1),"Claim not supported","OK")))))) -> OK
A8: TRN-02 | B8: 1. Training and model improvement | C8: Is 'no training on customer data' the default for our plan, or does it depend on an opt-out setting that an admin must switch on? | D8: Opt-out defaults are easily missed, and new workspaces may start with the setting on. | E8: Plan documentation plus a screenshot of the admin setting showing its default state. | F8: Yes | G8: Admin guide p.12; screenshot SS-01 | H8: 3 | I8: 2 | J8: No | K8: =IF(OR(A8="",F8="N/A",H8=""),"",H8*I8) -> 6 | L8: =IF(OR(A8="",F8="N/A",H8=""),"",3*I8) -> 6 | M8: =IF(AND(J8="Yes",OR(F8="No",AND(F8<>"N/A",H8<>"",N(H8)<=1))),"RED FLAG","") | N8: =IF(A8="","",IF(F8="","Awaiting answer",IF(AND(F8<>"N/A",H8=""),"Score it",IF(AND(OR(F8="Yes",F8="Partial"),G8=""),"Evidence missing",IF(AND(F8="N/A",J8="Yes"),"Critical N/A - justify",IF(AND(F8="Yes",H8<>"",N(H8)<=1),"Claim not supported","OK")))))) -> OK
A9: TRN-03 | B9: 1. Training and model improvement | C9: If data is used for 'service improvement' or abuse monitoring, who reviews it (people or systems), where are reviewers located, and can we opt out of human review? | D9: Your prompts can be read by people even when no model is trained on them. | E9: Written description of the review process, reviewer locations, access controls and opt-out route. | F9: Partial | G9: Trust portal FAQ 3.4 | H9: 2 | I9: 2 | J9: No | K9: =IF(OR(A9="",F9="N/A",H9=""),"",H9*I9) -> 4 | L9: =IF(OR(A9="",F9="N/A",H9=""),"",3*I9) -> 6 | M9: =IF(AND(J9="Yes",OR(F9="No",AND(F9<>"N/A",H9<>"",N(H9)<=1))),"RED FLAG","") | N9: =IF(A9="","",IF(F9="","Awaiting answer",IF(AND(F9<>"N/A",H9=""),"Score it",IF(AND(OR(F9="Yes",F9="Partial"),G9=""),"Evidence missing",IF(AND(F9="N/A",J9="Yes"),"Critical N/A - justify",IF(AND(F9="Yes",H9<>"",N(H9)<=1),"Claim not supported","OK")))))) -> OK
A10: TRN-04 | B10: 1. Training and model improvement | C10: Does the no-training commitment flow down in writing to every model provider and sub-processor that receives our data? | D10: The vendor's promise is worth little if the model provider behind it can use the data. | E10: Model provider's enterprise or API data terms, or the vendor's flow-down clause. | F10: Yes | G10: Sub-processor terms summary SP-2 | H10: 2 | I10: 3 | J10: Yes | K10: =IF(OR(A10="",F10="N/A",H10=""),"",H10*I10) -> 6 | L10: =IF(OR(A10="",F10="N/A",H10=""),"",3*I10) -> 9 | M10: =IF(AND(J10="Yes",OR(F10="No",AND(F10<>"N/A",H10<>"",N(H10)<=1))),"RED FLAG","") | N10: =IF(A10="","",IF(F10="","Awaiting answer",IF(AND(F10<>"N/A",H10=""),"Score it",IF(AND(OR(F10="Yes",F10="Partial"),G10=""),"Evidence missing",IF(AND(F10="N/A",J10="Yes"),"Critical N/A - justify",IF(AND(F10="Yes",H10<>"",N(H10)<=1),"Claim not supported","OK")))))) -> OK
A11: TRN-05 | B11: 1. Training and model improvement | C11: How are derived data - telemetry, embeddings, feedback ratings, aggregated or de-identified data - defined in the contract, and may the vendor keep or use them? | D11: Derived data is often excluded from the contract definition of 'customer data'. | E11: Contract definitions of Customer Data and Usage Data, and the permitted uses of each. | F11: Partial | G11: MSA cl. 1 definitions | H11: 1 | I11: 2 | J11: No | K11: =IF(OR(A11="",F11="N/A",H11=""),"",H11*I11) -> 2 | L11: =IF(OR(A11="",F11="N/A",H11=""),"",3*I11) -> 6 | M11: =IF(AND(J11="Yes",OR(F11="No",AND(F11<>"N/A",H11<>"",N(H11)<=1))),"RED FLAG","") | N11: =IF(A11="","",IF(F11="","Awaiting answer",IF(AND(F11<>"N/A",H11=""),"Score it",IF(AND(OR(F11="Yes",F11="Partial"),G11=""),"Evidence missing",IF(AND(F11="N/A",J11="Yes"),"Critical N/A - justify",IF(AND(F11="Yes",H11<>"",N(H11)<=1),"Claim not supported","OK")))))) -> OK
A12: 2. Retention of prompts, outputs and logs
A13: RET-01 | B13: 2. Retention of prompts, outputs and logs | C13: List the retention period separately for prompts, outputs, uploaded files, conversation history, embeddings or vector stores, caches and backups. | D13: Each data type usually lives in a different store with its own deletion clock. | E13: A retention schedule by data type, referenced in the DPA or security documentation. | F13: Yes | G13: Retention schedule RS-2026 | H13: 2 | I13: 3 | J13: No | K13: =IF(OR(A13="",F13="N/A",H13=""),"",H13*I13) -> 6 | L13: =IF(OR(A13="",F13="N/A",H13=""),"",3*I13) -> 9 | M13: =IF(AND(J13="Yes",OR(F13="No",AND(F13<>"N/A",H13<>"",N(H13)<=1))),"RED FLAG","") | N13: =IF(A13="","",IF(F13="","Awaiting answer",IF(AND(F13<>"N/A",H13=""),"Score it",IF(AND(OR(F13="Yes",F13="Partial"),G13=""),"Evidence missing",IF(AND(F13="N/A",J13="Yes"),"Critical N/A - justify",IF(AND(F13="Yes",H13<>"",N(H13)<=1),"Claim not supported","OK")))))) -> OK
A14: RET-02 | B14: 2. Retention of prompts, outputs and logs | C14: Does the model provider keep prompts or outputs (for example for abuse monitoring), for how long, and is a zero-data-retention or equivalent arrangement contracted for our tenant? | D14: Provider-side retention creates a second copy of your data that you do not control. | E14: Model provider retention terms and written confirmation of the arrangement that applies to us. | F14: Partial | G14: Vendor letter ZDR-03 (pending countersign) | H14: 2 | I14: 3 | J14: Yes | K14: =IF(OR(A14="",F14="N/A",H14=""),"",H14*I14) -> 6 | L14: =IF(OR(A14="",F14="N/A",H14=""),"",3*I14) -> 9 | M14: =IF(AND(J14="Yes",OR(F14="No",AND(F14<>"N/A",H14<>"",N(H14)<=1))),"RED FLAG","") | N14: =IF(A14="","",IF(F14="","Awaiting answer",IF(AND(F14<>"N/A",H14=""),"Score it",IF(AND(OR(F14="Yes",F14="Partial"),G14=""),"Evidence missing",IF(AND(F14="N/A",J14="Yes"),"Critical N/A - justify",IF(AND(F14="Yes",H14<>"",N(H14)<=1),"Claim not supported","OK")))))) -> OK
A15: RET-03 | B15: 2. Retention of prompts, outputs and logs | C15: Can our admins set retention and delete individual conversations or all data on demand, and within what period are backups purged? | D15: You need to act on deletion requests and your own retention rules without raising a ticket. | E15: Admin console documentation and a stated deletion period that includes backups. | F15: Yes | G15: Admin guide p.20 | H15: 3 | I15: 2 | J15: No | K15: =IF(OR(A15="",F15="N/A",H15=""),"",H15*I15) -> 6 | L15: =IF(OR(A15="",F15="N/A",H15=""),"",3*I15) -> 6 | M15: =IF(AND(J15="Yes",OR(F15="No",AND(F15<>"N/A",H15<>"",N(H15)<=1))),"RED FLAG","") | N15: =IF(A15="","",IF(F15="","Awaiting answer",IF(AND(F15<>"N/A",H15=""),"Score it",IF(AND(OR(F15="Yes",F15="Partial"),G15=""),"Evidence missing",IF(AND(F15="N/A",J15="Yes"),"Critical N/A - justify",IF(AND(F15="Yes",H15<>"",N(H15)<=1),"Claim not supported","OK")))))) -> OK
A16: RET-04 | B16: 2. Retention of prompts, outputs and logs | C16: Do prompts or outputs appear in the vendor's application logs, debugging tools or third-party observability services, and how are they redacted and retained there? | D16: Operational logs are where prompt content often stays longest and least controlled. | E16: Logging data-flow description, redaction approach, and the observability vendor on the sub-processor list. | F16: Partial | G16: Security whitepaper s.6 | H16: 1 | I16: 2 | J16: No | K16: =IF(OR(A16="",F16="N/A",H16=""),"",H16*I16) -> 2 | L16: =IF(OR(A16="",F16="N/A",H16=""),"",3*I16) -> 6 | M16: =IF(AND(J16="Yes",OR(F16="No",AND(F16<>"N/A",H16<>"",N(H16)<=1))),"RED FLAG","") | N16: =IF(A16="","",IF(F16="","Awaiting answer",IF(AND(F16<>"N/A",H16=""),"Score it",IF(AND(OR(F16="Yes",F16="Partial"),G16=""),"Evidence missing",IF(AND(F16="N/A",J16="Yes"),"Critical N/A - justify",IF(AND(F16="Yes",H16<>"",N(H16)<=1),"Claim not supported","OK")))))) -> OK
A17: RET-05 | B17: 2. Retention of prompts, outputs and logs | C17: Are cached copies (prompt caching, semantic caches, search indexes) covered by the same retention and deletion commitments? | D17: Caches and indexes are easily left out of deletion processes. | E17: Statement that caches are in scope of the retention schedule, with their time-to-live. | F17: Yes | G17: Retention schedule RS-2026 row 9 | H17: 2 | I17: 1 | J17: No | K17: =IF(OR(A17="",F17="N/A",H17=""),"",H17*I17) -> 2 | L17: =IF(OR(A17="",F17="N/A",H17=""),"",3*I17) -> 3 | M17: =IF(AND(J17="Yes",OR(F17="No",AND(F17<>"N/A",H17<>"",N(H17)<=1))),"RED FLAG","") | N17: =IF(A17="","",IF(F17="","Awaiting answer",IF(AND(F17<>"N/A",H17=""),"Score it",IF(AND(OR(F17="Yes",F17="Partial"),G17=""),"Evidence missing",IF(AND(F17="N/A",J17="Yes"),"Critical N/A - justify",IF(AND(F17="Yes",H17<>"",N(H17)<=1),"Claim not supported","OK")))))) -> OK
A18: 3. Data residency and sub-processors (including the model provider)
A19: RES-01 | B19: 3. Data residency and sub-processors (including the model provider) | C19: Name every model provider behind the product, per feature, including any fallback or routing providers used when the primary is unavailable. | D19: The model provider is your fourth party and receives your data; a hidden fallback is a hidden transfer. | E19: Sub-processor list naming each model provider, its purpose, data processed and region. | F19: Yes | G19: Sub-processor list v14 | H19: 3 | I19: 3 | J19: Yes | K19: =IF(OR(A19="",F19="N/A",H19=""),"",H19*I19) -> 9 | L19: =IF(OR(A19="",F19="N/A",H19=""),"",3*I19) -> 9 | M19: =IF(AND(J19="Yes",OR(F19="No",AND(F19<>"N/A",H19<>"",N(H19)<=1))),"RED FLAG","") | N19: =IF(A19="","",IF(F19="","Awaiting answer",IF(AND(F19<>"N/A",H19=""),"Score it",IF(AND(OR(F19="Yes",F19="Partial"),G19=""),"Evidence missing",IF(AND(F19="N/A",J19="Yes"),"Critical N/A - justify",IF(AND(F19="Yes",H19<>"",N(H19)<=1),"Claim not supported","OK")))))) -> OK
A20: RES-02 | B20: 3. Data residency and sub-processors (including the model provider) | C20: In which countries or regions is our data stored and processed - including model inference, support access and backups - and can we contractually pin it to a region? | D20: Inference and support often run outside the region where data is stored. | E20: Region documentation per data type and processing step, plus a residency clause in the contract. | F20: Partial | G20: Data residency page; no clause yet | H20: 2 | I20: 3 | J20: No | K20: =IF(OR(A20="",F20="N/A",H20=""),"",H20*I20) -> 6 | L20: =IF(OR(A20="",F20="N/A",H20=""),"",3*I20) -> 9 | M20: =IF(AND(J20="Yes",OR(F20="No",AND(F20<>"N/A",H20<>"",N(H20)<=1))),"RED FLAG","") | N20: =IF(A20="","",IF(F20="","Awaiting answer",IF(AND(F20<>"N/A",H20=""),"Score it",IF(AND(OR(F20="Yes",F20="Partial"),G20=""),"Evidence missing",IF(AND(F20="N/A",J20="Yes"),"Critical N/A - justify",IF(AND(F20="Yes",H20<>"",N(H20)<=1),"Claim not supported","OK")))))) -> OK
A21: RES-03 | B21: 3. Data residency and sub-processors (including the model provider) | C21: What transfer mechanism covers each cross-border transfer of personal data (for example standard contractual clauses with a transfer assessment, or an adequacy route)? | D21: Personal data sent abroad needs a lawful transfer mechanism under GDPR and similar laws. | E21: DPA transfer annex, the executed clauses, and a summary of the transfer risk assessment. | F21: Yes | G21: DPA Annex III | H21: 3 | I21: 2 | J21: No | K21: =IF(OR(A21="",F21="N/A",H21=""),"",H21*I21) -> 6 | L21: =IF(OR(A21="",F21="N/A",H21=""),"",3*I21) -> 6 | M21: =IF(AND(J21="Yes",OR(F21="No",AND(F21<>"N/A",H21<>"",N(H21)<=1))),"RED FLAG","") | N21: =IF(A21="","",IF(F21="","Awaiting answer",IF(AND(F21<>"N/A",H21=""),"Score it",IF(AND(OR(F21="Yes",F21="Partial"),G21=""),"Evidence missing",IF(AND(F21="N/A",J21="Yes"),"Critical N/A - justify",IF(AND(F21="Yes",H21<>"",N(H21)<=1),"Claim not supported","OK")))))) -> OK
A22: RES-04 | B22: 3. Data residency and sub-processors (including the model provider) | C22: Will we receive advance written notice of a new sub-processor, including a new or changed model provider, with a right to object or terminate? | D22: A model provider switch changes where your data goes and how outputs behave. | E22: DPA clause stating the notice period, notification channel and objection right. | F22: Yes | G22: DPA cl. 9.2 (30 days) | H22: 3 | I22: 3 | J22: No | K22: =IF(OR(A22="",F22="N/A",H22=""),"",H22*I22) -> 9 | L22: =IF(OR(A22="",F22="N/A",H22=""),"",3*I22) -> 9 | M22: =IF(AND(J22="Yes",OR(F22="No",AND(F22<>"N/A",H22<>"",N(H22)<=1))),"RED FLAG","") | N22: =IF(A22="","",IF(F22="","Awaiting answer",IF(AND(F22<>"N/A",H22=""),"Score it",IF(AND(OR(F22="Yes",F22="Partial"),G22=""),"Evidence missing",IF(AND(F22="N/A",J22="Yes"),"Critical N/A - justify",IF(AND(F22="Yes",H22<>"",N(H22)<=1),"Claim not supported","OK")))))) -> OK
A23: RES-05 | B23: 3. Data residency and sub-processors (including the model provider) | C23: How does the vendor assess and monitor its own sub-processors, and are they bound by terms at least as protective as ours? | D23: Your risk extends to every party the vendor relies on. | E23: Vendor's third-party risk procedure and evidence of flow-down terms. | F23: Partial | G23: TPRM procedure summary | H23: 2 | I23: 2 | J23: No | K23: =IF(OR(A23="",F23="N/A",H23=""),"",H23*I23) -> 4 | L23: =IF(OR(A23="",F23="N/A",H23=""),"",3*I23) -> 6 | M23: =IF(AND(J23="Yes",OR(F23="No",AND(F23<>"N/A",H23<>"",N(H23)<=1))),"RED FLAG","") | N23: =IF(A23="","",IF(F23="","Awaiting answer",IF(AND(F23<>"N/A",H23=""),"Score it",IF(AND(OR(F23="Yes",F23="Partial"),G23=""),"Evidence missing",IF(AND(F23="N/A",J23="Yes"),"Critical N/A - justify",IF(AND(F23="Yes",H23<>"",N(H23)<=1),"Claim not supported","OK")))))) -> OK
A24: 4. Security controls and certifications
A25: SEC-01 | B25: 4. Security controls and certifications | C25: Is there at least one current independent assurance - an ISO/IEC 27001 certificate or a SOC 2 Type II report - whose scope explicitly includes this AI product and its hosting? | D25: A logo on a website proves nothing if the AI product sits outside the audited scope. | E25: Certificate or report with the scope statement or system description naming the product. | F25: Yes | G25: SOC 2 Type II report (2025-10 to 2026-09) | H25: 3 | I25: 3 | J25: Yes | K25: =IF(OR(A25="",F25="N/A",H25=""),"",H25*I25) -> 9 | L25: =IF(OR(A25="",F25="N/A",H25=""),"",3*I25) -> 9 | M25: =IF(AND(J25="Yes",OR(F25="No",AND(F25<>"N/A",H25<>"",N(H25)<=1))),"RED FLAG","") | N25: =IF(A25="","",IF(F25="","Awaiting answer",IF(AND(F25<>"N/A",H25=""),"Score it",IF(AND(OR(F25="Yes",F25="Partial"),G25=""),"Evidence missing",IF(AND(F25="N/A",J25="Yes"),"Critical N/A - justify",IF(AND(F25="Yes",H25<>"",N(H25)<=1),"Claim not supported","OK")))))) -> OK
A26: SEC-02 | B26: 4. Security controls and certifications | C26: ISO/IEC 27001: provide the certificate number, certification body, accreditation, expiry date and scope statement. Does the Statement of Applicability cover the AI services? | D26: Scope and accreditation decide whether the certificate is relevant and verifiable. | E26: Certificate plus scope, checked on the certification body's or accreditation register. | F26: Yes | G26: Cert no. on CB register, checked 2026-10-14 | H26: 3 | I26: 2 | J26: No | K26: =IF(OR(A26="",F26="N/A",H26=""),"",H26*I26) -> 6 | L26: =IF(OR(A26="",F26="N/A",H26=""),"",3*I26) -> 6 | M26: =IF(AND(J26="Yes",OR(F26="No",AND(F26<>"N/A",H26<>"",N(H26)<=1))),"RED FLAG","") | N26: =IF(A26="","",IF(F26="","Awaiting answer",IF(AND(F26<>"N/A",H26=""),"Score it",IF(AND(OR(F26="Yes",F26="Partial"),G26=""),"Evidence missing",IF(AND(F26="N/A",J26="Yes"),"Critical N/A - justify",IF(AND(F26="Yes",H26<>"",N(H26)<=1),"Claim not supported","OK")))))) -> OK
A27: SEC-03 | B27: 4. Security controls and certifications | C27: SOC 2 Type II: what is the report period, which Trust Services Criteria are covered, is the model provider carved out or included, and were there exceptions or a qualified opinion? | D27: Ask for scope and period, not the logo; carve-outs move testing back onto you. | E27: Full report under NDA, the list of complementary user entity controls, and a bridge letter for any gap since period end. | F27: Partial | G27: SOC 2 report s.3; model provider carved out | H27: 2 | I27: 3 | J27: No | K27: =IF(OR(A27="",F27="N/A",H27=""),"",H27*I27) -> 6 | L27: =IF(OR(A27="",F27="N/A",H27=""),"",3*I27) -> 9 | M27: =IF(AND(J27="Yes",OR(F27="No",AND(F27<>"N/A",H27<>"",N(H27)<=1))),"RED FLAG","") | N27: =IF(A27="","",IF(F27="","Awaiting answer",IF(AND(F27<>"N/A",H27=""),"Score it",IF(AND(OR(F27="Yes",F27="Partial"),G27=""),"Evidence missing",IF(AND(F27="N/A",J27="Yes"),"Critical N/A - justify",IF(AND(F27="Yes",H27<>"",N(H27)<=1),"Claim not supported","OK")))))) -> OK
A28: SEC-04 | B28: 4. Security controls and certifications | C28: Does the vendor hold, or plan, ISO/IEC 42001 certification for its AI management system? Give scope, certification body and status. | D28: Shows AI governance is run as a managed system, not only IT security. | E28: Certificate and scope, or a roadmap with a target date and the chosen certification body. | F28: Partial | G28: Roadmap slide: target 2027 | H28: 1 | I28: 2 | J28: No | K28: =IF(OR(A28="",F28="N/A",H28=""),"",H28*I28) -> 2 | L28: =IF(OR(A28="",F28="N/A",H28=""),"",3*I28) -> 6 | M28: =IF(AND(J28="Yes",OR(F28="No",AND(F28<>"N/A",H28<>"",N(H28)<=1))),"RED FLAG","") | N28: =IF(A28="","",IF(F28="","Awaiting answer",IF(AND(F28<>"N/A",H28=""),"Score it",IF(AND(OR(F28="Yes",F28="Partial"),G28=""),"Evidence missing",IF(AND(F28="N/A",J28="Yes"),"Critical N/A - justify",IF(AND(F28="Yes",H28<>"",N(H28)<=1),"Claim not supported","OK")))))) -> OK
A29: SEC-05 | B29: 4. Security controls and certifications | C29: How are our prompts, context, files, vector stores and any fine-tuned models isolated from other customers' data? | D29: Weak tenant isolation in AI pipelines can expose one customer's data in another's answers. | E29: Architecture description of tenant isolation and test evidence (for example penetration test scope). | F29: Yes | G29: Architecture doc A-4; pen test 2026-06 | H29: 2 | I29: 3 | J29: Yes | K29: =IF(OR(A29="",F29="N/A",H29=""),"",H29*I29) -> 6 | L29: =IF(OR(A29="",F29="N/A",H29=""),"",3*I29) -> 9 | M29: =IF(AND(J29="Yes",OR(F29="No",AND(F29<>"N/A",H29<>"",N(H29)<=1))),"RED FLAG","") | N29: =IF(A29="","",IF(F29="","Awaiting answer",IF(AND(F29<>"N/A",H29=""),"Score it",IF(AND(OR(F29="Yes",F29="Partial"),G29=""),"Evidence missing",IF(AND(F29="N/A",J29="Yes"),"Critical N/A - justify",IF(AND(F29="Yes",H29<>"",N(H29)<=1),"Claim not supported","OK")))))) -> OK
A30: SEC-06 | B30: 4. Security controls and certifications | C30: Do the AI features support SSO, MFA, SCIM provisioning and role-based access, so we control who can use which AI capability? | D30: AI features that bypass your identity controls become an unmanaged access path. | E30: Admin documentation and a demonstration of role settings for AI features. | F30: Yes | G30: Admin guide p.5 | H30: 3 | I30: 2 | J30: No | K30: =IF(OR(A30="",F30="N/A",H30=""),"",H30*I30) -> 6 | L30: =IF(OR(A30="",F30="N/A",H30=""),"",3*I30) -> 6 | M30: =IF(AND(J30="Yes",OR(F30="No",AND(F30<>"N/A",H30<>"",N(H30)<=1))),"RED FLAG","") | N30: =IF(A30="","",IF(F30="","Awaiting answer",IF(AND(F30<>"N/A",H30=""),"Score it",IF(AND(OR(F30="Yes",F30="Partial"),G30=""),"Evidence missing",IF(AND(F30="N/A",J30="Yes"),"Critical N/A - justify",IF(AND(F30="Yes",H30<>"",N(H30)<=1),"Claim not supported","OK")))))) -> OK
A31: SEC-07 | B31: 4. Security controls and certifications | C31: How is our data encrypted in transit and at rest across the AI pipeline (including vector stores and the model provider), and is customer-managed key support available? | D31: Data copied into new AI stores often misses the encryption applied to the main database. | E31: Encryption and key management description covering every AI data store. | F31: Yes | G31: Security whitepaper s.4 | H31: 2 | I31: 2 | J31: No | K31: =IF(OR(A31="",F31="N/A",H31=""),"",H31*I31) -> 4 | L31: =IF(OR(A31="",F31="N/A",H31=""),"",3*I31) -> 6 | M31: =IF(AND(J31="Yes",OR(F31="No",AND(F31<>"N/A",H31<>"",N(H31)<=1))),"RED FLAG","") | N31: =IF(A31="","",IF(F31="","Awaiting answer",IF(AND(F31<>"N/A",H31=""),"Score it",IF(AND(OR(F31="Yes",F31="Partial"),G31=""),"Evidence missing",IF(AND(F31="N/A",J31="Yes"),"Critical N/A - justify",IF(AND(F31="Yes",H31<>"",N(H31)<=1),"Claim not supported","OK")))))) -> OK
A32: 5. Model change management
A33: CHG-01 | B33: 5. Model change management | C33: Will the vendor notify us in advance of changes to the underlying model, model version, provider, system prompt or safety settings that can change output behaviour - and with how much notice? | D33: Silent model updates can change accuracy, tone and safety overnight without any action by you. | E33: Contract change-notice clause with a notice period, plus a dated customer changelog. | F33: Partial | G33: Changelog only; no contract clause | H33: 1 | I33: 3 | J33: Yes | K33: =IF(OR(A33="",F33="N/A",H33=""),"",H33*I33) -> 3 | L33: =IF(OR(A33="",F33="N/A",H33=""),"",3*I33) -> 9 | M33: =IF(AND(J33="Yes",OR(F33="No",AND(F33<>"N/A",H33<>"",N(H33)<=1))),"RED FLAG","") -> RED FLAG | N33: =IF(A33="","",IF(F33="","Awaiting answer",IF(AND(F33<>"N/A",H33=""),"Score it",IF(AND(OR(F33="Yes",F33="Partial"),G33=""),"Evidence missing",IF(AND(F33="N/A",J33="Yes"),"Critical N/A - justify",IF(AND(F33="Yes",H33<>"",N(H33)<=1),"Claim not supported","OK")))))) -> OK
A34: CHG-02 | B34: 5. Model change management | C34: Can we pin a model version, and how long is a version supported before it is deprecated? | D34: Pinning lets you re-test before behaviour changes reach your users. | E34: Version support and deprecation policy with stated periods. | F34: No | G34: Not offered | H34: 1 | I34: 2 | J34: No | K34: =IF(OR(A34="",F34="N/A",H34=""),"",H34*I34) -> 2 | L34: =IF(OR(A34="",F34="N/A",H34=""),"",3*I34) -> 6 | M34: =IF(AND(J34="Yes",OR(F34="No",AND(F34<>"N/A",H34<>"",N(H34)<=1))),"RED FLAG","") | N34: =IF(A34="","",IF(F34="","Awaiting answer",IF(AND(F34<>"N/A",H34=""),"Score it",IF(AND(OR(F34="Yes",F34="Partial"),G34=""),"Evidence missing",IF(AND(F34="N/A",J34="Yes"),"Critical N/A - justify",IF(AND(F34="Yes",H34<>"",N(H34)<=1),"Claim not supported","OK")))))) -> OK
A35: CHG-03 | B35: 5. Model change management | C35: Does the vendor regression-test accuracy, safety and bias before releasing a model or prompt change, and will it share the results? | D35: Release testing is the vendor's main control against harmful changes. | E35: Release procedure and an example of a pre-release evaluation summary. | F35: Partial | G35: Release procedure summary | H35: 2 | I35: 3 | J35: No | K35: =IF(OR(A35="",F35="N/A",H35=""),"",H35*I35) -> 6 | L35: =IF(OR(A35="",F35="N/A",H35=""),"",3*I35) -> 9 | M35: =IF(AND(J35="Yes",OR(F35="No",AND(F35<>"N/A",H35<>"",N(H35)<=1))),"RED FLAG","") | N35: =IF(A35="","",IF(F35="","Awaiting answer",IF(AND(F35<>"N/A",H35=""),"Score it",IF(AND(OR(F35="Yes",F35="Partial"),G35=""),"Evidence missing",IF(AND(F35="N/A",J35="Yes"),"Critical N/A - justify",IF(AND(F35="Yes",H35<>"",N(H35)<=1),"Claim not supported","OK")))))) -> OK
A36: CHG-04 | B36: 5. Model change management | C36: Can we test a new model version in a sandbox or staging tenant before it reaches production users? | D36: Your own use-case testing catches failures the vendor's generic tests miss. | E36: Description of the preview or staging channel and its timing relative to release. | F36: Yes | G36: Preview channel, 14 days | H36: 2 | I36: 2 | J36: No | K36: =IF(OR(A36="",F36="N/A",H36=""),"",H36*I36) -> 4 | L36: =IF(OR(A36="",F36="N/A",H36=""),"",3*I36) -> 6 | M36: =IF(AND(J36="Yes",OR(F36="No",AND(F36<>"N/A",H36<>"",N(H36)<=1))),"RED FLAG","") | N36: =IF(A36="","",IF(F36="","Awaiting answer",IF(AND(F36<>"N/A",H36=""),"Score it",IF(AND(OR(F36="Yes",F36="Partial"),G36=""),"Evidence missing",IF(AND(F36="N/A",J36="Yes"),"Critical N/A - justify",IF(AND(F36="Yes",H36<>"",N(H36)<=1),"Claim not supported","OK")))))) -> OK
A37: CHG-05 | B37: 5. Model change management | C37: Can we roll back, or opt out of, a model change that degrades our use case? | D37: Without rollback, a bad update leaves you choosing between degraded output and switching it off. | E37: Rollback or opt-out mechanism and its time limits. | F37: No | G37: Not offered | H37: 0 | I37: 1 | J37: No | K37: =IF(OR(A37="",F37="N/A",H37=""),"",H37*I37) -> 0 | L37: =IF(OR(A37="",F37="N/A",H37=""),"",3*I37) -> 3 | M37: =IF(AND(J37="Yes",OR(F37="No",AND(F37<>"N/A",H37<>"",N(H37)<=1))),"RED FLAG","") | N37: =IF(A37="","",IF(F37="","Awaiting answer",IF(AND(F37<>"N/A",H37=""),"Score it",IF(AND(OR(F37="Yes",F37="Partial"),G37=""),"Evidence missing",IF(AND(F37="N/A",J37="Yes"),"Critical N/A - justify",IF(AND(F37="Yes",H37<>"",N(H37)<=1),"Claim not supported","OK")))))) -> OK
A38: 6. Evaluation and testing
A39: EVL-01 | B39: 6. Evaluation and testing | C39: How is accuracy or quality evaluated for our type of use case - methods, datasets, metrics and the latest results - and will you share them? | D39: Generic benchmark claims say little about performance on your tasks. | E39: Evaluation report with method, test data description, metrics and date. | F39: Partial | G39: Eval summary 2026-Q3 | H39: 2 | I39: 3 | J39: No | K39: =IF(OR(A39="",F39="N/A",H39=""),"",H39*I39) -> 6 | L39: =IF(OR(A39="",F39="N/A",H39=""),"",3*I39) -> 9 | M39: =IF(AND(J39="Yes",OR(F39="No",AND(F39<>"N/A",H39<>"",N(H39)<=1))),"RED FLAG","") | N39: =IF(A39="","",IF(F39="","Awaiting answer",IF(AND(F39<>"N/A",H39=""),"Score it",IF(AND(OR(F39="Yes",F39="Partial"),G39=""),"Evidence missing",IF(AND(F39="N/A",J39="Yes"),"Critical N/A - justify",IF(AND(F39="Yes",H39<>"",N(H39)<=1),"Claim not supported","OK")))))) -> OK
A40: EVL-02 | B40: 6. Evaluation and testing | C40: Has the system been tested for bias or unfair outcomes, which characteristics were tested, and what were the results? | D40: Matters most where outputs affect people's access to jobs, credit, services or support. | E40: Bias testing summary with method, characteristics, results and remediation. | F40: Partial | G40: Statement only | H40: 1 | I40: 2 | J40: No | K40: =IF(OR(A40="",F40="N/A",H40=""),"",H40*I40) -> 2 | L40: =IF(OR(A40="",F40="N/A",H40=""),"",3*I40) -> 6 | M40: =IF(AND(J40="Yes",OR(F40="No",AND(F40<>"N/A",H40<>"",N(H40)<=1))),"RED FLAG","") | N40: =IF(A40="","",IF(F40="","Awaiting answer",IF(AND(F40<>"N/A",H40=""),"Score it",IF(AND(OR(F40="Yes",F40="Partial"),G40=""),"Evidence missing",IF(AND(F40="N/A",J40="Yes"),"Critical N/A - justify",IF(AND(F40="Yes",H40<>"",N(H40)<=1),"Claim not supported","OK")))))) -> OK
A41: EVL-03 | B41: 6. Evaluation and testing | C41: Has independent red teaming or adversarial testing of the AI features been performed in the last 12 months, including sensitive-information disclosure and system-prompt leakage? Were high findings fixed? | D41: Adversarial testing finds abuse paths that functional testing does not. | E41: Tester identity, scope, date, finding counts by severity and remediation status. | F41: Yes | G41: Pen test 2026-06 incl. LLM scope | H41: 2 | I41: 3 | J41: No | K41: =IF(OR(A41="",F41="N/A",H41=""),"",H41*I41) -> 6 | L41: =IF(OR(A41="",F41="N/A",H41=""),"",3*I41) -> 9 | M41: =IF(AND(J41="Yes",OR(F41="No",AND(F41<>"N/A",H41<>"",N(H41)<=1))),"RED FLAG","") | N41: =IF(A41="","",IF(F41="","Awaiting answer",IF(AND(F41<>"N/A",H41=""),"Score it",IF(AND(OR(F41="Yes",F41="Partial"),G41=""),"Evidence missing",IF(AND(F41="N/A",J41="Yes"),"Critical N/A - justify",IF(AND(F41="Yes",H41<>"",N(H41)<=1),"Claim not supported","OK")))))) -> OK
A42: EVL-04 | B42: 6. Evaluation and testing | C42: Is the product tested against direct and indirect prompt injection - instructions hidden in documents, emails, web pages, tickets or tool outputs that the AI reads? | D42: Prompt injection (OWASP LLM01:2025) is the leading attack on AI features that read untrusted content. | E42: Test cases, results and the defences in place (input isolation, output checks, permission limits). | F42: Yes | G42: Pen test 2026-06 s.5 | H42: 2 | I42: 3 | J42: Yes | K42: =IF(OR(A42="",F42="N/A",H42=""),"",H42*I42) -> 6 | L42: =IF(OR(A42="",F42="N/A",H42=""),"",3*I42) -> 9 | M42: =IF(AND(J42="Yes",OR(F42="No",AND(F42<>"N/A",H42<>"",N(H42)<=1))),"RED FLAG","") | N42: =IF(A42="","",IF(F42="","Awaiting answer",IF(AND(F42<>"N/A",H42=""),"Score it",IF(AND(OR(F42="Yes",F42="Partial"),G42=""),"Evidence missing",IF(AND(F42="N/A",J42="Yes"),"Critical N/A - justify",IF(AND(F42="Yes",H42<>"",N(H42)<=1),"Claim not supported","OK")))))) -> OK
A43: EVL-05 | B43: 6. Evaluation and testing | C43: Is there published model or system documentation stating intended use, limitations, known failure modes and evaluation results? | D43: You cannot oversee a system whose limits you have not been told. | E43: Model card or system card for the version in use. | F43: Yes | G43: System card v3 | H43: 3 | I43: 2 | J43: No | K43: =IF(OR(A43="",F43="N/A",H43=""),"",H43*I43) -> 6 | L43: =IF(OR(A43="",F43="N/A",H43=""),"",3*I43) -> 6 | M43: =IF(AND(J43="Yes",OR(F43="No",AND(F43<>"N/A",H43<>"",N(H43)<=1))),"RED FLAG","") | N43: =IF(A43="","",IF(F43="","Awaiting answer",IF(AND(F43<>"N/A",H43=""),"Score it",IF(AND(OR(F43="Yes",F43="Partial"),G43=""),"Evidence missing",IF(AND(F43="N/A",J43="Yes"),"Critical N/A - justify",IF(AND(F43="Yes",H43<>"",N(H43)<=1),"Claim not supported","OK")))))) -> OK
A44: EVL-06 | B44: 6. Evaluation and testing | C44: Does the vendor monitor quality and drift in production, with thresholds that trigger investigation? | D44: Performance can degrade after release as data and usage change. | E44: Monitoring description, metrics, thresholds and an example alert or report. | F44: Partial | G44: Ops overview | H44: 2 | I44: 2 | J44: No | K44: =IF(OR(A44="",F44="N/A",H44=""),"",H44*I44) -> 4 | L44: =IF(OR(A44="",F44="N/A",H44=""),"",3*I44) -> 6 | M44: =IF(AND(J44="Yes",OR(F44="No",AND(F44<>"N/A",H44<>"",N(H44)<=1))),"RED FLAG","") | N44: =IF(A44="","",IF(F44="","Awaiting answer",IF(AND(F44<>"N/A",H44=""),"Score it",IF(AND(OR(F44="Yes",F44="Partial"),G44=""),"Evidence missing",IF(AND(F44="N/A",J44="Yes"),"Critical N/A - justify",IF(AND(F44="Yes",H44<>"",N(H44)<=1),"Claim not supported","OK")))))) -> OK
A45: 7. Agent and tool permissions (excessive agency)
A46: AGT-01 | B46: 7. Agent and tool permissions (excessive agency) | C46: List every tool, API, plugin or connector the AI can call, and every action it can take (read, create, update, delete, send, execute, pay). | D46: Excessive agency (OWASP LLM06:2025) starts with not knowing what the AI can do. | E46: Tool and permission inventory for the product as configured for us. | F46: Yes | G46: Connector matrix CM-1 | H46: 3 | I46: 3 | J46: Yes | K46: =IF(OR(A46="",F46="N/A",H46=""),"",H46*I46) -> 9 | L46: =IF(OR(A46="",F46="N/A",H46=""),"",3*I46) -> 9 | M46: =IF(AND(J46="Yes",OR(F46="No",AND(F46<>"N/A",H46<>"",N(H46)<=1))),"RED FLAG","") | N46: =IF(A46="","",IF(F46="","Awaiting answer",IF(AND(F46<>"N/A",H46=""),"Score it",IF(AND(OR(F46="Yes",F46="Partial"),G46=""),"Evidence missing",IF(AND(F46="N/A",J46="Yes"),"Critical N/A - justify",IF(AND(F46="Yes",H46<>"",N(H46)<=1),"Claim not supported","OK")))))) -> OK
A47: AGT-02 | B47: 7. Agent and tool permissions (excessive agency) | C47: Do tool calls run with the end user's own permissions (delegated, least privilege) rather than a broad service account, and are connector credentials scoped and revocable by us? | D47: A broad service account lets any user - or any injected instruction - reach data they should not. | E47: Authorisation design for tool calls and the OAuth scopes requested by each connector. | F47: Yes | G47: Architecture doc A-6 | H47: 2 | I47: 3 | J47: Yes | K47: =IF(OR(A47="",F47="N/A",H47=""),"",H47*I47) -> 6 | L47: =IF(OR(A47="",F47="N/A",H47=""),"",3*I47) -> 9 | M47: =IF(AND(J47="Yes",OR(F47="No",AND(F47<>"N/A",H47<>"",N(H47)<=1))),"RED FLAG","") | N47: =IF(A47="","",IF(F47="","Awaiting answer",IF(AND(F47<>"N/A",H47=""),"Score it",IF(AND(OR(F47="Yes",F47="Partial"),G47=""),"Evidence missing",IF(AND(F47="N/A",J47="Yes"),"Critical N/A - justify",IF(AND(F47="Yes",H47<>"",N(H47)<=1),"Claim not supported","OK")))))) -> OK
A48: AGT-03 | B48: 7. Agent and tool permissions (excessive agency) | C48: Can our admins enable, disable or restrict individual tools, connectors and actions per role or group? | D48: You need to grant capabilities deliberately rather than inherit the vendor's defaults. | E48: Admin console documentation and a demonstration. | F48: Yes | G48: Admin guide p.31 | H48: 3 | I48: 2 | J48: No | K48: =IF(OR(A48="",F48="N/A",H48=""),"",H48*I48) -> 6 | L48: =IF(OR(A48="",F48="N/A",H48=""),"",3*I48) -> 6 | M48: =IF(AND(J48="Yes",OR(F48="No",AND(F48<>"N/A",H48<>"",N(H48)<=1))),"RED FLAG","") | N48: =IF(A48="","",IF(F48="","Awaiting answer",IF(AND(F48<>"N/A",H48=""),"Score it",IF(AND(OR(F48="Yes",F48="Partial"),G48=""),"Evidence missing",IF(AND(F48="N/A",J48="Yes"),"Critical N/A - justify",IF(AND(F48="Yes",H48<>"",N(H48)<=1),"Claim not supported","OK")))))) -> OK
A49: AGT-04 | B49: 7. Agent and tool permissions (excessive agency) | C49: Do high-impact actions (sending externally, deleting, changing records, payments) require explicit human confirmation before they run? | D49: Confirmation is the last control between a wrong or manipulated output and a real-world action. | E49: Configuration showing which actions require confirmation, and whether we can extend the list. | F49: Yes | G49: Admin guide p.33 | H49: 3 | I49: 3 | J49: No | K49: =IF(OR(A49="",F49="N/A",H49=""),"",H49*I49) -> 9 | L49: =IF(OR(A49="",F49="N/A",H49=""),"",3*I49) -> 9 | M49: =IF(AND(J49="Yes",OR(F49="No",AND(F49<>"N/A",H49<>"",N(H49)<=1))),"RED FLAG","") | N49: =IF(A49="","",IF(F49="","Awaiting answer",IF(AND(F49<>"N/A",H49=""),"Score it",IF(AND(OR(F49="Yes",F49="Partial"),G49=""),"Evidence missing",IF(AND(F49="N/A",J49="Yes"),"Critical N/A - justify",IF(AND(F49="Yes",H49<>"",N(H49)<=1),"Claim not supported","OK")))))) -> OK
A50: AGT-05 | B50: 7. Agent and tool permissions (excessive agency) | C50: Are there limits on autonomous behaviour - maximum steps, rate and spend limits, timeouts? | D50: Unbounded consumption (OWASP LLM10:2025) turns loops and abuse into cost and availability incidents. | E50: Documented limits and whether we can configure them. | F50: Partial | G50: Rate limits documented | H50: 2 | I50: 1 | J50: No | K50: =IF(OR(A50="",F50="N/A",H50=""),"",H50*I50) -> 2 | L50: =IF(OR(A50="",F50="N/A",H50=""),"",3*I50) -> 3 | M50: =IF(AND(J50="Yes",OR(F50="No",AND(F50<>"N/A",H50<>"",N(H50)<=1))),"RED FLAG","") | N50: =IF(A50="","",IF(F50="","Awaiting answer",IF(AND(F50<>"N/A",H50=""),"Score it",IF(AND(OR(F50="Yes",F50="Partial"),G50=""),"Evidence missing",IF(AND(F50="N/A",J50="Yes"),"Critical N/A - justify",IF(AND(F50="Yes",H50<>"",N(H50)<=1),"Claim not supported","OK")))))) -> OK
A51: AGT-06 | B51: 7. Agent and tool permissions (excessive agency) | C51: In one session, can the AI hold our private data, read untrusted content and communicate externally? What stops data leaving through tool calls, links or rendered images? | D51: That combination lets an injected instruction exfiltrate data without any user noticing. | E51: Description of exfiltration defences (egress allow-lists, link and image rendering controls, approvals). | F51: Partial | G51: Security whitepaper s.8 | H51: 2 | I51: 3 | J51: No | K51: =IF(OR(A51="",F51="N/A",H51=""),"",H51*I51) -> 6 | L51: =IF(OR(A51="",F51="N/A",H51=""),"",3*I51) -> 9 | M51: =IF(AND(J51="Yes",OR(F51="No",AND(F51<>"N/A",H51<>"",N(H51)<=1))),"RED FLAG","") | N51: =IF(A51="","",IF(F51="","Awaiting answer",IF(AND(F51<>"N/A",H51=""),"Score it",IF(AND(OR(F51="Yes",F51="Partial"),G51=""),"Evidence missing",IF(AND(F51="N/A",J51="Yes"),"Critical N/A - justify",IF(AND(F51="Yes",H51<>"",N(H51)<=1),"Claim not supported","OK")))))) -> OK
A52: 8. Output handling and hallucination controls
A53: OUT-01 | B53: 8. Output handling and hallucination controls | C53: Are AI outputs treated as untrusted before they reach browsers, code, queries, shells or downstream systems (encoding, validation, sandboxing)? | D53: Improper output handling (OWASP LLM05:2025) turns a model output into an injection attack. | E53: Secure design description and test evidence for output encoding and validation. | F53: Yes | G53: Pen test 2026-06 s.6 | H53: 2 | I53: 3 | J53: No | K53: =IF(OR(A53="",F53="N/A",H53=""),"",H53*I53) -> 6 | L53: =IF(OR(A53="",F53="N/A",H53=""),"",3*I53) -> 9 | M53: =IF(AND(J53="Yes",OR(F53="No",AND(F53<>"N/A",H53<>"",N(H53)<=1))),"RED FLAG","") | N53: =IF(A53="","",IF(F53="","Awaiting answer",IF(AND(F53<>"N/A",H53=""),"Score it",IF(AND(OR(F53="Yes",F53="Partial"),G53=""),"Evidence missing",IF(AND(F53="N/A",J53="Yes"),"Critical N/A - justify",IF(AND(F53="Yes",H53<>"",N(H53)<=1),"Claim not supported","OK")))))) -> OK
A54: OUT-02 | B54: 8. Output handling and hallucination controls | C54: Does the product show the sources behind an answer (retrieval references) so users can verify it? | D54: Citations let users check an answer instead of trusting it. | E54: Product demonstration showing source references. | F54: Yes | G54: Demo 2026-10-09 | H54: 3 | I54: 2 | J54: No | K54: =IF(OR(A54="",F54="N/A",H54=""),"",H54*I54) -> 6 | L54: =IF(OR(A54="",F54="N/A",H54=""),"",3*I54) -> 6 | M54: =IF(AND(J54="Yes",OR(F54="No",AND(F54<>"N/A",H54<>"",N(H54)<=1))),"RED FLAG","") | N54: =IF(A54="","",IF(F54="","Awaiting answer",IF(AND(F54<>"N/A",H54=""),"Score it",IF(AND(OR(F54="Yes",F54="Partial"),G54=""),"Evidence missing",IF(AND(F54="N/A",J54="Yes"),"Critical N/A - justify",IF(AND(F54="Yes",H54<>"",N(H54)<=1),"Claim not supported","OK")))))) -> OK
A55: OUT-03 | B55: 8. Output handling and hallucination controls | C55: What controls reduce fabricated or incorrect output (grounding, refusing when unsupported, confidence cues), and how is their effectiveness measured? | D55: Misinformation (OWASP LLM09:2025) causes harm when users act on confident but wrong output. | E55: Description of controls and the metric used to track them. | F55: Partial | G55: Statement only | H55: 1 | I55: 2 | J55: No | K55: =IF(OR(A55="",F55="N/A",H55=""),"",H55*I55) -> 2 | L55: =IF(OR(A55="",F55="N/A",H55=""),"",3*I55) -> 6 | M55: =IF(AND(J55="Yes",OR(F55="No",AND(F55<>"N/A",H55<>"",N(H55)<=1))),"RED FLAG","") | N55: =IF(A55="","",IF(F55="","Awaiting answer",IF(AND(F55<>"N/A",H55=""),"Score it",IF(AND(OR(F55="Yes",F55="Partial"),G55=""),"Evidence missing",IF(AND(F55="N/A",J55="Yes"),"Critical N/A - justify",IF(AND(F55="Yes",H55<>"",N(H55)<=1),"Claim not supported","OK")))))) -> OK
A56: OUT-04 | B56: 8. Output handling and hallucination controls | C56: Are there input and output safety filters, and can we configure them for our context? | D56: Default filters may be too weak - or too strict - for your users and content. | E56: Filter documentation and available configuration options. | F56: Yes | G56: Admin guide p.40 | H56: 2 | I56: 2 | J56: No | K56: =IF(OR(A56="",F56="N/A",H56=""),"",H56*I56) -> 4 | L56: =IF(OR(A56="",F56="N/A",H56=""),"",3*I56) -> 6 | M56: =IF(AND(J56="Yes",OR(F56="No",AND(F56<>"N/A",H56<>"",N(H56)<=1))),"RED FLAG","") | N56: =IF(A56="","",IF(F56="","Awaiting answer",IF(AND(F56<>"N/A",H56=""),"Score it",IF(AND(OR(F56="Yes",F56="Partial"),G56=""),"Evidence missing",IF(AND(F56="N/A",J56="Yes"),"Critical N/A - justify",IF(AND(F56="Yes",H56<>"",N(H56)<=1),"Claim not supported","OK")))))) -> OK
A57: OUT-05 | B57: 8. Output handling and hallucination controls | C57: Does retrieval respect the permissions on source documents, so users only receive content they are entitled to see? | D57: Vector and embedding weaknesses (OWASP LLM08:2025) can expose restricted documents through answers. | E57: Design showing permission checks at retrieval time, plus test results. | F57: Yes | G57: Architecture doc A-7; test TR-12 | H57: 3 | I57: 3 | J57: Yes | K57: =IF(OR(A57="",F57="N/A",H57=""),"",H57*I57) -> 9 | L57: =IF(OR(A57="",F57="N/A",H57=""),"",3*I57) -> 9 | M57: =IF(AND(J57="Yes",OR(F57="No",AND(F57<>"N/A",H57<>"",N(H57)<=1))),"RED FLAG","") | N57: =IF(A57="","",IF(F57="","Awaiting answer",IF(AND(F57<>"N/A",H57=""),"Score it",IF(AND(OR(F57="Yes",F57="Partial"),G57=""),"Evidence missing",IF(AND(F57="N/A",J57="Yes"),"Critical N/A - justify",IF(AND(F57="Yes",H57<>"",N(H57)<=1),"Claim not supported","OK")))))) -> OK
A58: 9. Human oversight
A59: HUM-01 | B59: 9. Human oversight | C59: Can users review, edit and approve AI outputs before they are sent or acted on, and can we make that review mandatory? | D59: Mandatory review is how you keep a person accountable for what leaves the organisation. | E59: Configuration option and demonstration. | F59: Yes | G59: Admin guide p.33 | H59: 3 | I59: 3 | J59: No | K59: =IF(OR(A59="",F59="N/A",H59=""),"",H59*I59) -> 9 | L59: =IF(OR(A59="",F59="N/A",H59=""),"",3*I59) -> 9 | M59: =IF(AND(J59="Yes",OR(F59="No",AND(F59<>"N/A",H59<>"",N(H59)<=1))),"RED FLAG","") | N59: =IF(A59="","",IF(F59="","Awaiting answer",IF(AND(F59<>"N/A",H59=""),"Score it",IF(AND(OR(F59="Yes",F59="Partial"),G59=""),"Evidence missing",IF(AND(F59="N/A",J59="Yes"),"Critical N/A - justify",IF(AND(F59="Yes",H59<>"",N(H59)<=1),"Claim not supported","OK")))))) -> OK
A60: HUM-02 | B60: 9. Human oversight | C60: Does the product tell users, and where relevant the people affected, that they are interacting with AI or that content is AI-generated? | D60: Supports the transparency obligations in Art. 50 of the EU AI Act. | E60: Screenshots of disclosures and any configurable notice text. | F60: Yes | G60: Screenshot SS-04 | H60: 2 | I60: 2 | J60: No | K60: =IF(OR(A60="",F60="N/A",H60=""),"",H60*I60) -> 4 | L60: =IF(OR(A60="",F60="N/A",H60=""),"",3*I60) -> 6 | M60: =IF(AND(J60="Yes",OR(F60="No",AND(F60<>"N/A",H60<>"",N(H60)<=1))),"RED FLAG","") | N60: =IF(A60="","",IF(F60="","Awaiting answer",IF(AND(F60<>"N/A",H60=""),"Score it",IF(AND(OR(F60="Yes",F60="Partial"),G60=""),"Evidence missing",IF(AND(F60="N/A",J60="Yes"),"Critical N/A - justify",IF(AND(F60="Yes",H60<>"",N(H60)<=1),"Claim not supported","OK")))))) -> OK
A61: HUM-03 | B61: 9. Human oversight | C61: Can we switch AI features off quickly - globally, per feature and per user group - without a vendor ticket? | D61: A kill switch is your first containment step in an AI incident. | E61: Admin control demonstration and the time it takes to take effect. | F61: Yes | G61: Admin guide p.8; tested 2026-10-09 | H61: 3 | I61: 3 | J61: Yes | K61: =IF(OR(A61="",F61="N/A",H61=""),"",H61*I61) -> 9 | L61: =IF(OR(A61="",F61="N/A",H61=""),"",3*I61) -> 9 | M61: =IF(AND(J61="Yes",OR(F61="No",AND(F61<>"N/A",H61<>"",N(H61)<=1))),"RED FLAG","") | N61: =IF(A61="","",IF(F61="","Awaiting answer",IF(AND(F61<>"N/A",H61=""),"Score it",IF(AND(OR(F61="Yes",F61="Partial"),G61=""),"Evidence missing",IF(AND(F61="N/A",J61="Yes"),"Critical N/A - justify",IF(AND(F61="Yes",H61<>"",N(H61)<=1),"Claim not supported","OK")))))) -> OK
A62: HUM-04 | B62: 9. Human oversight | C62: Does the vendor provide instructions for use and user guidance explaining capabilities, limitations and when not to rely on the output? | D62: People cannot exercise real oversight without knowing the system's limits. | E62: Instructions for use or user guidance document for the version in use. | F62: Yes | G62: User guide v3 | H62: 2 | I62: 2 | J62: No | K62: =IF(OR(A62="",F62="N/A",H62=""),"",H62*I62) -> 4 | L62: =IF(OR(A62="",F62="N/A",H62=""),"",3*I62) -> 6 | M62: =IF(AND(J62="Yes",OR(F62="No",AND(F62<>"N/A",H62<>"",N(H62)<=1))),"RED FLAG","") | N62: =IF(A62="","",IF(F62="","Awaiting answer",IF(AND(F62<>"N/A",H62=""),"Score it",IF(AND(OR(F62="Yes",F62="Partial"),G62=""),"Evidence missing",IF(AND(F62="N/A",J62="Yes"),"Critical N/A - justify",IF(AND(F62="Yes",H62<>"",N(H62)<=1),"Claim not supported","OK")))))) -> OK
A63: 10. Logging and audit trail (customer-accessible)
A64: LOG-01 | B64: 10. Logging and audit trail (customer-accessible) | C64: Can we access logs of prompts, outputs, tool calls and actions taken, attributed to a user and timestamped? | D64: Without these logs you cannot investigate an incident or answer a regulator. | E64: Log schema, sample export and the access method. | F64: Yes | G64: Audit log API docs; sample LOG-1 | H64: 2 | I64: 3 | J64: Yes | K64: =IF(OR(A64="",F64="N/A",H64=""),"",H64*I64) -> 6 | L64: =IF(OR(A64="",F64="N/A",H64=""),"",3*I64) -> 9 | M64: =IF(AND(J64="Yes",OR(F64="No",AND(F64<>"N/A",H64<>"",N(H64)<=1))),"RED FLAG","") | N64: =IF(A64="","",IF(F64="","Awaiting answer",IF(AND(F64<>"N/A",H64=""),"Score it",IF(AND(OR(F64="Yes",F64="Partial"),G64=""),"Evidence missing",IF(AND(F64="N/A",J64="Yes"),"Critical N/A - justify",IF(AND(F64="Yes",H64<>"",N(H64)<=1),"Claim not supported","OK")))))) -> OK
A65: LOG-02 | B65: 10. Logging and audit trail (customer-accessible) | C65: Is there an admin audit log of configuration changes (AI settings, connectors, retention, permissions)? | D65: Configuration changes are a common root cause of AI incidents. | E65: Admin audit log documentation and sample. | F65: Yes | G65: Admin guide p.50 | H65: 3 | I65: 2 | J65: No | K65: =IF(OR(A65="",F65="N/A",H65=""),"",H65*I65) -> 6 | L65: =IF(OR(A65="",F65="N/A",H65=""),"",3*I65) -> 6 | M65: =IF(AND(J65="Yes",OR(F65="No",AND(F65<>"N/A",H65<>"",N(H65)<=1))),"RED FLAG","") | N65: =IF(A65="","",IF(F65="","Awaiting answer",IF(AND(F65<>"N/A",H65=""),"Score it",IF(AND(OR(F65="Yes",F65="Partial"),G65=""),"Evidence missing",IF(AND(F65="N/A",J65="Yes"),"Critical N/A - justify",IF(AND(F65="Yes",H65<>"",N(H65)<=1),"Claim not supported","OK")))))) -> OK
A66: LOG-03 | B66: 10. Logging and audit trail (customer-accessible) | C66: Can logs be exported to our SIEM by API or streaming, and in what format? | D66: Logs you cannot correlate with other security data are rarely reviewed. | E66: API or streaming documentation and supported formats. | F66: Partial | G66: API only, no streaming | H66: 2 | I66: 2 | J66: No | K66: =IF(OR(A66="",F66="N/A",H66=""),"",H66*I66) -> 4 | L66: =IF(OR(A66="",F66="N/A",H66=""),"",3*I66) -> 6 | M66: =IF(AND(J66="Yes",OR(F66="No",AND(F66<>"N/A",H66<>"",N(H66)<=1))),"RED FLAG","") | N66: =IF(A66="","",IF(F66="","Awaiting answer",IF(AND(F66<>"N/A",H66=""),"Score it",IF(AND(OR(F66="Yes",F66="Partial"),G66=""),"Evidence missing",IF(AND(F66="N/A",J66="Yes"),"Critical N/A - justify",IF(AND(F66="Yes",H66<>"",N(H66)<=1),"Claim not supported","OK")))))) -> OK
A67: LOG-04 | B67: 10. Logging and audit trail (customer-accessible) | C67: Can we control log retention, and keep logs for at least six months where we deploy a high-risk AI system? | D67: Art. 26(6) of the EU AI Act requires deployers of high-risk systems to keep logs under their control. | E67: Retention settings for logs, or confirmation that exported logs are complete. | F67: Yes | G67: Retention schedule RS-2026 row 12 | H67: 2 | I67: 2 | J67: No | K67: =IF(OR(A67="",F67="N/A",H67=""),"",H67*I67) -> 4 | L67: =IF(OR(A67="",F67="N/A",H67=""),"",3*I67) -> 6 | M67: =IF(AND(J67="Yes",OR(F67="No",AND(F67<>"N/A",H67<>"",N(H67)<=1))),"RED FLAG","") | N67: =IF(A67="","",IF(F67="","Awaiting answer",IF(AND(F67<>"N/A",H67=""),"Score it",IF(AND(OR(F67="Yes",F67="Partial"),G67=""),"Evidence missing",IF(AND(F67="N/A",J67="Yes"),"Critical N/A - justify",IF(AND(F67="Yes",H67<>"",N(H67)<=1),"Claim not supported","OK")))))) -> OK
A68: LOG-05 | B68: 10. Logging and audit trail (customer-accessible) | C68: Are logs protected against tampering, and is vendor staff access to our logs restricted and recorded? | D68: Logs are only useful as evidence if they can be trusted. | E68: Description of log integrity controls and privileged access monitoring. | F68: Yes | H68: 1 | I68: 1 | J68: No | K68: =IF(OR(A68="",F68="N/A",H68=""),"",H68*I68) -> 1 | L68: =IF(OR(A68="",F68="N/A",H68=""),"",3*I68) -> 3 | M68: =IF(AND(J68="Yes",OR(F68="No",AND(F68<>"N/A",H68<>"",N(H68)<=1))),"RED FLAG","") | N68: =IF(A68="","",IF(F68="","Awaiting answer",IF(AND(F68<>"N/A",H68=""),"Score it",IF(AND(OR(F68="Yes",F68="Partial"),G68=""),"Evidence missing",IF(AND(F68="N/A",J68="Yes"),"Critical N/A - justify",IF(AND(F68="Yes",H68<>"",N(H68)<=1),"Claim not supported","OK")))))) -> Evidence missing
A69: 11. Incident response and AI-incident notification
A70: INC-01 | B70: 11. Incident response and AI-incident notification | C70: What is the contractual timeline for notifying us of a security incident or personal data breach affecting our data? | D70: Your own regulatory clocks start when you become aware - the vendor's delay is your delay. | E70: Contract or DPA clause with the notification period and what the notice will contain. | F70: Yes | G70: DPA cl. 11 (48 hours) | H70: 3 | I70: 3 | J70: Yes | K70: =IF(OR(A70="",F70="N/A",H70=""),"",H70*I70) -> 9 | L70: =IF(OR(A70="",F70="N/A",H70=""),"",3*I70) -> 9 | M70: =IF(AND(J70="Yes",OR(F70="No",AND(F70<>"N/A",H70<>"",N(H70)<=1))),"RED FLAG","") | N70: =IF(A70="","",IF(F70="","Awaiting answer",IF(AND(F70<>"N/A",H70=""),"Score it",IF(AND(OR(F70="Yes",F70="Partial"),G70=""),"Evidence missing",IF(AND(F70="N/A",J70="Yes"),"Critical N/A - justify",IF(AND(F70="Yes",H70<>"",N(H70)<=1),"Claim not supported","OK")))))) -> OK
A71: INC-02 | B71: 11. Incident response and AI-incident notification | C71: Does the vendor's incident definition include AI-specific events: harmful outputs at scale, exploited prompt injection, data leakage through outputs, and model provider incidents? | D71: Many contracts only cover classic security breaches. | E71: Incident definition and classification scheme covering AI events. | F71: Partial | G71: Not in contract | H71: 1 | I71: 3 | J71: No | K71: =IF(OR(A71="",F71="N/A",H71=""),"",H71*I71) -> 3 | L71: =IF(OR(A71="",F71="N/A",H71=""),"",3*I71) -> 9 | M71: =IF(AND(J71="Yes",OR(F71="No",AND(F71<>"N/A",H71<>"",N(H71)<=1))),"RED FLAG","") | N71: =IF(A71="","",IF(F71="","Awaiting answer",IF(AND(F71<>"N/A",H71=""),"Score it",IF(AND(OR(F71="Yes",F71="Partial"),G71=""),"Evidence missing",IF(AND(F71="N/A",J71="Yes"),"Critical N/A - justify",IF(AND(F71="Yes",H71<>"",N(H71)<=1),"Claim not supported","OK")))))) -> OK
A72: INC-03 | B72: 11. Incident response and AI-incident notification | C72: Will we be notified of incidents at the model provider or other sub-processors that affect our data or service? | D72: Fourth-party incidents reach you only if the vendor passes them on. | E72: Flow-down notification clause or incident procedure. | F72: Yes | G72: DPA cl. 11.3 | H72: 2 | I72: 2 | J72: No | K72: =IF(OR(A72="",F72="N/A",H72=""),"",H72*I72) -> 4 | L72: =IF(OR(A72="",F72="N/A",H72=""),"",3*I72) -> 6 | M72: =IF(AND(J72="Yes",OR(F72="No",AND(F72<>"N/A",H72<>"",N(H72)<=1))),"RED FLAG","") | N72: =IF(A72="","",IF(F72="","Awaiting answer",IF(AND(F72<>"N/A",H72=""),"Score it",IF(AND(OR(F72="Yes",F72="Partial"),G72=""),"Evidence missing",IF(AND(F72="N/A",J72="Yes"),"Critical N/A - justify",IF(AND(F72="Yes",H72<>"",N(H72)<=1),"Claim not supported","OK")))))) -> OK
A73: INC-04 | B73: 11. Incident response and AI-incident notification | C73: Is there a documented AI incident response playbook, tested in the last 12 months, with a channel for reporting vulnerabilities and harmful outputs? | D73: Untested playbooks fail on first contact. | E73: Playbook table of contents, test date and lessons learned, plus the disclosure or reporting channel. | F73: Yes | G73: IR summary; tabletop 2026-05 | H73: 2 | I73: 2 | J73: No | K73: =IF(OR(A73="",F73="N/A",H73=""),"",H73*I73) -> 4 | L73: =IF(OR(A73="",F73="N/A",H73=""),"",3*I73) -> 6 | M73: =IF(AND(J73="Yes",OR(F73="No",AND(F73<>"N/A",H73<>"",N(H73)<=1))),"RED FLAG","") | N73: =IF(A73="","",IF(F73="","Awaiting answer",IF(AND(F73<>"N/A",H73=""),"Score it",IF(AND(OR(F73="Yes",F73="Partial"),G73=""),"Evidence missing",IF(AND(F73="N/A",J73="Yes"),"Critical N/A - justify",IF(AND(F73="Yes",H73<>"",N(H73)<=1),"Claim not supported","OK")))))) -> OK
A74: INC-05 | B74: 11. Incident response and AI-incident notification | C74: Will the vendor give us timely information and logs to meet our own regulatory reporting duties? | D74: You remain answerable for incidents involving your customers and staff. | E74: Contract assistance clause and the named contact route. | F74: Yes | G74: DPA cl. 11.4 | H74: 3 | I74: 2 | J74: No | K74: =IF(OR(A74="",F74="N/A",H74=""),"",H74*I74) -> 6 | L74: =IF(OR(A74="",F74="N/A",H74=""),"",3*I74) -> 6 | M74: =IF(AND(J74="Yes",OR(F74="No",AND(F74<>"N/A",H74<>"",N(H74)<=1))),"RED FLAG","") | N74: =IF(A74="","",IF(F74="","Awaiting answer",IF(AND(F74<>"N/A",H74=""),"Score it",IF(AND(OR(F74="Yes",F74="Partial"),G74=""),"Evidence missing",IF(AND(F74="N/A",J74="Yes"),"Critical N/A - justify",IF(AND(F74="Yes",H74<>"",N(H74)<=1),"Claim not supported","OK")))))) -> OK
A75: 12. Regulatory position (EU AI Act, GDPR, DPDP)
A76: REG-01 | B76: 12. Regulatory position (EU AI Act, GDPR, DPDP) | C76: What role does the vendor take under Regulation (EU) 2024/1689 for this product, and does it consider any feature high-risk or a general-purpose AI model? Provide its written position. | D76: Roles decide who carries which obligations; you need the vendor's position in writing. | E76: Signed statement of AI Act role and classification, with reasoning. | F76: Yes | G76: AI Act position letter 2026-09 | H76: 2 | I76: 3 | J76: No | K76: =IF(OR(A76="",F76="N/A",H76=""),"",H76*I76) -> 6 | L76: =IF(OR(A76="",F76="N/A",H76=""),"",3*I76) -> 9 | M76: =IF(AND(J76="Yes",OR(F76="No",AND(F76<>"N/A",H76<>"",N(H76)<=1))),"RED FLAG","") | N76: =IF(A76="","",IF(F76="","Awaiting answer",IF(AND(F76<>"N/A",H76=""),"Score it",IF(AND(OR(F76="Yes",F76="Partial"),G76=""),"Evidence missing",IF(AND(F76="N/A",J76="Yes"),"Critical N/A - justify",IF(AND(F76="Yes",H76<>"",N(H76)<=1),"Claim not supported","OK")))))) -> OK
A77: REG-02 | B77: 12. Regulatory position (EU AI Act, GDPR, DPDP) | C77: Would our intended configuration (our branding, fine-tuning, a new intended purpose) make us a provider under Art. 25? Does the vendor document the permitted intended purpose? | D77: Art. 25 can turn a deployer into a provider with provider obligations. | E77: Intended-purpose statement and the vendor's guidance on modifications. | F77: Partial | G77: Acceptable use policy s.2 | H77: 2 | I77: 2 | J77: No | K77: =IF(OR(A77="",F77="N/A",H77=""),"",H77*I77) -> 4 | L77: =IF(OR(A77="",F77="N/A",H77=""),"",3*I77) -> 6 | M77: =IF(AND(J77="Yes",OR(F77="No",AND(F77<>"N/A",H77<>"",N(H77)<=1))),"RED FLAG","") | N77: =IF(A77="","",IF(F77="","Awaiting answer",IF(AND(F77<>"N/A",H77=""),"Score it",IF(AND(OR(F77="Yes",F77="Partial"),G77=""),"Evidence missing",IF(AND(F77="N/A",J77="Yes"),"Critical N/A - justify",IF(AND(F77="Yes",H77<>"",N(H77)<=1),"Claim not supported","OK")))))) -> OK
A78: REG-03 | B78: 12. Regulatory position (EU AI Act, GDPR, DPDP) | C78: If the system is high-risk: will the vendor give us the instructions for use, logs and information we need to meet deployer obligations under Art. 26? | D78: Deployers depend on the provider's information to use, monitor and log the system correctly. | E78: Instructions for use and a commitment to provide information and support. | F78: N/A | G78: Not high-risk for our use case | I78: 2 | J78: No | K78: =IF(OR(A78="",F78="N/A",H78=""),"",H78*I78) | L78: =IF(OR(A78="",F78="N/A",H78=""),"",3*I78) | M78: =IF(AND(J78="Yes",OR(F78="No",AND(F78<>"N/A",H78<>"",N(H78)<=1))),"RED FLAG","") | N78: =IF(A78="","",IF(F78="","Awaiting answer",IF(AND(F78<>"N/A",H78=""),"Score it",IF(AND(OR(F78="Yes",F78="Partial"),G78=""),"Evidence missing",IF(AND(F78="N/A",J78="Yes"),"Critical N/A - justify",IF(AND(F78="Yes",H78<>"",N(H78)<=1),"Claim not supported","OK")))))) -> OK
A79: REG-04 | B79: 12. Regulatory position (EU AI Act, GDPR, DPDP) | C79: Which Art. 50 transparency measures does the product implement (AI interaction disclosure, machine-readable marking of synthetic content), and which are left to us? | D79: Art. 50 places transparency duties on providers and on deployers. | E79: Feature description mapped to each transparency measure, with the split of responsibility. | F79: Partial | G79: Product note PN-7 | H79: 2 | I79: 2 | J79: No | K79: =IF(OR(A79="",F79="N/A",H79=""),"",H79*I79) -> 4 | L79: =IF(OR(A79="",F79="N/A",H79=""),"",3*I79) -> 6 | M79: =IF(AND(J79="Yes",OR(F79="No",AND(F79<>"N/A",H79<>"",N(H79)<=1))),"RED FLAG","") | N79: =IF(A79="","",IF(F79="","Awaiting answer",IF(AND(F79<>"N/A",H79=""),"Score it",IF(AND(OR(F79="Yes",F79="Partial"),G79=""),"Evidence missing",IF(AND(F79="N/A",J79="Yes"),"Critical N/A - justify",IF(AND(F79="Yes",H79<>"",N(H79)<=1),"Claim not supported","OK")))))) -> OK
A80: REG-05 | B80: 12. Regulatory position (EU AI Act, GDPR, DPDP) | C80: Is a data processing agreement in place with processor terms covering instructions, confidentiality, sub-processors, assistance, deletion and audit? | D80: Processor terms are a legal requirement under GDPR and similar laws when personal data is shared. | E80: Executed DPA with annexes. | F80: Yes | G80: DPA executed 2026-09-30 | H80: 3 | I80: 3 | J80: Yes | K80: =IF(OR(A80="",F80="N/A",H80=""),"",H80*I80) -> 9 | L80: =IF(OR(A80="",F80="N/A",H80=""),"",3*I80) -> 9 | M80: =IF(AND(J80="Yes",OR(F80="No",AND(F80<>"N/A",H80<>"",N(H80)<=1))),"RED FLAG","") | N80: =IF(A80="","",IF(F80="","Awaiting answer",IF(AND(F80<>"N/A",H80=""),"Score it",IF(AND(OR(F80="Yes",F80="Partial"),G80=""),"Evidence missing",IF(AND(F80="N/A",J80="Yes"),"Critical N/A - justify",IF(AND(F80="Yes",H80<>"",N(H80)<=1),"Claim not supported","OK")))))) -> OK
A81: REG-06 | B81: 12. Regulatory position (EU AI Act, GDPR, DPDP) | C81: For personal data under India's DPDP Act, will the vendor act as a data processor under a valid contract and support our duties as data fiduciary (erasure, breach intimation, security safeguards)? | D81: Under the DPDP Act the data fiduciary stays responsible for processing done on its behalf. | E81: Contract clauses mapped to these duties, or a DPDP addendum. | F81: Partial | G81: DPA addendum draft | H81: 2 | I81: 2 | J81: No | K81: =IF(OR(A81="",F81="N/A",H81=""),"",H81*I81) -> 4 | L81: =IF(OR(A81="",F81="N/A",H81=""),"",3*I81) -> 6 | M81: =IF(AND(J81="Yes",OR(F81="No",AND(F81<>"N/A",H81<>"",N(H81)<=1))),"RED FLAG","") | N81: =IF(A81="","",IF(F81="","Awaiting answer",IF(AND(F81<>"N/A",H81=""),"Score it",IF(AND(OR(F81="Yes",F81="Partial"),G81=""),"Evidence missing",IF(AND(F81="N/A",J81="Yes"),"Critical N/A - justify",IF(AND(F81="Yes",H81<>"",N(H81)<=1),"Claim not supported","OK")))))) -> OK
A82: REG-07 | B82: 12. Regulatory position (EU AI Act, GDPR, DPDP) | C82: Will the vendor support our DPIA or AI impact assessment with information on data flows, logic, limitations and risks? | D82: You cannot assess impact on people without the vendor's information. | E82: Commitment to assist and an example information pack. | F82: Yes | G82: DPIA support pack | H82: 3 | I82: 2 | J82: No | K82: =IF(OR(A82="",F82="N/A",H82=""),"",H82*I82) -> 6 | L82: =IF(OR(A82="",F82="N/A",H82=""),"",3*I82) -> 6 | M82: =IF(AND(J82="Yes",OR(F82="No",AND(F82<>"N/A",H82<>"",N(H82)<=1))),"RED FLAG","") | N82: =IF(A82="","",IF(F82="","Awaiting answer",IF(AND(F82<>"N/A",H82=""),"Score it",IF(AND(OR(F82="Yes",F82="Partial"),G82=""),"Evidence missing",IF(AND(F82="N/A",J82="Yes"),"Critical N/A - justify",IF(AND(F82="Yes",H82<>"",N(H82)<=1),"Claim not supported","OK")))))) -> OK
A83: 13. IP and indemnity for generated output
A84: IPI-01 | B84: 13. IP and indemnity for generated output | C84: Who owns the outputs? Does the contract assign or licence outputs to us without restrictions on use? | D84: Unclear ownership limits how you can use and protect generated content. | E84: Ownership and licence clause. | F84: Yes | G84: MSA cl. 8.1 | H84: 3 | I84: 2 | J84: No | K84: =IF(OR(A84="",F84="N/A",H84=""),"",H84*I84) -> 6 | L84: =IF(OR(A84="",F84="N/A",H84=""),"",3*I84) -> 6 | M84: =IF(AND(J84="Yes",OR(F84="No",AND(F84<>"N/A",H84<>"",N(H84)<=1))),"RED FLAG","") | N84: =IF(A84="","",IF(F84="","Awaiting answer",IF(AND(F84<>"N/A",H84=""),"Score it",IF(AND(OR(F84="Yes",F84="Partial"),G84=""),"Evidence missing",IF(AND(F84="N/A",J84="Yes"),"Critical N/A - justify",IF(AND(F84="Yes",H84<>"",N(H84)<=1),"Claim not supported","OK")))))) -> OK
A85: IPI-02 | B85: 13. IP and indemnity for generated output | C85: Does the vendor indemnify us against third-party IP claims arising from generated output, and what conditions or exclusions apply (for example filters on, unmodified output)? | D85: Conditions on an indemnity can make it unusable in practice. | E85: Indemnity clause with its conditions and exclusions. | F85: Partial | G85: MSA cl. 12.3 (conditions apply) | H85: 2 | I85: 3 | J85: No | K85: =IF(OR(A85="",F85="N/A",H85=""),"",H85*I85) -> 6 | L85: =IF(OR(A85="",F85="N/A",H85=""),"",3*I85) -> 9 | M85: =IF(AND(J85="Yes",OR(F85="No",AND(F85<>"N/A",H85<>"",N(H85)<=1))),"RED FLAG","") | N85: =IF(A85="","",IF(F85="","Awaiting answer",IF(AND(F85<>"N/A",H85=""),"Score it",IF(AND(OR(F85="Yes",F85="Partial"),G85=""),"Evidence missing",IF(AND(F85="N/A",J85="Yes"),"Critical N/A - justify",IF(AND(F85="Yes",H85<>"",N(H85)<=1),"Claim not supported","OK")))))) -> OK
A86: IPI-03 | B86: 13. IP and indemnity for generated output | C86: Do AI-related data breaches and IP claims sit under the general liability cap or a separate, higher cap? | D86: A low general cap can make the indemnity and breach terms largely symbolic. | E86: Limitation of liability clause and any super-cap. | F86: Partial | G86: General cap only | H86: 1 | I86: 2 | J86: No | K86: =IF(OR(A86="",F86="N/A",H86=""),"",H86*I86) -> 2 | L86: =IF(OR(A86="",F86="N/A",H86=""),"",3*I86) -> 6 | M86: =IF(AND(J86="Yes",OR(F86="No",AND(F86<>"N/A",H86<>"",N(H86)<=1))),"RED FLAG","") | N86: =IF(A86="","",IF(F86="","Awaiting answer",IF(AND(F86<>"N/A",H86=""),"Score it",IF(AND(OR(F86="Yes",F86="Partial"),G86=""),"Evidence missing",IF(AND(F86="N/A",J86="Yes"),"Critical N/A - justify",IF(AND(F86="Yes",H86<>"",N(H86)<=1),"Claim not supported","OK")))))) -> OK
A87: IPI-04 | B87: 13. IP and indemnity for generated output | C87: Are our prompts, files and outputs classed as our confidential information under the contract? | D87: Confidentiality terms give you remedies that privacy terms alone may not. | E87: Definition of Confidential Information in the contract. | F87: Yes | G87: MSA cl. 10 | H87: 3 | I87: 2 | J87: No | K87: =IF(OR(A87="",F87="N/A",H87=""),"",H87*I87) -> 6 | L87: =IF(OR(A87="",F87="N/A",H87=""),"",3*I87) -> 6 | M87: =IF(AND(J87="Yes",OR(F87="No",AND(F87<>"N/A",H87<>"",N(H87)<=1))),"RED FLAG","") | N87: =IF(A87="","",IF(F87="","Awaiting answer",IF(AND(F87<>"N/A",H87=""),"Score it",IF(AND(OR(F87="Yes",F87="Partial"),G87=""),"Evidence missing",IF(AND(F87="N/A",J87="Yes"),"Critical N/A - justify",IF(AND(F87="Yes",H87<>"",N(H87)<=1),"Claim not supported","OK")))))) -> OK
A88: 14. Continuity and exit
A89: EXT-01 | B89: 14. Continuity and exit | C89: On termination, will the vendor return our data - prompts, outputs, files, configurations, custom agents, fine-tunes, embeddings and logs - in a usable format within a stated period? | D89: Exit is when data is most likely to be lost or retained by default. | E89: Exit clause with data scope, format and period. | F89: Partial | G89: MSA cl. 15.2 (scope excludes embeddings) | H89: 2 | I89: 3 | J89: No | K89: =IF(OR(A89="",F89="N/A",H89=""),"",H89*I89) -> 6 | L89: =IF(OR(A89="",F89="N/A",H89=""),"",3*I89) -> 9 | M89: =IF(AND(J89="Yes",OR(F89="No",AND(F89<>"N/A",H89<>"",N(H89)<=1))),"RED FLAG","") | N89: =IF(A89="","",IF(F89="","Awaiting answer",IF(AND(F89<>"N/A",H89=""),"Score it",IF(AND(OR(F89="Yes",F89="Partial"),G89=""),"Evidence missing",IF(AND(F89="N/A",J89="Yes"),"Critical N/A - justify",IF(AND(F89="Yes",H89<>"",N(H89)<=1),"Claim not supported","OK")))))) -> OK
A90: EXT-02 | B90: 14. Continuity and exit | C90: After return, will all copies be deleted - including backups and copies at the model provider - within a stated period, with written certification? | D90: Data left behind at the vendor or the model provider is still your exposure. | E90: Deletion clause with period and certificate of deletion. | F90: Yes | G90: DPA cl. 13 | H90: 3 | I90: 3 | J90: Yes | K90: =IF(OR(A90="",F90="N/A",H90=""),"",H90*I90) -> 9 | L90: =IF(OR(A90="",F90="N/A",H90=""),"",3*I90) -> 9 | M90: =IF(AND(J90="Yes",OR(F90="No",AND(F90<>"N/A",H90<>"",N(H90)<=1))),"RED FLAG","") | N90: =IF(A90="","",IF(F90="","Awaiting answer",IF(AND(F90<>"N/A",H90=""),"Score it",IF(AND(OR(F90="Yes",F90="Partial"),G90=""),"Evidence missing",IF(AND(F90="N/A",J90="Yes"),"Critical N/A - justify",IF(AND(F90="Yes",H90<>"",N(H90)<=1),"Claim not supported","OK")))))) -> OK
A91: EXT-03 | B91: 14. Continuity and exit | C91: Can custom prompts, agents, workflows and fine-tuned models be exported or reproduced on another platform? | D91: Lock-in raises the cost of leaving a vendor that no longer meets your bar. | E91: Export documentation and supported formats. | F91: Partial | G91: Prompts only | H91: 1 | I91: 2 | J91: No | K91: =IF(OR(A91="",F91="N/A",H91=""),"",H91*I91) -> 2 | L91: =IF(OR(A91="",F91="N/A",H91=""),"",3*I91) -> 6 | M91: =IF(AND(J91="Yes",OR(F91="No",AND(F91<>"N/A",H91<>"",N(H91)<=1))),"RED FLAG","") | N91: =IF(A91="","",IF(F91="","Awaiting answer",IF(AND(F91<>"N/A",H91=""),"Score it",IF(AND(OR(F91="Yes",F91="Partial"),G91=""),"Evidence missing",IF(AND(F91="N/A",J91="Yes"),"Critical N/A - justify",IF(AND(F91="Yes",H91<>"",N(H91)<=1),"Claim not supported","OK")))))) -> OK
A92: EXT-04 | B92: 14. Continuity and exit | C92: What happens if the model provider becomes unavailable or stops serving the vendor - fallback provider, recovery objectives and customer notice? | D92: Concentration on one model provider is a single point of failure for your process. | E92: Business continuity plan for AI features, with recovery objectives and test date. | F92: Partial | G92: BCP summary | H92: 2 | I92: 2 | J92: No | K92: =IF(OR(A92="",F92="N/A",H92=""),"",H92*I92) -> 4 | L92: =IF(OR(A92="",F92="N/A",H92=""),"",3*I92) -> 6 | M92: =IF(AND(J92="Yes",OR(F92="No",AND(F92<>"N/A",H92<>"",N(H92)<=1))),"RED FLAG","") | N92: =IF(A92="","",IF(F92="","Awaiting answer",IF(AND(F92<>"N/A",H92=""),"Score it",IF(AND(OR(F92="Yes",F92="Partial"),G92=""),"Evidence missing",IF(AND(F92="N/A",J92="Yes"),"Critical N/A - justify",IF(AND(F92="Yes",H92<>"",N(H92)<=1),"Claim not supported","OK")))))) -> OK
A93: EXT-05 | B93: 14. Continuity and exit | C93: Will we receive notice of a change of control, and of discontinuing an AI feature or model we rely on? | D93: Ownership changes and end-of-life decisions can change data terms and service overnight. | E93: Notice clauses with periods. | F93: Yes | G93: MSA cl. 18 | H93: 2 | I93: 1 | J93: No | K93: =IF(OR(A93="",F93="N/A",H93=""),"",H93*I93) -> 2 | L93: =IF(OR(A93="",F93="N/A",H93=""),"",3*I93) -> 3 | M93: =IF(AND(J93="Yes",OR(F93="No",AND(F93<>"N/A",H93<>"",N(H93)<=1))),"RED FLAG","") | N93: =IF(A93="","",IF(F93="","Awaiting answer",IF(AND(F93<>"N/A",H93=""),"Score it",IF(AND(OR(F93="Yes",F93="Partial"),G93=""),"Evidence missing",IF(AND(F93="N/A",J93="Yes"),"Critical N/A - justify",IF(AND(F93="Yes",H93<>"",N(H93)<=1),"Claim not supported","OK")))))) -> OK

Sheet Scoring Summary
B1: Scoring Summary and Recommendation
B2: By John Bommeraveni Joseph | linkedin.com/in/john-bj | Free every weekday: GRC Made Simple Daily
B5: Section | C5: Questions | D5: Answered | E5: N/A | F5: Scored | G5: Weighted score | H5: Max possible | I5: Score % | J5: Rating | K5: Red flags | L5: Critical questions
B6: 1. Training and model improvement | C6: =COUNTIF(Questionnaire!$B$6:$B$93,B6) -> 5 | D6: =COUNTIFS(Questionnaire!$B$6:$B$93,B6,Questionnaire!$F$6:$F$93,"<>") -> 5 | E6: =COUNTIFS(Questionnaire!$B$6:$B$93,B6,Questionnaire!$F$6:$F$93,"N/A") -> 0 | F6: =COUNTIFS(Questionnaire!$B$6:$B$93,B6,Questionnaire!$K$6:$K$93,">=0") -> 5 | G6: =SUMIFS(Questionnaire!$K$6:$K$93,Questionnaire!$B$6:$B$93,B6) -> 27 | H6: =SUMIFS(Questionnaire!$L$6:$L$93,Questionnaire!$B$6:$B$93,B6) -> 36 | I6: =IF(H6=0,"",G6/H6) -> 0.75 | J6: =IF(I6="","Not scored",IF(I6>=$C$24,"Strong",IF(I6>=$C$25,"Adequate",IF(I6>=$C$26,"Weak","Poor")))) -> Adequate | K6: =COUNTIFS(Questionnaire!$B$6:$B$93,B6,Questionnaire!$M$6:$M$93,"RED FLAG") -> 0 | L6: =COUNTIFS(Questionnaire!$B$6:$B$93,B6,Questionnaire!$J$6:$J$93,"Yes") -> 2
B7: 2. Retention of prompts, outputs and logs | C7: =COUNTIF(Questionnaire!$B$6:$B$93,B7) -> 5 | D7: =COUNTIFS(Questionnaire!$B$6:$B$93,B7,Questionnaire!$F$6:$F$93,"<>") -> 5 | E7: =COUNTIFS(Questionnaire!$B$6:$B$93,B7,Questionnaire!$F$6:$F$93,"N/A") -> 0 | F7: =COUNTIFS(Questionnaire!$B$6:$B$93,B7,Questionnaire!$K$6:$K$93,">=0") -> 5 | G7: =SUMIFS(Questionnaire!$K$6:$K$93,Questionnaire!$B$6:$B$93,B7) -> 22 | H7: =SUMIFS(Questionnaire!$L$6:$L$93,Questionnaire!$B$6:$B$93,B7) -> 33 | I7: =IF(H7=0,"",G7/H7) -> 0.66666667 | J7: =IF(I7="","Not scored",IF(I7>=$C$24,"Strong",IF(I7>=$C$25,"Adequate",IF(I7>=$C$26,"Weak","Poor")))) -> Adequate | K7: =COUNTIFS(Questionnaire!$B$6:$B$93,B7,Questionnaire!$M$6:$M$93,"RED FLAG") -> 0 | L7: =COUNTIFS(Questionnaire!$B$6:$B$93,B7,Questionnaire!$J$6:$J$93,"Yes") -> 1
B8: 3. Data residency and sub-processors (including the model provider) | C8: =COUNTIF(Questionnaire!$B$6:$B$93,B8) -> 5 | D8: =COUNTIFS(Questionnaire!$B$6:$B$93,B8,Questionnaire!$F$6:$F$93,"<>") -> 5 | E8: =COUNTIFS(Questionnaire!$B$6:$B$93,B8,Questionnaire!$F$6:$F$93,"N/A") -> 0 | F8: =COUNTIFS(Questionnaire!$B$6:$B$93,B8,Questionnaire!$K$6:$K$93,">=0") -> 5 | G8: =SUMIFS(Questionnaire!$K$6:$K$93,Questionnaire!$B$6:$B$93,B8) -> 34 | H8: =SUMIFS(Questionnaire!$L$6:$L$93,Questionnaire!$B$6:$B$93,B8) -> 39 | I8: =IF(H8=0,"",G8/H8) -> 0.87179487 | J8: =IF(I8="","Not scored",IF(I8>=$C$24,"Strong",IF(I8>=$C$25,"Adequate",IF(I8>=$C$26,"Weak","Poor")))) -> Strong | K8: =COUNTIFS(Questionnaire!$B$6:$B$93,B8,Questionnaire!$M$6:$M$93,"RED FLAG") -> 0 | L8: =COUNTIFS(Questionnaire!$B$6:$B$93,B8,Questionnaire!$J$6:$J$93,"Yes") -> 1
B9: 4. Security controls and certifications | C9: =COUNTIF(Questionnaire!$B$6:$B$93,B9) -> 7 | D9: =COUNTIFS(Questionnaire!$B$6:$B$93,B9,Questionnaire!$F$6:$F$93,"<>") -> 7 | E9: =COUNTIFS(Questionnaire!$B$6:$B$93,B9,Questionnaire!$F$6:$F$93,"N/A") -> 0 | F9: =COUNTIFS(Questionnaire!$B$6:$B$93,B9,Questionnaire!$K$6:$K$93,">=0") -> 7 | G9: =SUMIFS(Questionnaire!$K$6:$K$93,Questionnaire!$B$6:$B$93,B9) -> 39 | H9: =SUMIFS(Questionnaire!$L$6:$L$93,Questionnaire!$B$6:$B$93,B9) -> 51 | I9: =IF(H9=0,"",G9/H9) -> 0.76470588 | J9: =IF(I9="","Not scored",IF(I9>=$C$24,"Strong",IF(I9>=$C$25,"Adequate",IF(I9>=$C$26,"Weak","Poor")))) -> Adequate | K9: =COUNTIFS(Questionnaire!$B$6:$B$93,B9,Questionnaire!$M$6:$M$93,"RED FLAG") -> 0 | L9: =COUNTIFS(Questionnaire!$B$6:$B$93,B9,Questionnaire!$J$6:$J$93,"Yes") -> 2
B10: 5. Model change management | C10: =COUNTIF(Questionnaire!$B$6:$B$93,B10) -> 5 | D10: =COUNTIFS(Questionnaire!$B$6:$B$93,B10,Questionnaire!$F$6:$F$93,"<>") -> 5 | E10: =COUNTIFS(Questionnaire!$B$6:$B$93,B10,Questionnaire!$F$6:$F$93,"N/A") -> 0 | F10: =COUNTIFS(Questionnaire!$B$6:$B$93,B10,Questionnaire!$K$6:$K$93,">=0") -> 5 | G10: =SUMIFS(Questionnaire!$K$6:$K$93,Questionnaire!$B$6:$B$93,B10) -> 15 | H10: =SUMIFS(Questionnaire!$L$6:$L$93,Questionnaire!$B$6:$B$93,B10) -> 33 | I10: =IF(H10=0,"",G10/H10) -> 0.45454545 | J10: =IF(I10="","Not scored",IF(I10>=$C$24,"Strong",IF(I10>=$C$25,"Adequate",IF(I10>=$C$26,"Weak","Poor")))) -> Poor | K10: =COUNTIFS(Questionnaire!$B$6:$B$93,B10,Questionnaire!$M$6:$M$93,"RED FLAG") -> 1 | L10: =COUNTIFS(Questionnaire!$B$6:$B$93,B10,Questionnaire!$J$6:$J$93,"Yes") -> 1
B11: 6. Evaluation and testing | C11: =COUNTIF(Questionnaire!$B$6:$B$93,B11) -> 6 | D11: =COUNTIFS(Questionnaire!$B$6:$B$93,B11,Questionnaire!$F$6:$F$93,"<>") -> 6 | E11: =COUNTIFS(Questionnaire!$B$6:$B$93,B11,Questionnaire!$F$6:$F$93,"N/A") -> 0 | F11: =COUNTIFS(Questionnaire!$B$6:$B$93,B11,Questionnaire!$K$6:$K$93,">=0") -> 6 | G11: =SUMIFS(Questionnaire!$K$6:$K$93,Questionnaire!$B$6:$B$93,B11) -> 30 | H11: =SUMIFS(Questionnaire!$L$6:$L$93,Questionnaire!$B$6:$B$93,B11) -> 45 | I11: =IF(H11=0,"",G11/H11) -> 0.66666667 | J11: =IF(I11="","Not scored",IF(I11>=$C$24,"Strong",IF(I11>=$C$25,"Adequate",IF(I11>=$C$26,"Weak","Poor")))) -> Adequate | K11: =COUNTIFS(Questionnaire!$B$6:$B$93,B11,Questionnaire!$M$6:$M$93,"RED FLAG") -> 0 | L11: =COUNTIFS(Questionnaire!$B$6:$B$93,B11,Questionnaire!$J$6:$J$93,"Yes") -> 1
B12: 7. Agent and tool permissions (excessive agency) | C12: =COUNTIF(Questionnaire!$B$6:$B$93,B12) -> 6 | D12: =COUNTIFS(Questionnaire!$B$6:$B$93,B12,Questionnaire!$F$6:$F$93,"<>") -> 6 | E12: =COUNTIFS(Questionnaire!$B$6:$B$93,B12,Questionnaire!$F$6:$F$93,"N/A") -> 0 | F12: =COUNTIFS(Questionnaire!$B$6:$B$93,B12,Questionnaire!$K$6:$K$93,">=0") -> 6 | G12: =SUMIFS(Questionnaire!$K$6:$K$93,Questionnaire!$B$6:$B$93,B12) -> 38 | H12: =SUMIFS(Questionnaire!$L$6:$L$93,Questionnaire!$B$6:$B$93,B12) -> 45 | I12: =IF(H12=0,"",G12/H12) -> 0.84444444 | J12: =IF(I12="","Not scored",IF(I12>=$C$24,"Strong",IF(I12>=$C$25,"Adequate",IF(I12>=$C$26,"Weak","Poor")))) -> Strong | K12: =COUNTIFS(Questionnaire!$B$6:$B$93,B12,Questionnaire!$M$6:$M$93,"RED FLAG") -> 0 | L12: =COUNTIFS(Questionnaire!$B$6:$B$93,B12,Questionnaire!$J$6:$J$93,"Yes") -> 2
B13: 8. Output handling and hallucination controls | C13: =COUNTIF(Questionnaire!$B$6:$B$93,B13) -> 5 | D13: =COUNTIFS(Questionnaire!$B$6:$B$93,B13,Questionnaire!$F$6:$F$93,"<>") -> 5 | E13: =COUNTIFS(Questionnaire!$B$6:$B$93,B13,Questionnaire!$F$6:$F$93,"N/A") -> 0 | F13: =COUNTIFS(Questionnaire!$B$6:$B$93,B13,Questionnaire!$K$6:$K$93,">=0") -> 5 | G13: =SUMIFS(Questionnaire!$K$6:$K$93,Questionnaire!$B$6:$B$93,B13) -> 27 | H13: =SUMIFS(Questionnaire!$L$6:$L$93,Questionnaire!$B$6:$B$93,B13) -> 36 | I13: =IF(H13=0,"",G13/H13) -> 0.75 | J13: =IF(I13="","Not scored",IF(I13>=$C$24,"Strong",IF(I13>=$C$25,"Adequate",IF(I13>=$C$26,"Weak","Poor")))) -> Adequate | K13: =COUNTIFS(Questionnaire!$B$6:$B$93,B13,Questionnaire!$M$6:$M$93,"RED FLAG") -> 0 | L13: =COUNTIFS(Questionnaire!$B$6:$B$93,B13,Questionnaire!$J$6:$J$93,"Yes") -> 1
B14: 9. Human oversight | C14: =COUNTIF(Questionnaire!$B$6:$B$93,B14) -> 4 | D14: =COUNTIFS(Questionnaire!$B$6:$B$93,B14,Questionnaire!$F$6:$F$93,"<>") -> 4 | E14: =COUNTIFS(Questionnaire!$B$6:$B$93,B14,Questionnaire!$F$6:$F$93,"N/A") -> 0 | F14: =COUNTIFS(Questionnaire!$B$6:$B$93,B14,Questionnaire!$K$6:$K$93,">=0") -> 4 | G14: =SUMIFS(Questionnaire!$K$6:$K$93,Questionnaire!$B$6:$B$93,B14) -> 26 | H14: =SUMIFS(Questionnaire!$L$6:$L$93,Questionnaire!$B$6:$B$93,B14) -> 30 | I14: =IF(H14=0,"",G14/H14) -> 0.86666667 | J14: =IF(I14="","Not scored",IF(I14>=$C$24,"Strong",IF(I14>=$C$25,"Adequate",IF(I14>=$C$26,"Weak","Poor")))) -> Strong | K14: =COUNTIFS(Questionnaire!$B$6:$B$93,B14,Questionnaire!$M$6:$M$93,"RED FLAG") -> 0 | L14: =COUNTIFS(Questionnaire!$B$6:$B$93,B14,Questionnaire!$J$6:$J$93,"Yes") -> 1
B15: 10. Logging and audit trail (customer-accessible) | C15: =COUNTIF(Questionnaire!$B$6:$B$93,B15) -> 5 | D15: =COUNTIFS(Questionnaire!$B$6:$B$93,B15,Questionnaire!$F$6:$F$93,"<>") -> 5 | E15: =COUNTIFS(Questionnaire!$B$6:$B$93,B15,Questionnaire!$F$6:$F$93,"N/A") -> 0 | F15: =COUNTIFS(Questionnaire!$B$6:$B$93,B15,Questionnaire!$K$6:$K$93,">=0") -> 5 | G15: =SUMIFS(Questionnaire!$K$6:$K$93,Questionnaire!$B$6:$B$93,B15) -> 21 | H15: =SUMIFS(Questionnaire!$L$6:$L$93,Questionnaire!$B$6:$B$93,B15) -> 30 | I15: =IF(H15=0,"",G15/H15) -> 0.7 | J15: =IF(I15="","Not scored",IF(I15>=$C$24,"Strong",IF(I15>=$C$25,"Adequate",IF(I15>=$C$26,"Weak","Poor")))) -> Adequate | K15: =COUNTIFS(Questionnaire!$B$6:$B$93,B15,Questionnaire!$M$6:$M$93,"RED FLAG") -> 0 | L15: =COUNTIFS(Questionnaire!$B$6:$B$93,B15,Questionnaire!$J$6:$J$93,"Yes") -> 1
B16: 11. Incident response and AI-incident notification | C16: =COUNTIF(Questionnaire!$B$6:$B$93,B16) -> 5 | D16: =COUNTIFS(Questionnaire!$B$6:$B$93,B16,Questionnaire!$F$6:$F$93,"<>") -> 5 | E16: =COUNTIFS(Questionnaire!$B$6:$B$93,B16,Questionnaire!$F$6:$F$93,"N/A") -> 0 | F16: =COUNTIFS(Questionnaire!$B$6:$B$93,B16,Questionnaire!$K$6:$K$93,">=0") -> 5 | G16: =SUMIFS(Questionnaire!$K$6:$K$93,Questionnaire!$B$6:$B$93,B16) -> 26 | H16: =SUMIFS(Questionnaire!$L$6:$L$93,Questionnaire!$B$6:$B$93,B16) -> 36 | I16: =IF(H16=0,"",G16/H16) -> 0.72222222 | J16: =IF(I16="","Not scored",IF(I16>=$C$24,"Strong",IF(I16>=$C$25,"Adequate",IF(I16>=$C$26,"Weak","Poor")))) -> Adequate | K16: =COUNTIFS(Questionnaire!$B$6:$B$93,B16,Questionnaire!$M$6:$M$93,"RED FLAG") -> 0 | L16: =COUNTIFS(Questionnaire!$B$6:$B$93,B16,Questionnaire!$J$6:$J$93,"Yes") -> 1
B17: 12. Regulatory position (EU AI Act, GDPR, DPDP) | C17: =COUNTIF(Questionnaire!$B$6:$B$93,B17) -> 7 | D17: =COUNTIFS(Questionnaire!$B$6:$B$93,B17,Questionnaire!$F$6:$F$93,"<>") -> 7 | E17: =COUNTIFS(Questionnaire!$B$6:$B$93,B17,Questionnaire!$F$6:$F$93,"N/A") -> 1 | F17: =COUNTIFS(Questionnaire!$B$6:$B$93,B17,Questionnaire!$K$6:$K$93,">=0") -> 6 | G17: =SUMIFS(Questionnaire!$K$6:$K$93,Questionnaire!$B$6:$B$93,B17) -> 33 | H17: =SUMIFS(Questionnaire!$L$6:$L$93,Questionnaire!$B$6:$B$93,B17) -> 42 | I17: =IF(H17=0,"",G17/H17) -> 0.78571429 | J17: =IF(I17="","Not scored",IF(I17>=$C$24,"Strong",IF(I17>=$C$25,"Adequate",IF(I17>=$C$26,"Weak","Poor")))) -> Adequate | K17: =COUNTIFS(Questionnaire!$B$6:$B$93,B17,Questionnaire!$M$6:$M$93,"RED FLAG") -> 0 | L17: =COUNTIFS(Questionnaire!$B$6:$B$93,B17,Questionnaire!$J$6:$J$93,"Yes") -> 1
... B19: 14. Continuity and exit | C19: =COUNTIF(Questionnaire!$B$6:$B$93,B19) -> 5 | D19: =COUNTIFS(Questionnaire!$B$6:$B$93,B19,Questionnaire!$F$6:$F$93,"<>") -> 5 | E19: =COUNTIFS(Questionnaire!$B$6:$B$93,B19,Questionnaire!$F$6:$F$93,"N/A") -> 0 | F19: =COUNTIFS(Questionnaire!$B$6:$B$93,B19,Questionnaire!$K$6:$K$93,">=0") -> 5 | G19: =SUMIFS(Questionnaire!$K$6:$K$93,Questionnaire!$B$6:$B$93,B19) -> 23 | H19: =SUMIFS(Questionnaire!$L$6:$L$93,Questionnaire!$B$6:$B$93,B19) -> 33 | I19: =IF(H19=0,"",G19/H19) -> 0.6969697 | J19: =IF(I19="","Not scored",IF(I19>=$C$24,"Strong",IF(I19>=$C$25,"Adequate",IF(I19>=$C$26,"Weak","Poor")))) -> Adequate | K19: =COUNTIFS(Questionnaire!$B$6:$B$93,B19,Questionnaire!$M$6:$M$93,"RED FLAG") -> 0 | L19: =COUNTIFS(Questionnaire!$B$6:$B$93,B19,Questionnaire!$J$6:$J$93,"Yes") -> 1
B20: Overall | C20: =SUM(C6:C19) -> 74 | D20: =SUM(D6:D19) -> 74 | E20: =SUM(E6:E19) -> 1 | F20: =SUM(F6:F19) -> 73 | G20: =SUM(G6:G19) -> 381 | H20: =SUM(H6:H19) -> 516 | I20: =IF(H20=0,"",G20/H20) -> 0.73837209 | J20: =IF(I20="","Not scored",IF(I20>=$C$24,"Strong",IF(I20>=$C$25,"Adequate",IF(I20>=$C$26,"Weak","Poor")))) -> Adequate | K20: =SUM(K6:K19) -> 1 | L20: =SUM(L6:L19) -> 16
B23: Thresholds (edit the yellow cells to match your third-party risk policy) | E23: Result
B24: Rating 'Strong' - score at or above | C24: 0.8 | E24: Overall score | J24: =I20 -> 0.73837209
B25: Rating 'Adequate' - score at or above | C25: 0.65 | E25: Overall rating | J25: =J20 -> Adequate
B26: Rating 'Weak' - score at or above (below this = 'Poor') | C26: 0.5 | E26: Red flags (critical questions answered No or scored 0-1) | J26: =K20 -> 1
B27: Approve - overall score at or above | C27: 0.8 | E27: Lowest section score | J27: =IF(COUNT(I6:I19)=0,"",MIN(I6:I19)) -> 0.45454545
B28: Approve - every section at or above | C28: 0.65 | E28: Questions not yet answered or scored | J28: =COUNTIF(Questionnaire!$N$6:$N$93,"Awaiting answer")+COUNTIF(Questionnaire!$N$6:$N$93,"Score it") -> 0
B29: Approve with conditions - overall score at or above | C29: 0.65 | E29: Recommendation on the scores so far | J29: =IF($J$24="","Not scored",IF(OR($J$26>=$C$31,$J$24<$C$30),"Reject",IF(OR($J$26>0,$J$24<$C$29),"Escalate",IF(AND($J$24>=$C$27,$J$27>=$C$28),"Approve","Approve with conditions")))) -> Escalate
B30: Reject - overall score below | C30: 0.5 | E30: RECOMMENDATION | J30: =IF($J$24="","Not scored",IF($J$28>0,"Incomplete - finish answers and scoring",$J$29)) -> Escalate
B31: Reject - red flags at or above | C31: 3
B33: How the recommendation is decided (rules are applied top to bottom; the first that matches wins)
B34: Reject - red flags at or above the Reject red-flag threshold, OR overall score below the Reject threshold.
B35: Escalate - at least one red flag, OR overall score below the 'Approve with conditions' threshold. The approver decides, with documented compensating controls or risk acceptance.
B36: Approve - overall score at or above the Approve threshold AND every section at or above the section minimum (and no red flags).
B37: Approve with conditions - everything else: no red flags and overall score at or above the conditions threshold. Track each condition on the Follow-up Tracker and in the contract.
B38: While any question is still awaiting an answer or a score, the RECOMMENDATION shows 'Incomplete'; the row above it shows where the scores so far point.
B39: Score % = sum of (score x weight) / sum of (3 x weight) over answered, scored questions. N/A answers are excluded from both.

Sheet Follow-up Tracker
B1: Follow-up Tracker
B2: By John Bommeraveni Joseph | linkedin.com/in/john-bj | Free every weekday: GRC Made Simple Daily
A5: FU ID | B5: Question ID | C5: Section | D5: Question | E5: Gap or issue found | F5: Condition or action required | G5: Type | H5: Our owner | I5: Vendor contact | J5: Raised | K5: Due | L5: Status | M5: Closed on | N5: Blocks approval? | O5: Overdue? | P5: Days open
A6: FU-001 | B6: CHG-01 | C6: =IF(B6="","",IFERROR(INDEX(Questionnaire!$B$6:$B$93,MATCH(B6,Questionnaire!$A$6:$A$93,0)),"ID not in questionnaire")) -> 5. Model change management | D6: =IF(B6="","",IFERROR(INDEX(Questionnaire!$C$6:$C$93,MATCH(B6,Questionnaire!$A$6:$A$93,0)),"")) -> Will the vendor notify us in advance of changes to the underlying model, model version, provider, system prompt or safety settings that can change output behaviour - and with how much notice? | E6: No contractual notice of model, provider or system-prompt changes; changelog only | F6: Add a clause: 30 days' written notice of material model or provider changes, with right to terminate | G6: Contract change | H6: Procurement lead | I6: Vendor account manager | J6: 46315 | K6: 46356 | L6: Open | N6: Yes | O6: =IF(OR(K6="",L6="Closed",L6="Risk accepted"),"",IF(K6<TODAY(),"OVERDUE","")) | P6: =IF(J6="","",IF(M6<>"",M6-J6,TODAY()-J6)) -> 7
A7: FU-002 | B7: RET-02 | C7: =IF(B7="","",IFERROR(INDEX(Questionnaire!$B$6:$B$93,MATCH(B7,Questionnaire!$A$6:$A$93,0)),"ID not in questionnaire")) -> 2. Retention of prompts, outputs and logs | D7: =IF(B7="","",IFERROR(INDEX(Questionnaire!$C$6:$C$93,MATCH(B7,Questionnaire!$A$6:$A$93,0)),"")) -> Does the model provider keep prompts or outputs (for example for abuse monitoring), for how long, and is a zero-data-retention or equivalent arrangement contracted for our tenant? | E7: Zero-data-retention arrangement with the model provider not yet countersigned | F7: Obtain countersigned confirmation before go-live | G7: Evidence requested | H7: A. Reviewer | I7: Vendor security team | J7: 46301 | K7: 46319 | L7: In progress | N7: Yes | O7: =IF(OR(K7="",L7="Closed",L7="Risk accepted"),"",IF(K7<TODAY(),"OVERDUE","")) -> OVERDUE | P7: =IF(J7="","",IF(M7<>"",M7-J7,TODAY()-J7)) -> 21
C8: =IF(B8="","",IFERROR(INDEX(Questionnaire!$B$6:$B$93,MATCH(B8,Questionnaire!$A$6:$A$93,0)),"ID not in questionnaire")) | D8: =IF(B8="","",IFERROR(INDEX(Questionnaire!$C$6:$C$93,MATCH(B8,Questionnaire!$A$6:$A$93,0)),"")) | O8: =IF(OR(K8="",L8="Closed",L8="Risk accepted"),"",IF(K8<TODAY(),"OVERDUE","")) | P8: =IF(J8="","",IF(M8<>"",M8-J8,TODAY()-J8))
C9: =IF(B9="","",IFERROR(INDEX(Questionnaire!$B$6:$B$93,MATCH(B9,Questionnaire!$A$6:$A$93,0)),"ID not in questionnaire")) | D9: =IF(B9="","",IFERROR(INDEX(Questionnaire!$C$6:$C$93,MATCH(B9,Questionnaire!$A$6:$A$93,0)),"")) | O9: =IF(OR(K9="",L9="Closed",L9="Risk accepted"),"",IF(K9<TODAY(),"OVERDUE","")) | P9: =IF(J9="","",IF(M9<>"",M9-J9,TODAY()-J9))
C10: =IF(B10="","",IFERROR(INDEX(Questionnaire!$B$6:$B$93,MATCH(B10,Questionnaire!$A$6:$A$93,0)),"ID not in questionnaire")) | D10: =IF(B10="","",IFERROR(INDEX(Questionnaire!$C$6:$C$93,MATCH(B10,Questionnaire!$A$6:$A$93,0)),"")) | O10: =IF(OR(K10="",L10="Closed",L10="Risk accepted"),"",IF(K10<TODAY(),"OVERDUE","")) | P10: =IF(J10="","",IF(M10<>"",M10-J10,TODAY()-J10))
C11: =IF(B11="","",IFERROR(INDEX(Questionnaire!$B$6:$B$93,MATCH(B11,Questionnaire!$A$6:$A$93,0)),"ID not in questionnaire")) | D11: =IF(B11="","",IFERROR(INDEX(Questionnaire!$C$6:$C$93,MATCH(B11,Questionnaire!$A$6:$A$93,0)),"")) | O11: =IF(OR(K11="",L11="Closed",L11="Risk accepted"),"",IF(K11<TODAY(),"OVERDUE","")) | P11: =IF(J11="","",IF(M11<>"",M11-J11,TODAY()-J11))
C12: =IF(B12="","",IFERROR(INDEX(Questionnaire!$B$6:$B$93,MATCH(B12,Questionnaire!$A$6:$A$93,0)),"ID not in questionnaire")) | D12: =IF(B12="","",IFERROR(INDEX(Questionnaire!$C$6:$C$93,MATCH(B12,Questionnaire!$A$6:$A$93,0)),"")) | O12: =IF(OR(K12="",L12="Closed",L12="Risk accepted"),"",IF(K12<TODAY(),"OVERDUE","")) | P12: =IF(J12="","",IF(M12<>"",M12-J12,TODAY()-J12))
C13: =IF(B13="","",IFERROR(INDEX(Questionnaire!$B$6:$B$93,MATCH(B13,Questionnaire!$A$6:$A$93,0)),"ID not in questionnaire")) | D13: =IF(B13="","",IFERROR(INDEX(Questionnaire!$C$6:$C$93,MATCH(B13,Questionnaire!$A$6:$A$93,0)),"")) | O13: =IF(OR(K13="",L13="Closed",L13="Risk accepted"),"",IF(K13<TODAY(),"OVERDUE","")) | P13: =IF(J13="","",IF(M13<>"",M13-J13,TODAY()-J13))
C14: =IF(B14="","",IFERROR(INDEX(Questionnaire!$B$6:$B$93,MATCH(B14,Questionnaire!$A$6:$A$93,0)),"ID not in questionnaire")) | D14: =IF(B14="","",IFERROR(INDEX(Questionnaire!$C$6:$C$93,MATCH(B14,Questionnaire!$A$6:$A$93,0)),"")) | O14: =IF(OR(K14="",L14="Closed",L14="Risk accepted"),"",IF(K14<TODAY(),"OVERDUE","")) | P14: =IF(J14="","",IF(M14<>"",M14-J14,TODAY()-J14))
C15: =IF(B15="","",IFERROR(INDEX(Questionnaire!$B$6:$B$93,MATCH(B15,Questionnaire!$A$6:$A$93,0)),"ID not in questionnaire")) | D15: =IF(B15="","",IFERROR(INDEX(Questionnaire!$C$6:$C$93,MATCH(B15,Questionnaire!$A$6:$A$93,0)),"")) | O15: =IF(OR(K15="",L15="Closed",L15="Risk accepted"),"",IF(K15<TODAY(),"OVERDUE","")) | P15: =IF(J15="","",IF(M15<>"",M15-J15,TODAY()-J15))
C16: =IF(B16="","",IFERROR(INDEX(Questionnaire!$B$6:$B$93,MATCH(B16,Questionnaire!$A$6:$A$93,0)),"ID not in questionnaire")) | D16: =IF(B16="","",IFERROR(INDEX(Questionnaire!$C$6:$C$93,MATCH(B16,Questionnaire!$A$6:$A$93,0)),"")) | O16: =IF(OR(K16="",L16="Closed",L16="Risk accepted"),"",IF(K16<TODAY(),"OVERDUE","")) | P16: =IF(J16="","",IF(M16<>"",M16-J16,TODAY()-J16))
C17: =IF(B17="","",IFERROR(INDEX(Questionnaire!$B$6:$B$93,MATCH(B17,Questionnaire!$A$6:$A$93,0)),"ID not in questionnaire")) | D17: =IF(B17="","",IFERROR(INDEX(Questionnaire!$C$6:$C$93,MATCH(B17,Questionnaire!$A$6:$A$93,0)),"")) | O17: =IF(OR(K17="",L17="Closed",L17="Risk accepted"),"",IF(K17<TODAY(),"OVERDUE","")) | P17: =IF(J17="","",IF(M17<>"",M17-J17,TODAY()-J17))
C18: =IF(B18="","",IFERROR(INDEX(Questionnaire!$B$6:$B$93,MATCH(B18,Questionnaire!$A$6:$A$93,0)),"ID not in questionnaire")) | D18: =IF(B18="","",IFERROR(INDEX(Questionnaire!$C$6:$C$93,MATCH(B18,Questionnaire!$A$6:$A$93,0)),"")) | O18: =IF(OR(K18="",L18="Closed",L18="Risk accepted"),"",IF(K18<TODAY(),"OVERDUE","")) | P18: =IF(J18="","",IF(M18<>"",M18-J18,TODAY()-J18))
C19: =IF(B19="","",IFERROR(INDEX(Questionnaire!$B$6:$B$93,MATCH(B19,Questionnaire!$A$6:$A$93,0)),"ID not in questionnaire")) | D19: =IF(B19="","",IFERROR(INDEX(Questionnaire!$C$6:$C$93,MATCH(B19,Questionnaire!$A$6:$A$93,0)),"")) | O19: =IF(OR(K19="",L19="Closed",L19="Risk accepted"),"",IF(K19<TODAY(),"OVERDUE","")) | P19: =IF(J19="","",IF(M19<>"",M19-J19,TODAY()-J19))
... C105: =IF(B105="","",IFERROR(INDEX(Questionnaire!$B$6:$B$93,MATCH(B105,Questionnaire!$A$6:$A$93,0)),"ID not in questionnaire")) | D105: =IF(B105="","",IFERROR(INDEX(Questionnaire!$C$6:$C$93,MATCH(B105,Questionnaire!$A$6:$A$93,0)),"")) | O105: =IF(OR(K105="",L105="Closed",L105="Risk accepted"),"",IF(K105<TODAY(),"OVERDUE","")) | P105: =IF(J105="","",IF(M105<>"",M105-J105,TODAY()-J105))

Sheet Sources
B1: Sources and further reading
B2: By John Bommeraveni Joseph | linkedin.com/in/john-bj | Free every weekday: GRC Made Simple Daily
B5: Source | C5: Link
B6: Regulation (EU) 2024/1689 (Artificial Intelligence Act), Official Journal - Art. 25 Responsibilities along the AI value chain; Art. 26 Obligations of deployers of high-risk AI systems (incl. Art. 26(6) log retention); Art. 50 Transparency obligations for providers and deployers of certain AI systems. Check the current consolidated text for later amendments. | C6: https://eur-lex.europa.eu/eli/reg/2024/1689/oj
B7: ISO/IEC 42001:2023 Information technology - Artificial intelligence - Management system. Annex A.10 'Third-party and customer relationships' referenced by title only; use your licensed copy. | C7: https://www.iso.org/standard/81230.html
B8: NIST AI Risk Management Framework (AI RMF 1.0, January 2023) - Govern, Map, Measure, Manage; and the Generative AI Profile (NIST AI 600-1) | C8: https://www.nist.gov/itl/ai-risk-management-framework
B9: OWASP Top 10 for Large Language Model Applications (2025) - referenced: LLM01 Prompt Injection, LLM02 Sensitive Information Disclosure, LLM05 Improper Output Handling, LLM06 Excessive Agency, LLM07 System Prompt Leakage, LLM08 Vector and Embedding Weaknesses, LLM09 Misinformation, LLM10 Unbounded Consumption | C9: https://genai.owasp.org/llm-top-10/
B11: Template by John Bommeraveni Joseph - ISO/IEC 27001, 42001 and 27701 Lead Auditor. Follow on LinkedIn for the free weekday newsletter GRC Made Simple Daily: linkedin.com/in/john-bj

Sheet Lists
B1: Lists (drop-down values)
B2: By John Bommeraveni Joseph | linkedin.com/in/john-bj | Free every weekday: GRC Made Simple Daily
A5: Answer | B5: Score | C5: Weight | D5: YesNo | E5: Tier | F5: Hosting | G5: AIActRole | H5: FUType | I5: FUStatus
A6: Yes | B6: 0 | C6: 1 | D6: Yes | E6: Tier 1 - Critical | F6: Vendor-hosted, vendor's own model | G6: Deployer | H6: Contract change | I6: Open
A7: Partial | B7: 1 | C7: 2 | D7: No | E7: Tier 2 - High | F7: Vendor-hosted, third-party model API | G7: Provider (Art. 25 may apply) | H7: Evidence requested | I7: In progress
A8: No | B8: 2 | C8: 3 | E8: Tier 3 - Moderate | F8: Hosted in our cloud tenant | G8: Importer | H8: Vendor remediation | I8: Closed
A9: N/A | B9: 3 | E9: Tier 4 - Low | F9: On-premises / self-hosted | G9: Distributor | H9: Configuration by us | I9: Risk accepted
F10: Mixed / per feature | G10: Not in scope | H10: Compensating control
F11: Unknown | G11: To assess | H11: Risk acceptance
