Workbook

Sheet Start here
B1: DPDP Act 2023 & DPDP Rules 2025 - Readiness Checklist
B2: By John Bommeraveni Joseph | linkedin.com/in/john-bj | Free every weekday: GRC Made Simple Daily
B5: What this is
B6: A working checklist for India's Digital Personal Data Protection Act, 2023 and the Digital Personal Data Protection Rules, 2025 (notified 13 November 2025). Every row cites the section of the Act and/or rule it comes from, says who the duty falls on, and when it comes into force under the phased commencement. Built for privacy, GRC and security teams in India and for companies outside India that serve people in India.
B7: Important
B8: This template is not legal advice. It supports, and does not replace, the official text of the Act and Rules or advice from qualified counsel. Requirement summaries are in our own words; where wording matters, read the Gazette text linked on the Sources tab. Other Indian laws and sector rules (for example CERT-In directions or a sector regulator's requirements) may impose separate obligations and shorter timelines - they are not covered here. Penalty amounts are maximums from the Act's Schedule. Not affiliated with MeitY or the Data Protection Board.
B9: How to use it (about half a day for a first pass)
B10: 1. Applicability Screen: answer the 13 questions. Your answers switch rows on or off in the Checklist ('Applies (from screen)' column).
B11: 2. Timeline: check the date the phased deadlines are counted from. The default is the Gazette date, 13 November 2025. Change it only if your counsel advises a different reading - every 'In force from' date follows it.
B12: 3. Checklist: for each row set Status, record where the evidence lives, name an owner, describe the gap, set a priority and a target date. Mark rows that do not apply 'Not applicable' and say why in the Gap column.
B13: 4. Read the Flags column: it warns about rows your screen says do not apply, duties already in force, target dates later than the date the duty applies, High priority rows with no owner, and 'Done' rows with no evidence.
B14: 5. Dashboard: readiness % by area, open High priority gaps, overdue items and days left to each deadline - the summary for your steering committee or board.
... B21: Version 1.0 - 27 October 2026. Texts checked against the official Gazette PDFs on 27 October 2026. Free to use and share with this credit kept.

Sheet Dashboard
B1: DPDP Readiness Dashboard
B2: By John Bommeraveni Joseph | linkedin.com/in/john-bj | Free every weekday: GRC Made Simple Daily
B5: Headline | C5: Value
B6: Days until Phase 2 (Consent Managers) | C6: =MAX(0,Timeline!$C$9-TODAY()) -> 17
B7: Days until Phase 3 (main obligations) | C7: =MAX(0,Timeline!$C$10-TODAY()) -> 198
B8: Overall readiness (Done / in scope) | C8: =I32 -> 0.01010101
B9: Open High priority gaps | C9: =COUNTIFS(Checklist!$A$6:$A$119,"<>",Checklist!$N$6:$N$119,"High",Checklist!$J$6:$J$119,"<>Done",Checklist!$J$6:$J$119,"<>Not applicable") -> 2
B10: Overdue items | C10: =COUNTIF(Checklist!$P$6:$P$119,"OVERDUE") -> 1
B11: Rows with a target date after the duty applies | C11: =COUNTIF(Checklist!$Q$6:$Q$119,"*Target date is after*") -> 0
B12: Rows marked Done with no evidence location | C12: =COUNTIF(Checklist!$Q$6:$Q$119,"*Done but no evidence*") -> 1
B13: Rows your screen says are not triggered (not yet N/A) | C13: =COUNTIF(Checklist!$Q$6:$Q$119,"*Screen says not triggered*") -> 0
B15: Area | C15: Requirements | D15: Not applicable | E15: In scope | F15: Done | G15: In progress | H15: Not started | I15: Readiness % | J15: Open High gaps | K15: Overdue
B16: Applicability and roles | C16: =COUNTIFS(Checklist!$B$6:$B$119,$B16,Checklist!$A$6:$A$119,"<>")+COUNTIFS(Checklist!$B$6:$B$119,$B16,Checklist!$A$6:$A$119,"",Checklist!$D$6:$D$119,"<>") -> 9 | D16: =COUNTIFS(Checklist!$B$6:$B$119,$B16,Checklist!$J$6:$J$119,"Not applicable") -> 0 | E16: =C16-D16 -> 9 | F16: =COUNTIFS(Checklist!$B$6:$B$119,$B16,Checklist!$J$6:$J$119,"Done") -> 0 | G16: =COUNTIFS(Checklist!$B$6:$B$119,$B16,Checklist!$J$6:$J$119,"In progress") -> 0 | H16: =E16-F16-G16 -> 9 | I16: =IF(E16=0,"",F16/E16) -> 0 | J16: =COUNTIFS(Checklist!$B$6:$B$119,$B16,Checklist!$N$6:$N$119,"High",Checklist!$J$6:$J$119,"<>Done",Checklist!$J$6:$J$119,"<>Not applicable") -> 0 | K16: =COUNTIFS(Checklist!$B$6:$B$119,$B16,Checklist!$P$6:$P$119,"OVERDUE") -> 0
B17: Notice | C17: =COUNTIFS(Checklist!$B$6:$B$119,$B17,Checklist!$A$6:$A$119,"<>")+COUNTIFS(Checklist!$B$6:$B$119,$B17,Checklist!$A$6:$A$119,"",Checklist!$D$6:$D$119,"<>") -> 6 | D17: =COUNTIFS(Checklist!$B$6:$B$119,$B17,Checklist!$J$6:$J$119,"Not applicable") -> 0 | E17: =C17-D17 -> 6 | F17: =COUNTIFS(Checklist!$B$6:$B$119,$B17,Checklist!$J$6:$J$119,"Done") -> 0 | G17: =COUNTIFS(Checklist!$B$6:$B$119,$B17,Checklist!$J$6:$J$119,"In progress") -> 1 | H17: =E17-F17-G17 -> 5 | I17: =IF(E17=0,"",F17/E17) -> 0 | J17: =COUNTIFS(Checklist!$B$6:$B$119,$B17,Checklist!$N$6:$N$119,"High",Checklist!$J$6:$J$119,"<>Done",Checklist!$J$6:$J$119,"<>Not applicable") -> 1 | K17: =COUNTIFS(Checklist!$B$6:$B$119,$B17,Checklist!$P$6:$P$119,"OVERDUE") -> 0
B18: Consent and withdrawal | C18: =COUNTIFS(Checklist!$B$6:$B$119,$B18,Checklist!$A$6:$A$119,"<>")+COUNTIFS(Checklist!$B$6:$B$119,$B18,Checklist!$A$6:$A$119,"",Checklist!$D$6:$D$119,"<>") -> 8 | D18: =COUNTIFS(Checklist!$B$6:$B$119,$B18,Checklist!$J$6:$J$119,"Not applicable") -> 0 | E18: =C18-D18 -> 8 | F18: =COUNTIFS(Checklist!$B$6:$B$119,$B18,Checklist!$J$6:$J$119,"Done") -> 0 | G18: =COUNTIFS(Checklist!$B$6:$B$119,$B18,Checklist!$J$6:$J$119,"In progress") -> 0 | H18: =E18-F18-G18 -> 8 | I18: =IF(E18=0,"",F18/E18) -> 0 | J18: =COUNTIFS(Checklist!$B$6:$B$119,$B18,Checklist!$N$6:$N$119,"High",Checklist!$J$6:$J$119,"<>Done",Checklist!$J$6:$J$119,"<>Not applicable") -> 0 | K18: =COUNTIFS(Checklist!$B$6:$B$119,$B18,Checklist!$P$6:$P$119,"OVERDUE") -> 0
B19: Legitimate uses | C19: =COUNTIFS(Checklist!$B$6:$B$119,$B19,Checklist!$A$6:$A$119,"<>")+COUNTIFS(Checklist!$B$6:$B$119,$B19,Checklist!$A$6:$A$119,"",Checklist!$D$6:$D$119,"<>") -> 5 | D19: =COUNTIFS(Checklist!$B$6:$B$119,$B19,Checklist!$J$6:$J$119,"Not applicable") -> 0 | E19: =C19-D19 -> 5 | F19: =COUNTIFS(Checklist!$B$6:$B$119,$B19,Checklist!$J$6:$J$119,"Done") -> 0 | G19: =COUNTIFS(Checklist!$B$6:$B$119,$B19,Checklist!$J$6:$J$119,"In progress") -> 0 | H19: =E19-F19-G19 -> 5 | I19: =IF(E19=0,"",F19/E19) -> 0 | J19: =COUNTIFS(Checklist!$B$6:$B$119,$B19,Checklist!$N$6:$N$119,"High",Checklist!$J$6:$J$119,"<>Done",Checklist!$J$6:$J$119,"<>Not applicable") -> 0 | K19: =COUNTIFS(Checklist!$B$6:$B$119,$B19,Checklist!$P$6:$P$119,"OVERDUE") -> 0
B20: Governance and data accuracy | C20: =COUNTIFS(Checklist!$B$6:$B$119,$B20,Checklist!$A$6:$A$119,"<>")+COUNTIFS(Checklist!$B$6:$B$119,$B20,Checklist!$A$6:$A$119,"",Checklist!$D$6:$D$119,"<>") -> 4 | D20: =COUNTIFS(Checklist!$B$6:$B$119,$B20,Checklist!$J$6:$J$119,"Not applicable") -> 0 | E20: =C20-D20 -> 4 | F20: =COUNTIFS(Checklist!$B$6:$B$119,$B20,Checklist!$J$6:$J$119,"Done") -> 0 | G20: =COUNTIFS(Checklist!$B$6:$B$119,$B20,Checklist!$J$6:$J$119,"In progress") -> 0 | H20: =E20-F20-G20 -> 4 | I20: =IF(E20=0,"",F20/E20) -> 0 | J20: =COUNTIFS(Checklist!$B$6:$B$119,$B20,Checklist!$N$6:$N$119,"High",Checklist!$J$6:$J$119,"<>Done",Checklist!$J$6:$J$119,"<>Not applicable") -> 0 | K20: =COUNTIFS(Checklist!$B$6:$B$119,$B20,Checklist!$P$6:$P$119,"OVERDUE") -> 0
B21: Security safeguards | C21: =COUNTIFS(Checklist!$B$6:$B$119,$B21,Checklist!$A$6:$A$119,"<>")+COUNTIFS(Checklist!$B$6:$B$119,$B21,Checklist!$A$6:$A$119,"",Checklist!$D$6:$D$119,"<>") -> 7 | D21: =COUNTIFS(Checklist!$B$6:$B$119,$B21,Checklist!$J$6:$J$119,"Not applicable") -> 0 | E21: =C21-D21 -> 7 | F21: =COUNTIFS(Checklist!$B$6:$B$119,$B21,Checklist!$J$6:$J$119,"Done") -> 0 | G21: =COUNTIFS(Checklist!$B$6:$B$119,$B21,Checklist!$J$6:$J$119,"In progress") -> 0 | H21: =E21-F21-G21 -> 7 | I21: =IF(E21=0,"",F21/E21) -> 0 | J21: =COUNTIFS(Checklist!$B$6:$B$119,$B21,Checklist!$N$6:$N$119,"High",Checklist!$J$6:$J$119,"<>Done",Checklist!$J$6:$J$119,"<>Not applicable") -> 0 | K21: =COUNTIFS(Checklist!$B$6:$B$119,$B21,Checklist!$P$6:$P$119,"OVERDUE") -> 0
B22: Breach intimation | C22: =COUNTIFS(Checklist!$B$6:$B$119,$B22,Checklist!$A$6:$A$119,"<>")+COUNTIFS(Checklist!$B$6:$B$119,$B22,Checklist!$A$6:$A$119,"",Checklist!$D$6:$D$119,"<>") -> 6 | D22: =COUNTIFS(Checklist!$B$6:$B$119,$B22,Checklist!$J$6:$J$119,"Not applicable") -> 0 | E22: =C22-D22 -> 6 | F22: =COUNTIFS(Checklist!$B$6:$B$119,$B22,Checklist!$J$6:$J$119,"Done") -> 0 | G22: =COUNTIFS(Checklist!$B$6:$B$119,$B22,Checklist!$J$6:$J$119,"In progress") -> 0 | H22: =E22-F22-G22 -> 6 | I22: =IF(E22=0,"",F22/E22) -> 0 | J22: =COUNTIFS(Checklist!$B$6:$B$119,$B22,Checklist!$N$6:$N$119,"High",Checklist!$J$6:$J$119,"<>Done",Checklist!$J$6:$J$119,"<>Not applicable") -> 1 | K22: =COUNTIFS(Checklist!$B$6:$B$119,$B22,Checklist!$P$6:$P$119,"OVERDUE") -> 1
B23: Retention and erasure | C23: =COUNTIFS(Checklist!$B$6:$B$119,$B23,Checklist!$A$6:$A$119,"<>")+COUNTIFS(Checklist!$B$6:$B$119,$B23,Checklist!$A$6:$A$119,"",Checklist!$D$6:$D$119,"<>") -> 6 | D23: =COUNTIFS(Checklist!$B$6:$B$119,$B23,Checklist!$J$6:$J$119,"Not applicable") -> 0 | E23: =C23-D23 -> 6 | F23: =COUNTIFS(Checklist!$B$6:$B$119,$B23,Checklist!$J$6:$J$119,"Done") -> 0 | G23: =COUNTIFS(Checklist!$B$6:$B$119,$B23,Checklist!$J$6:$J$119,"In progress") -> 0 | H23: =E23-F23-G23 -> 6 | I23: =IF(E23=0,"",F23/E23) -> 0 | J23: =COUNTIFS(Checklist!$B$6:$B$119,$B23,Checklist!$N$6:$N$119,"High",Checklist!$J$6:$J$119,"<>Done",Checklist!$J$6:$J$119,"<>Not applicable") -> 0 | K23: =COUNTIFS(Checklist!$B$6:$B$119,$B23,Checklist!$P$6:$P$119,"OVERDUE") -> 0
B24: Contact and grievance | C24: =COUNTIFS(Checklist!$B$6:$B$119,$B24,Checklist!$A$6:$A$119,"<>")+COUNTIFS(Checklist!$B$6:$B$119,$B24,Checklist!$A$6:$A$119,"",Checklist!$D$6:$D$119,"<>") -> 5 | D24: =COUNTIFS(Checklist!$B$6:$B$119,$B24,Checklist!$J$6:$J$119,"Not applicable") -> 0 | E24: =C24-D24 -> 5 | F24: =COUNTIFS(Checklist!$B$6:$B$119,$B24,Checklist!$J$6:$J$119,"Done") -> 1 | G24: =COUNTIFS(Checklist!$B$6:$B$119,$B24,Checklist!$J$6:$J$119,"In progress") -> 0 | H24: =E24-F24-G24 -> 4 | I24: =IF(E24=0,"",F24/E24) -> 0.2 | J24: =COUNTIFS(Checklist!$B$6:$B$119,$B24,Checklist!$N$6:$N$119,"High",Checklist!$J$6:$J$119,"<>Done",Checklist!$J$6:$J$119,"<>Not applicable") -> 0 | K24: =COUNTIFS(Checklist!$B$6:$B$119,$B24,Checklist!$P$6:$P$119,"OVERDUE") -> 0
B25: Data Processors and contracts | C25: =COUNTIFS(Checklist!$B$6:$B$119,$B25,Checklist!$A$6:$A$119,"<>")+COUNTIFS(Checklist!$B$6:$B$119,$B25,Checklist!$A$6:$A$119,"",Checklist!$D$6:$D$119,"<>") -> 6 | D25: =COUNTIFS(Checklist!$B$6:$B$119,$B25,Checklist!$J$6:$J$119,"Not applicable") -> 0 | E25: =C25-D25 -> 6 | F25: =COUNTIFS(Checklist!$B$6:$B$119,$B25,Checklist!$J$6:$J$119,"Done") -> 0 | G25: =COUNTIFS(Checklist!$B$6:$B$119,$B25,Checklist!$J$6:$J$119,"In progress") -> 0 | H25: =E25-F25-G25 -> 6 | I25: =IF(E25=0,"",F25/E25) -> 0 | J25: =COUNTIFS(Checklist!$B$6:$B$119,$B25,Checklist!$N$6:$N$119,"High",Checklist!$J$6:$J$119,"<>Done",Checklist!$J$6:$J$119,"<>Not applicable") -> 0 | K25: =COUNTIFS(Checklist!$B$6:$B$119,$B25,Checklist!$P$6:$P$119,"OVERDUE") -> 0
B26: Children and persons with disability | C26: =COUNTIFS(Checklist!$B$6:$B$119,$B26,Checklist!$A$6:$A$119,"<>")+COUNTIFS(Checklist!$B$6:$B$119,$B26,Checklist!$A$6:$A$119,"",Checklist!$D$6:$D$119,"<>") -> 7 | D26: =COUNTIFS(Checklist!$B$6:$B$119,$B26,Checklist!$J$6:$J$119,"Not applicable") -> 0 | E26: =C26-D26 -> 7 | F26: =COUNTIFS(Checklist!$B$6:$B$119,$B26,Checklist!$J$6:$J$119,"Done") -> 0 | G26: =COUNTIFS(Checklist!$B$6:$B$119,$B26,Checklist!$J$6:$J$119,"In progress") -> 0 | H26: =E26-F26-G26 -> 7 | I26: =IF(E26=0,"",F26/E26) -> 0 | J26: =COUNTIFS(Checklist!$B$6:$B$119,$B26,Checklist!$N$6:$N$119,"High",Checklist!$J$6:$J$119,"<>Done",Checklist!$J$6:$J$119,"<>Not applicable") -> 0 | K26: =COUNTIFS(Checklist!$B$6:$B$119,$B26,Checklist!$P$6:$P$119,"OVERDUE") -> 0
B27: Significant Data Fiduciary | C27: =COUNTIFS(Checklist!$B$6:$B$119,$B27,Checklist!$A$6:$A$119,"<>")+COUNTIFS(Checklist!$B$6:$B$119,$B27,Checklist!$A$6:$A$119,"",Checklist!$D$6:$D$119,"<>") -> 7 | D27: =COUNTIFS(Checklist!$B$6:$B$119,$B27,Checklist!$J$6:$J$119,"Not applicable") -> 0 | E27: =C27-D27 -> 7 | F27: =COUNTIFS(Checklist!$B$6:$B$119,$B27,Checklist!$J$6:$J$119,"Done") -> 0 | G27: =COUNTIFS(Checklist!$B$6:$B$119,$B27,Checklist!$J$6:$J$119,"In progress") -> 0 | H27: =E27-F27-G27 -> 7 | I27: =IF(E27=0,"",F27/E27) -> 0 | J27: =COUNTIFS(Checklist!$B$6:$B$119,$B27,Checklist!$N$6:$N$119,"High",Checklist!$J$6:$J$119,"<>Done",Checklist!$J$6:$J$119,"<>Not applicable") -> 0 | K27: =COUNTIFS(Checklist!$B$6:$B$119,$B27,Checklist!$P$6:$P$119,"OVERDUE") -> 0
... B31: Records and information requests | C31: =COUNTIFS(Checklist!$B$6:$B$119,$B31,Checklist!$A$6:$A$119,"<>")+COUNTIFS(Checklist!$B$6:$B$119,$B31,Checklist!$A$6:$A$119,"",Checklist!$D$6:$D$119,"<>") -> 3 | D31: =COUNTIFS(Checklist!$B$6:$B$119,$B31,Checklist!$J$6:$J$119,"Not applicable") -> 0 | E31: =C31-D31 -> 3 | F31: =COUNTIFS(Checklist!$B$6:$B$119,$B31,Checklist!$J$6:$J$119,"Done") -> 0 | G31: =COUNTIFS(Checklist!$B$6:$B$119,$B31,Checklist!$J$6:$J$119,"In progress") -> 0 | H31: =E31-F31-G31 -> 3 | I31: =IF(E31=0,"",F31/E31) -> 0 | J31: =COUNTIFS(Checklist!$B$6:$B$119,$B31,Checklist!$N$6:$N$119,"High",Checklist!$J$6:$J$119,"<>Done",Checklist!$J$6:$J$119,"<>Not applicable") -> 0 | K31: =COUNTIFS(Checklist!$B$6:$B$119,$B31,Checklist!$P$6:$P$119,"OVERDUE") -> 0
B32: Total | C32: =SUM(C16:C31) -> 99 | D32: =SUM(D16:D31) -> 0 | E32: =SUM(E16:E31) -> 99 | F32: =SUM(F16:F31) -> 1 | G32: =SUM(G16:G31) -> 1 | H32: =SUM(H16:H31) -> 97 | I32: =IF(E32=0,"",F32/E32) -> 0.01010101 | J32: =SUM(J16:J31) -> 2 | K32: =SUM(K16:K31) -> 1
B34: First 10 open High priority gaps (in Checklist order)
B35: # | C35: ID | D35: Area | F35: Owner | H35: Target date | J35: Overdue?
B36: 1 | C36: =IFERROR(INDEX(Checklist!$A$6:$A$119,MATCH(1,Checklist!$R$6:$R$119,0)),"") -> NOT-01 | D36: =IFERROR(INDEX(Checklist!$B$6:$B$119,MATCH(1,Checklist!$R$6:$R$119,0)),"") -> Notice | F36: =IFERROR(IF(INDEX(Checklist!$L$6:$L$119,MATCH(1,Checklist!$R$6:$R$119,0))="","(no owner)",INDEX(Checklist!$L$6:$L$119,MATCH(1,Checklist!$R$6:$R$119,0))),"") -> Head of Privacy | H36: =IFERROR(IF(INDEX(Checklist!$O$6:$O$119,MATCH(1,Checklist!$R$6:$R$119,0))="","",INDEX(Checklist!$O$6:$O$119,MATCH(1,Checklist!$R$6:$R$119,0))),"") -> 46418 | J36: =IFERROR(INDEX(Checklist!$P$6:$P$119,MATCH(1,Checklist!$R$6:$R$119,0)),"")
B37: 2 | C37: =IFERROR(INDEX(Checklist!$A$6:$A$119,MATCH(2,Checklist!$R$6:$R$119,0)),"") -> BRE-05 | D37: =IFERROR(INDEX(Checklist!$B$6:$B$119,MATCH(2,Checklist!$R$6:$R$119,0)),"") -> Breach intimation | F37: =IFERROR(IF(INDEX(Checklist!$L$6:$L$119,MATCH(2,Checklist!$R$6:$R$119,0))="","(no owner)",INDEX(Checklist!$L$6:$L$119,MATCH(2,Checklist!$R$6:$R$119,0))),"") -> (no owner) | H37: =IFERROR(IF(INDEX(Checklist!$O$6:$O$119,MATCH(2,Checklist!$R$6:$R$119,0))="","",INDEX(Checklist!$O$6:$O$119,MATCH(2,Checklist!$R$6:$R$119,0))),"") -> 46295 | J37: =IFERROR(INDEX(Checklist!$P$6:$P$119,MATCH(2,Checklist!$R$6:$R$119,0)),"") -> OVERDUE
B38: 3 | C38: =IFERROR(INDEX(Checklist!$A$6:$A$119,MATCH(3,Checklist!$R$6:$R$119,0)),"") | D38: =IFERROR(INDEX(Checklist!$B$6:$B$119,MATCH(3,Checklist!$R$6:$R$119,0)),"") | F38: =IFERROR(IF(INDEX(Checklist!$L$6:$L$119,MATCH(3,Checklist!$R$6:$R$119,0))="","(no owner)",INDEX(Checklist!$L$6:$L$119,MATCH(3,Checklist!$R$6:$R$119,0))),"") | H38: =IFERROR(IF(INDEX(Checklist!$O$6:$O$119,MATCH(3,Checklist!$R$6:$R$119,0))="","",INDEX(Checklist!$O$6:$O$119,MATCH(3,Checklist!$R$6:$R$119,0))),"") | J38: =IFERROR(INDEX(Checklist!$P$6:$P$119,MATCH(3,Checklist!$R$6:$R$119,0)),"")
B39: 4 | C39: =IFERROR(INDEX(Checklist!$A$6:$A$119,MATCH(4,Checklist!$R$6:$R$119,0)),"") | D39: =IFERROR(INDEX(Checklist!$B$6:$B$119,MATCH(4,Checklist!$R$6:$R$119,0)),"") | F39: =IFERROR(IF(INDEX(Checklist!$L$6:$L$119,MATCH(4,Checklist!$R$6:$R$119,0))="","(no owner)",INDEX(Checklist!$L$6:$L$119,MATCH(4,Checklist!$R$6:$R$119,0))),"") | H39: =IFERROR(IF(INDEX(Checklist!$O$6:$O$119,MATCH(4,Checklist!$R$6:$R$119,0))="","",INDEX(Checklist!$O$6:$O$119,MATCH(4,Checklist!$R$6:$R$119,0))),"") | J39: =IFERROR(INDEX(Checklist!$P$6:$P$119,MATCH(4,Checklist!$R$6:$R$119,0)),"")
B40: 5 | C40: =IFERROR(INDEX(Checklist!$A$6:$A$119,MATCH(5,Checklist!$R$6:$R$119,0)),"") | D40: =IFERROR(INDEX(Checklist!$B$6:$B$119,MATCH(5,Checklist!$R$6:$R$119,0)),"") | F40: =IFERROR(IF(INDEX(Checklist!$L$6:$L$119,MATCH(5,Checklist!$R$6:$R$119,0))="","(no owner)",INDEX(Checklist!$L$6:$L$119,MATCH(5,Checklist!$R$6:$R$119,0))),"") | H40: =IFERROR(IF(INDEX(Checklist!$O$6:$O$119,MATCH(5,Checklist!$R$6:$R$119,0))="","",INDEX(Checklist!$O$6:$O$119,MATCH(5,Checklist!$R$6:$R$119,0))),"") | J40: =IFERROR(INDEX(Checklist!$P$6:$P$119,MATCH(5,Checklist!$R$6:$R$119,0)),"")
B41: 6 | C41: =IFERROR(INDEX(Checklist!$A$6:$A$119,MATCH(6,Checklist!$R$6:$R$119,0)),"") | D41: =IFERROR(INDEX(Checklist!$B$6:$B$119,MATCH(6,Checklist!$R$6:$R$119,0)),"") | F41: =IFERROR(IF(INDEX(Checklist!$L$6:$L$119,MATCH(6,Checklist!$R$6:$R$119,0))="","(no owner)",INDEX(Checklist!$L$6:$L$119,MATCH(6,Checklist!$R$6:$R$119,0))),"") | H41: =IFERROR(IF(INDEX(Checklist!$O$6:$O$119,MATCH(6,Checklist!$R$6:$R$119,0))="","",INDEX(Checklist!$O$6:$O$119,MATCH(6,Checklist!$R$6:$R$119,0))),"") | J41: =IFERROR(INDEX(Checklist!$P$6:$P$119,MATCH(6,Checklist!$R$6:$R$119,0)),"")
B42: 7 | C42: =IFERROR(INDEX(Checklist!$A$6:$A$119,MATCH(7,Checklist!$R$6:$R$119,0)),"") | D42: =IFERROR(INDEX(Checklist!$B$6:$B$119,MATCH(7,Checklist!$R$6:$R$119,0)),"") | F42: =IFERROR(IF(INDEX(Checklist!$L$6:$L$119,MATCH(7,Checklist!$R$6:$R$119,0))="","(no owner)",INDEX(Checklist!$L$6:$L$119,MATCH(7,Checklist!$R$6:$R$119,0))),"") | H42: =IFERROR(IF(INDEX(Checklist!$O$6:$O$119,MATCH(7,Checklist!$R$6:$R$119,0))="","",INDEX(Checklist!$O$6:$O$119,MATCH(7,Checklist!$R$6:$R$119,0))),"") | J42: =IFERROR(INDEX(Checklist!$P$6:$P$119,MATCH(7,Checklist!$R$6:$R$119,0)),"")
B43: 8 | C43: =IFERROR(INDEX(Checklist!$A$6:$A$119,MATCH(8,Checklist!$R$6:$R$119,0)),"") | D43: =IFERROR(INDEX(Checklist!$B$6:$B$119,MATCH(8,Checklist!$R$6:$R$119,0)),"") | F43: =IFERROR(IF(INDEX(Checklist!$L$6:$L$119,MATCH(8,Checklist!$R$6:$R$119,0))="","(no owner)",INDEX(Checklist!$L$6:$L$119,MATCH(8,Checklist!$R$6:$R$119,0))),"") | H43: =IFERROR(IF(INDEX(Checklist!$O$6:$O$119,MATCH(8,Checklist!$R$6:$R$119,0))="","",INDEX(Checklist!$O$6:$O$119,MATCH(8,Checklist!$R$6:$R$119,0))),"") | J43: =IFERROR(INDEX(Checklist!$P$6:$P$119,MATCH(8,Checklist!$R$6:$R$119,0)),"")
B44: 9 | C44: =IFERROR(INDEX(Checklist!$A$6:$A$119,MATCH(9,Checklist!$R$6:$R$119,0)),"") | D44: =IFERROR(INDEX(Checklist!$B$6:$B$119,MATCH(9,Checklist!$R$6:$R$119,0)),"") | F44: =IFERROR(IF(INDEX(Checklist!$L$6:$L$119,MATCH(9,Checklist!$R$6:$R$119,0))="","(no owner)",INDEX(Checklist!$L$6:$L$119,MATCH(9,Checklist!$R$6:$R$119,0))),"") | H44: =IFERROR(IF(INDEX(Checklist!$O$6:$O$119,MATCH(9,Checklist!$R$6:$R$119,0))="","",INDEX(Checklist!$O$6:$O$119,MATCH(9,Checklist!$R$6:$R$119,0))),"") | J44: =IFERROR(INDEX(Checklist!$P$6:$P$119,MATCH(9,Checklist!$R$6:$R$119,0)),"")
B45: 10 | C45: =IFERROR(INDEX(Checklist!$A$6:$A$119,MATCH(10,Checklist!$R$6:$R$119,0)),"") | D45: =IFERROR(INDEX(Checklist!$B$6:$B$119,MATCH(10,Checklist!$R$6:$R$119,0)),"") | F45: =IFERROR(IF(INDEX(Checklist!$L$6:$L$119,MATCH(10,Checklist!$R$6:$R$119,0))="","(no owner)",INDEX(Checklist!$L$6:$L$119,MATCH(10,Checklist!$R$6:$R$119,0))),"") | H45: =IFERROR(IF(INDEX(Checklist!$O$6:$O$119,MATCH(10,Checklist!$R$6:$R$119,0))="","",INDEX(Checklist!$O$6:$O$119,MATCH(10,Checklist!$R$6:$R$119,0))),"") | J45: =IFERROR(INDEX(Checklist!$P$6:$P$119,MATCH(10,Checklist!$R$6:$R$119,0)),"")
B47: Red = needs action. Readiness % = Done / (requirements - Not applicable); blank status counts as Not started. The worked examples on NOT-01, BRE-05 and CGR-01 are counted until you clear them.

Sheet Applicability Screen
B1: Applicability Screen
B2: By John Bommeraveni Joseph | linkedin.com/in/john-bj | Free every weekday: GRC Made Simple Daily
C5: Overall result | F5: =IF(COUNTA(E8:E20)<13,"Answer all 13 questions",IF(E10="Yes","Likely excluded under s.3(c)(i) - record your reasoning",IF(OR(E8<>"No",E9<>"No"),"In scope - work through the Checklist","Likely out of scope - record your reasoning and re-check yearly"))) -> Answer all 13 questions
B7: No. | C7: Question | D7: Reference | E7: Your answer | F7: What it means | G7: Key
B8: 1 | C8: Do you process personal data in digital form in India - collected digitally, or collected on paper and digitised later? | D8: s.3(a) | F8: =IF(E8="","Answer this question",IF(E8="Yes","In scope under s.3(a).",IF(E8="No","Not in scope through s.3(a) - check the next question.","Not sure - treat as Yes until confirmed."))) -> Answer this question | G8: IN_INDIA
B9: 2 | C9: Do you process digital personal data outside India in connection with offering goods or services to people in India? | D9: s.3(b) | F9: =IF(E9="","Answer this question",IF(E9="Yes","In scope under s.3(b), even though processing happens outside India.",IF(E9="No","Not in scope through s.3(b).","Not sure - treat as Yes until confirmed."))) -> Answer this question | G9: OUTSIDE
B10: 3 | C10: Is ALL of your processing done by an individual for purely personal or domestic purposes? | D10: s.3(c)(i) | F10: =IF(E10="","Answer this question",IF(E10="Yes","Likely excluded - record your reasoning.",IF(E10="No","The personal / domestic exclusion does not help you.","Not sure - treat as Yes until confirmed."))) -> Answer this question | G10: DOMESTIC
B11: 4 | C11: Do you decide, alone or with others, why and how personal data is processed (Data Fiduciary)? | D11: s.2(i) | F11: =IF(E11="","Answer this question",IF(E11="Yes","You are a Data Fiduciary - most rows apply to you.",IF(E11="No","Rows marked DF will show as not triggered - confirm before marking N/A.","Not sure - treat as Yes until confirmed."))) -> Answer this question | G11: DF
B12: 5 | C12: Do you process personal data on behalf of another organisation (Data Processor)? | D12: s.2(k), s.8(2) | F12: =IF(E12="","Answer this question",IF(E12="Yes","Expect your customers to pass DPDP duties to you by contract.",IF(E12="No","Processor-only rows not triggered.","Not sure - treat as Yes until confirmed."))) -> Answer this question | G12: PROC
B13: 6 | C13: Has the Central Government notified you, or a class you belong to, as a Significant Data Fiduciary? | D13: s.10(1) | F13: =IF(E13="","Answer this question",IF(E13="Yes","Significant Data Fiduciary rows apply.",IF(E13="No","SDF rows not triggered - keep watching the Gazette.","Not sure - treat as Yes until confirmed."))) -> Answer this question | G13: SDF
B14: 7 | C14: Do you process personal data of children (individuals under 18)? | D14: s.2(f), s.9 | F14: =IF(E14="","Answer this question",IF(E14="Yes","Children rows apply.",IF(E14="No","Children rows not triggered - check how you know users are adults.","Not sure - treat as Yes until confirmed."))) -> Answer this question | G14: CHILD
B15: 8 | C15: Do you process personal data of persons with disability who have a lawful guardian? | D15: s.9(1), r.11 | F15: =IF(E15="","Answer this question",IF(E15="Yes","Lawful-guardian consent rows apply.",IF(E15="No","Guardian row not triggered.","Not sure - treat as Yes until confirmed."))) -> Answer this question | G15: PWD
B16: 9 | C16: Are you an e-commerce entity with 2 crore+ registered users in India, an online gaming intermediary with 50 lakh+, or a social media intermediary with 2 crore+? | D16: r.8(1), Third Schedule | F16: =IF(E16="","Answer this question",IF(E16="Yes","Fixed three-year inactivity erasure and 48-hour warning apply.",IF(E16="No","Third Schedule erasure rows not triggered.","Not sure - treat as Yes until confirmed."))) -> Answer this question | G16: THIRD
B17: 10 | C17: Do you transfer personal data outside India, including cloud hosting, offshore support or vendor access? | D17: s.16, r.15 | F17: =IF(E17="","Answer this question",IF(E17="Yes","Cross-border rows apply.",IF(E17="No","Cross-border rows not triggered - check vendor and cloud regions first.","Not sure - treat as Yes until confirmed."))) -> Answer this question | G17: XB
B18: 11 | C18: Do you operate, or plan to operate, as a Consent Manager registered with the Board? | D18: s.6(9), r.4 | F18: =IF(E18="","Answer this question",IF(E18="Yes","Consent Manager rows apply (in force earlier than most rows).",IF(E18="No","Consent Manager rows not triggered.","Not sure - treat as Yes until confirmed."))) -> Answer this question | G18: CM
B19: 12 | C19: Do you rely on an exemption under s.17 or a Government notification under s.17(3) or s.17(5)? | D19: s.17 | F19: =IF(E19="","Answer this question",IF(E19="Yes","Document the exemption, its scope and evidence.",IF(E19="No","No exemption relied on.","Not sure - treat as Yes until confirmed."))) -> Answer this question | G19: EXEMPT
B20: 13 | C20: Are you the State or an instrumentality of the State processing for subsidies, benefits, services, certificates, licences or permits? | D20: s.7(b), r.5 | F20: =IF(E20="","Answer this question",IF(E20="Yes","State legitimate-use row applies.",IF(E20="No","State row not triggered.","Not sure - treat as Yes until confirmed."))) -> Answer this question | G20: STATE
C22: 'Not sure' counts as Yes for scope. The Key column links each answer to Checklist rows.

Sheet Checklist
B1: DPDP Readiness Checklist
B2: By John Bommeraveni Joseph | linkedin.com/in/john-bj | Free every weekday: GRC Made Simple Daily
A5: ID | B5: Area | C5: Reference (Act s. / Rule r.) | D5: Requirement (our summary - read the official text) | E5: Applies to | F5: Phase | G5: In force from | H5: Screen key | I5: Applies (from screen) | J5: Status | K5: Evidence location | L5: Owner | M5: Gap / notes | N5: Priority | O5: Target date | P5: Overdue? | Q5: Flags | R5: Open High #
A6: APP-01 | B6: Applicability and roles | C6: s.3(a), s.3(b) | D6: Confirm and record whether the Act applies to you: digital personal data processed in India (collected digitally, or collected in non-digital form and digitised later), or processed outside India in connection with offering goods or services to Data Principals in India. | E6: Any person processing digital personal data | F6: 3 | G6: =IF(F6="","",INDEX(Timeline!$C$8:$C$10,F6)) -> 46520 | H6: ALL | I6: =IF(H6="","",IF(H6="ALL","Yes",IF(IFERROR(INDEX('Applicability Screen'!$E$8:$E$20,MATCH(H6,'Applicability Screen'!$G$8:$G$20,0)),"")="","Answer screen",INDEX('Applicability Screen'!$E$8:$E$20,MATCH(H6,'Applicability Screen'!$G$8:$G$20,0))))) -> Yes | P6: =IF(OR(O6="",J6="Done",J6="Not applicable"),"",IF(O6<TODAY(),"OVERDUE","")) | Q6: =IF(AND(A6="",D6=""),"",IF(AND(I6="No",J6<>"Not applicable"),"Screen says not triggered - confirm or mark Not applicable. ","")&IF(AND(G6<>"",J6<>"Done",J6<>"Not applicable",G6<=TODAY()),"Duty already in force. ","")&IF(AND(O6<>"",G6<>"",J6<>"Done",J6<>"Not applicable",O6>G6),"Target date is after the duty applies. ","")&IF(AND(N6="High",L6="",J6<>"Done",J6<>"Not applicable"),"High priority with no owner. ","")&IF(AND(J6="Done",K6=""),"Done but no evidence location. ","")&IF(AND(J6="Not applicable",M6=""),"Say why it is not applicable. ","")) | R6: =IF(AND(A6<>"",N6="High",J6<>"Done",J6<>"Not applicable"),COUNTIFS($A$6:A6,"<>",$N$6:N6,"High",$J$6:J6,"<>Done",$J$6:J6,"<>Not applicable"),"")
A7: APP-02 | B7: Applicability and roles | C7: s.3(c) | D7: If you rely on an exclusion, record which and keep the evidence: processing by an individual for a personal or domestic purpose; or personal data made publicly available by the Data Principal herself, or by a person obliged under Indian law to publish it. | E7: Any person processing digital personal data | F7: 3 | G7: =IF(F7="","",INDEX(Timeline!$C$8:$C$10,F7)) -> 46520 | H7: ALL | I7: =IF(H7="","",IF(H7="ALL","Yes",IF(IFERROR(INDEX('Applicability Screen'!$E$8:$E$20,MATCH(H7,'Applicability Screen'!$G$8:$G$20,0)),"")="","Answer screen",INDEX('Applicability Screen'!$E$8:$E$20,MATCH(H7,'Applicability Screen'!$G$8:$G$20,0))))) -> Yes | P7: =IF(OR(O7="",J7="Done",J7="Not applicable"),"",IF(O7<TODAY(),"OVERDUE","")) | Q7: =IF(AND(A7="",D7=""),"",IF(AND(I7="No",J7<>"Not applicable"),"Screen says not triggered - confirm or mark Not applicable. ","")&IF(AND(G7<>"",J7<>"Done",J7<>"Not applicable",G7<=TODAY()),"Duty already in force. ","")&IF(AND(O7<>"",G7<>"",J7<>"Done",J7<>"Not applicable",O7>G7),"Target date is after the duty applies. ","")&IF(AND(N7="High",L7="",J7<>"Done",J7<>"Not applicable"),"High priority with no owner. ","")&IF(AND(J7="Done",K7=""),"Done but no evidence location. ","")&IF(AND(J7="Not applicable",M7=""),"Say why it is not applicable. ","")) | R7: =IF(AND(A7<>"",N7="High",J7<>"Done",J7<>"Not applicable"),COUNTIFS($A$6:A7,"<>",$N$6:N7,"High",$J$6:J7,"<>Done",$J$6:J7,"<>Not applicable"),"")
A8: APP-03 | B8: Applicability and roles | C8: s.2(i), s.2(k) | D8: For each processing activity, record your role: Data Fiduciary (you alone or with others decide the purpose and means) or Data Processor (you process on behalf of a Data Fiduciary). | E8: Any person processing digital personal data | F8: 1 | G8: =IF(F8="","",INDEX(Timeline!$C$8:$C$10,F8)) -> 45974 | H8: ALL | I8: =IF(H8="","",IF(H8="ALL","Yes",IF(IFERROR(INDEX('Applicability Screen'!$E$8:$E$20,MATCH(H8,'Applicability Screen'!$G$8:$G$20,0)),"")="","Answer screen",INDEX('Applicability Screen'!$E$8:$E$20,MATCH(H8,'Applicability Screen'!$G$8:$G$20,0))))) -> Yes | P8: =IF(OR(O8="",J8="Done",J8="Not applicable"),"",IF(O8<TODAY(),"OVERDUE","")) | Q8: =IF(AND(A8="",D8=""),"",IF(AND(I8="No",J8<>"Not applicable"),"Screen says not triggered - confirm or mark Not applicable. ","")&IF(AND(G8<>"",J8<>"Done",J8<>"Not applicable",G8<=TODAY()),"Duty already in force. ","")&IF(AND(O8<>"",G8<>"",J8<>"Done",J8<>"Not applicable",O8>G8),"Target date is after the duty applies. ","")&IF(AND(N8="High",L8="",J8<>"Done",J8<>"Not applicable"),"High priority with no owner. ","")&IF(AND(J8="Done",K8=""),"Done but no evidence location. ","")&IF(AND(J8="Not applicable",M8=""),"Say why it is not applicable. ","")) -> Duty already in force. | R8: =IF(AND(A8<>"",N8="High",J8<>"Done",J8<>"Not applicable"),COUNTIFS($A$6:A8,"<>",$N$6:N8,"High",$J$6:J8,"<>Done",$J$6:J8,"<>Not applicable"),"")
A9: APP-04 | B9: Applicability and roles | C9: s.4(1), s.4(2) | D9: For each processing activity, record the ground relied on - consent, or one of the 'certain legitimate uses' in s.7 - and confirm the purpose is lawful (not expressly forbidden by law). | E9: Data Fiduciary | F9: 3 | G9: =IF(F9="","",INDEX(Timeline!$C$8:$C$10,F9)) -> 46520 | H9: DF | I9: =IF(H9="","",IF(H9="ALL","Yes",IF(IFERROR(INDEX('Applicability Screen'!$E$8:$E$20,MATCH(H9,'Applicability Screen'!$G$8:$G$20,0)),"")="","Answer screen",INDEX('Applicability Screen'!$E$8:$E$20,MATCH(H9,'Applicability Screen'!$G$8:$G$20,0))))) -> Answer screen | P9: =IF(OR(O9="",J9="Done",J9="Not applicable"),"",IF(O9<TODAY(),"OVERDUE","")) | Q9: =IF(AND(A9="",D9=""),"",IF(AND(I9="No",J9<>"Not applicable"),"Screen says not triggered - confirm or mark Not applicable. ","")&IF(AND(G9<>"",J9<>"Done",J9<>"Not applicable",G9<=TODAY()),"Duty already in force. ","")&IF(AND(O9<>"",G9<>"",J9<>"Done",J9<>"Not applicable",O9>G9),"Target date is after the duty applies. ","")&IF(AND(N9="High",L9="",J9<>"Done",J9<>"Not applicable"),"High priority with no owner. ","")&IF(AND(J9="Done",K9=""),"Done but no evidence location. ","")&IF(AND(J9="Not applicable",M9=""),"Say why it is not applicable. ","")) | R9: =IF(AND(A9<>"",N9="High",J9<>"Done",J9<>"Not applicable"),COUNTIFS($A$6:A9,"<>",$N$6:N9,"High",$J$6:J9,"<>Done",$J$6:J9,"<>Not applicable"),"")
A10: APP-05 | B10: Applicability and roles | C10: s.17(1) | D10: If you rely on a s.17(1) exemption (enforcing a legal right or claim; judicial, quasi-judicial, regulatory or supervisory bodies; offences and contraventions; personal data of people outside India processed under a contract with a person outside India; court-approved mergers, demergers and similar schemes; financial information of a loan defaulter), document which one and why. Chapter II except s.8(1) and s.8(5), Chapter III and s.16 do not apply to that processing - accountability and security safeguards still do. | E10: Data Fiduciary | F10: 3 | G10: =IF(F10="","",INDEX(Timeline!$C$8:$C$10,F10)) -> 46520 | H10: EXEMPT | I10: =IF(H10="","",IF(H10="ALL","Yes",IF(IFERROR(INDEX('Applicability Screen'!$E$8:$E$20,MATCH(H10,'Applicability Screen'!$G$8:$G$20,0)),"")="","Answer screen",INDEX('Applicability Screen'!$E$8:$E$20,MATCH(H10,'Applicability Screen'!$G$8:$G$20,0))))) -> Answer screen | P10: =IF(OR(O10="",J10="Done",J10="Not applicable"),"",IF(O10<TODAY(),"OVERDUE","")) | Q10: =IF(AND(A10="",D10=""),"",IF(AND(I10="No",J10<>"Not applicable"),"Screen says not triggered - confirm or mark Not applicable. ","")&IF(AND(G10<>"",J10<>"Done",J10<>"Not applicable",G10<=TODAY()),"Duty already in force. ","")&IF(AND(O10<>"",G10<>"",J10<>"Done",J10<>"Not applicable",O10>G10),"Target date is after the duty applies. ","")&IF(AND(N10="High",L10="",J10<>"Done",J10<>"Not applicable"),"High priority with no owner. ","")&IF(AND(J10="Done",K10=""),"Done but no evidence location. ","")&IF(AND(J10="Not applicable",M10=""),"Say why it is not applicable. ","")) | R10: =IF(AND(A10<>"",N10="High",J10<>"Done",J10<>"Not applicable"),COUNTIFS($A$6:A10,"<>",$N$6:N10,"High",$J$6:J10,"<>Done",$J$6:J10,"<>Not applicable"),"")
A11: APP-06 | B11: Applicability and roles | C11: s.17(2)(b), r.16, Second Schedule | D11: Processing necessary for research, archiving or statistical purposes falls outside the Act only if the data is not used to take a decision specific to a Data Principal and the processing follows the Second Schedule standards (lawful; limited to the purpose and to necessary data; reasonable efforts on accuracy; retention limited; reasonable security safeguards; accountability). Document conformance if you rely on it. | E11: Data Fiduciary | F11: 3 | G11: =IF(F11="","",INDEX(Timeline!$C$8:$C$10,F11)) -> 46520 | H11: EXEMPT | I11: =IF(H11="","",IF(H11="ALL","Yes",IF(IFERROR(INDEX('Applicability Screen'!$E$8:$E$20,MATCH(H11,'Applicability Screen'!$G$8:$G$20,0)),"")="","Answer screen",INDEX('Applicability Screen'!$E$8:$E$20,MATCH(H11,'Applicability Screen'!$G$8:$G$20,0))))) -> Answer screen | P11: =IF(OR(O11="",J11="Done",J11="Not applicable"),"",IF(O11<TODAY(),"OVERDUE","")) | Q11: =IF(AND(A11="",D11=""),"",IF(AND(I11="No",J11<>"Not applicable"),"Screen says not triggered - confirm or mark Not applicable. ","")&IF(AND(G11<>"",J11<>"Done",J11<>"Not applicable",G11<=TODAY()),"Duty already in force. ","")&IF(AND(O11<>"",G11<>"",J11<>"Done",J11<>"Not applicable",O11>G11),"Target date is after the duty applies. ","")&IF(AND(N11="High",L11="",J11<>"Done",J11<>"Not applicable"),"High priority with no owner. ","")&IF(AND(J11="Done",K11=""),"Done but no evidence location. ","")&IF(AND(J11="Not applicable",M11=""),"Say why it is not applicable. ","")) | R11: =IF(AND(A11<>"",N11="High",J11<>"Done",J11<>"Not applicable"),COUNTIFS($A$6:A11,"<>",$N$6:N11,"High",$J$6:J11,"<>Done",$J$6:J11,"<>Not applicable"),"")
A12: APP-07 | B12: Applicability and roles | C12: s.17(3) | D12: Check whether the Central Government has notified you or your class (which may include startups) as a Data Fiduciary to whom s.5, s.8(3), s.8(7), s.10 and s.11 do not apply. Do not assume this exemption until a notification covers your class. | E12: Data Fiduciary | F12: 3 | G12: =IF(F12="","",INDEX(Timeline!$C$8:$C$10,F12)) -> 46520 | H12: DF | I12: =IF(H12="","",IF(H12="ALL","Yes",IF(IFERROR(INDEX('Applicability Screen'!$E$8:$E$20,MATCH(H12,'Applicability Screen'!$G$8:$G$20,0)),"")="","Answer screen",INDEX('Applicability Screen'!$E$8:$E$20,MATCH(H12,'Applicability Screen'!$G$8:$G$20,0))))) -> Answer screen | P12: =IF(OR(O12="",J12="Done",J12="Not applicable"),"",IF(O12<TODAY(),"OVERDUE","")) | Q12: =IF(AND(A12="",D12=""),"",IF(AND(I12="No",J12<>"Not applicable"),"Screen says not triggered - confirm or mark Not applicable. ","")&IF(AND(G12<>"",J12<>"Done",J12<>"Not applicable",G12<=TODAY()),"Duty already in force. ","")&IF(AND(O12<>"",G12<>"",J12<>"Done",J12<>"Not applicable",O12>G12),"Target date is after the duty applies. ","")&IF(AND(N12="High",L12="",J12<>"Done",J12<>"Not applicable"),"High priority with no owner. ","")&IF(AND(J12="Done",K12=""),"Done but no evidence location. ","")&IF(AND(J12="Not applicable",M12=""),"Say why it is not applicable. ","")) | R12: =IF(AND(A12<>"",N12="High",J12<>"Done",J12<>"Not applicable"),COUNTIFS($A$6:A12,"<>",$N$6:N12,"High",$J$6:J12,"<>Done",$J$6:J12,"<>Not applicable"),"")
A13: APP-08 | B13: Applicability and roles | C13: s.10(1) | D13: Check whether the Central Government has notified you or your class as a Significant Data Fiduciary. Factors it may assess include volume and sensitivity of personal data, risk to Data Principals' rights, sovereignty and integrity of India, risk to electoral democracy, security of the State and public order. Monitor the Gazette. | E13: Data Fiduciary | F13: 3 | G13: =IF(F13="","",INDEX(Timeline!$C$8:$C$10,F13)) -> 46520 | H13: DF | I13: =IF(H13="","",IF(H13="ALL","Yes",IF(IFERROR(INDEX('Applicability Screen'!$E$8:$E$20,MATCH(H13,'Applicability Screen'!$G$8:$G$20,0)),"")="","Answer screen",INDEX('Applicability Screen'!$E$8:$E$20,MATCH(H13,'Applicability Screen'!$G$8:$G$20,0))))) -> Answer screen | P13: =IF(OR(O13="",J13="Done",J13="Not applicable"),"",IF(O13<TODAY(),"OVERDUE","")) | Q13: =IF(AND(A13="",D13=""),"",IF(AND(I13="No",J13<>"Not applicable"),"Screen says not triggered - confirm or mark Not applicable. ","")&IF(AND(G13<>"",J13<>"Done",J13<>"Not applicable",G13<=TODAY()),"Duty already in force. ","")&IF(AND(O13<>"",G13<>"",J13<>"Done",J13<>"Not applicable",O13>G13),"Target date is after the duty applies. ","")&IF(AND(N13="High",L13="",J13<>"Done",J13<>"Not applicable"),"High priority with no owner. ","")&IF(AND(J13="Done",K13=""),"Done but no evidence location. ","")&IF(AND(J13="Not applicable",M13=""),"Say why it is not applicable. ","")) | R13: =IF(AND(A13<>"",N13="High",J13<>"Done",J13<>"Not applicable"),COUNTIFS($A$6:A13,"<>",$N$6:N13,"High",$J$6:J13,"<>Done",$J$6:J13,"<>Not applicable"),"")
A14: APP-09 | B14: Applicability and roles | C14: r.8(1), Third Schedule | D14: Check whether you are in a Third Schedule class: e-commerce entity with at least two crore registered users in India; online gaming intermediary with at least fifty lakh registered users in India; social media intermediary with at least two crore registered users in India. These classes have a fixed inactivity-based erasure rule (RET-03, RET-04). | E14: Data Fiduciary | F14: 3 | G14: =IF(F14="","",INDEX(Timeline!$C$8:$C$10,F14)) -> 46520 | H14: DF | I14: =IF(H14="","",IF(H14="ALL","Yes",IF(IFERROR(INDEX('Applicability Screen'!$E$8:$E$20,MATCH(H14,'Applicability Screen'!$G$8:$G$20,0)),"")="","Answer screen",INDEX('Applicability Screen'!$E$8:$E$20,MATCH(H14,'Applicability Screen'!$G$8:$G$20,0))))) -> Answer screen | P14: =IF(OR(O14="",J14="Done",J14="Not applicable"),"",IF(O14<TODAY(),"OVERDUE","")) | Q14: =IF(AND(A14="",D14=""),"",IF(AND(I14="No",J14<>"Not applicable"),"Screen says not triggered - confirm or mark Not applicable. ","")&IF(AND(G14<>"",J14<>"Done",J14<>"Not applicable",G14<=TODAY()),"Duty already in force. ","")&IF(AND(O14<>"",G14<>"",J14<>"Done",J14<>"Not applicable",O14>G14),"Target date is after the duty applies. ","")&IF(AND(N14="High",L14="",J14<>"Done",J14<>"Not applicable"),"High priority with no owner. ","")&IF(AND(J14="Done",K14=""),"Done but no evidence location. ","")&IF(AND(J14="Not applicable",M14=""),"Say why it is not applicable. ","")) | R14: =IF(AND(A14<>"",N14="High",J14<>"Done",J14<>"Not applicable"),COUNTIFS($A$6:A14,"<>",$N$6:N14,"High",$J$6:J14,"<>Done",$J$6:J14,"<>Not applicable"),"")
A15: NOT-01 | B15: Notice | C15: s.5(1), r.3 | D15: Give a notice with, or before, every request for consent. | E15: Data Fiduciary | F15: 3 | G15: =IF(F15="","",INDEX(Timeline!$C$8:$C$10,F15)) -> 46520 | H15: DF | I15: =IF(H15="","",IF(H15="ALL","Yes",IF(IFERROR(INDEX('Applicability Screen'!$E$8:$E$20,MATCH(H15,'Applicability Screen'!$G$8:$G$20,0)),"")="","Answer screen",INDEX('Applicability Screen'!$E$8:$E$20,MATCH(H15,'Applicability Screen'!$G$8:$G$20,0))))) -> Answer screen | J15: In progress | K15: Example: Legal SharePoint > DPDP > Notices > v0.3 | L15: Head of Privacy | M15: Example: app sign-up flow asks for consent before showing the notice | N15: High | O15: 46418 | P15: =IF(OR(O15="",J15="Done",J15="Not applicable"),"",IF(O15<TODAY(),"OVERDUE","")) | Q15: =IF(AND(A15="",D15=""),"",IF(AND(I15="No",J15<>"Not applicable"),"Screen says not triggered - confirm or mark Not applicable. ","")&IF(AND(G15<>"",J15<>"Done",J15<>"Not applicable",G15<=TODAY()),"Duty already in force. ","")&IF(AND(O15<>"",G15<>"",J15<>"Done",J15<>"Not applicable",O15>G15),"Target date is after the duty applies. ","")&IF(AND(N15="High",L15="",J15<>"Done",J15<>"Not applicable"),"High priority with no owner. ","")&IF(AND(J15="Done",K15=""),"Done but no evidence location. ","")&IF(AND(J15="Not applicable",M15=""),"Say why it is not applicable. ","")) | R15: =IF(AND(A15<>"",N15="High",J15<>"Done",J15<>"Not applicable"),COUNTIFS($A$6:A15,"<>",$N$6:N15,"High",$J$6:J15,"<>Done",$J$6:J15,"<>Not applicable"),"") -> 1
A16: NOT-02 | B16: Notice | C16: r.3(a) | D16: Make the notice understandable on its own - independently of any other information you have made, make or may make available (for example terms of service or a general privacy policy). | E16: Data Fiduciary | F16: 3 | G16: =IF(F16="","",INDEX(Timeline!$C$8:$C$10,F16)) -> 46520 | H16: DF | I16: =IF(H16="","",IF(H16="ALL","Yes",IF(IFERROR(INDEX('Applicability Screen'!$E$8:$E$20,MATCH(H16,'Applicability Screen'!$G$8:$G$20,0)),"")="","Answer screen",INDEX('Applicability Screen'!$E$8:$E$20,MATCH(H16,'Applicability Screen'!$G$8:$G$20,0))))) -> Answer screen | P16: =IF(OR(O16="",J16="Done",J16="Not applicable"),"",IF(O16<TODAY(),"OVERDUE","")) | Q16: =IF(AND(A16="",D16=""),"",IF(AND(I16="No",J16<>"Not applicable"),"Screen says not triggered - confirm or mark Not applicable. ","")&IF(AND(G16<>"",J16<>"Done",J16<>"Not applicable",G16<=TODAY()),"Duty already in force. ","")&IF(AND(O16<>"",G16<>"",J16<>"Done",J16<>"Not applicable",O16>G16),"Target date is after the duty applies. ","")&IF(AND(N16="High",L16="",J16<>"Done",J16<>"Not applicable"),"High priority with no owner. ","")&IF(AND(J16="Done",K16=""),"Done but no evidence location. ","")&IF(AND(J16="Not applicable",M16=""),"Say why it is not applicable. ","")) | R16: =IF(AND(A16<>"",N16="High",J16<>"Done",J16<>"Not applicable"),COUNTIFS($A$6:A16,"<>",$N$6:N16,"High",$J$6:J16,"<>Done",$J$6:J16,"<>Not applicable"),"")
A17: NOT-03 | B17: Notice | C17: s.5(1)(i), r.3(b) | D17: In clear and plain language, give a fair account that lets the Data Principal give specific and informed consent. At the minimum: an itemised description of the personal data; and the specified purpose(s), with a specific description of the goods or services provided, or uses enabled, by the processing. | E17: Data Fiduciary | F17: 3 | G17: =IF(F17="","",INDEX(Timeline!$C$8:$C$10,F17)) -> 46520 | H17: DF | I17: =IF(H17="","",IF(H17="ALL","Yes",IF(IFERROR(INDEX('Applicability Screen'!$E$8:$E$20,MATCH(H17,'Applicability Screen'!$G$8:$G$20,0)),"")="","Answer screen",INDEX('Applicability Screen'!$E$8:$E$20,MATCH(H17,'Applicability Screen'!$G$8:$G$20,0))))) -> Answer screen | P17: =IF(OR(O17="",J17="Done",J17="Not applicable"),"",IF(O17<TODAY(),"OVERDUE","")) | Q17: =IF(AND(A17="",D17=""),"",IF(AND(I17="No",J17<>"Not applicable"),"Screen says not triggered - confirm or mark Not applicable. ","")&IF(AND(G17<>"",J17<>"Done",J17<>"Not applicable",G17<=TODAY()),"Duty already in force. ","")&IF(AND(O17<>"",G17<>"",J17<>"Done",J17<>"Not applicable",O17>G17),"Target date is after the duty applies. ","")&IF(AND(N17="High",L17="",J17<>"Done",J17<>"Not applicable"),"High priority with no owner. ","")&IF(AND(J17="Done",K17=""),"Done but no evidence location. ","")&IF(AND(J17="Not applicable",M17=""),"Say why it is not applicable. ","")) | R17: =IF(AND(A17<>"",N17="High",J17<>"Done",J17<>"Not applicable"),COUNTIFS($A$6:A17,"<>",$N$6:N17,"High",$J$6:J17,"<>Done",$J$6:J17,"<>Not applicable"),"")
A18: NOT-04 | B18: Notice | C18: s.5(1)(ii)-(iii), r.3(c) | D18: Tell the Data Principal how to withdraw consent, exercise her rights under the Act and complain to the Board: give the particular link to your website or app (or both), and describe any other means available. Withdrawal must be comparable in ease to giving consent. | E18: Data Fiduciary | F18: 3 | G18: =IF(F18="","",INDEX(Timeline!$C$8:$C$10,F18)) -> 46520 | H18: DF | I18: =IF(H18="","",IF(H18="ALL","Yes",IF(IFERROR(INDEX('Applicability Screen'!$E$8:$E$20,MATCH(H18,'Applicability Screen'!$G$8:$G$20,0)),"")="","Answer screen",INDEX('Applicability Screen'!$E$8:$E$20,MATCH(H18,'Applicability Screen'!$G$8:$G$20,0))))) -> Answer screen | P18: =IF(OR(O18="",J18="Done",J18="Not applicable"),"",IF(O18<TODAY(),"OVERDUE","")) | Q18: =IF(AND(A18="",D18=""),"",IF(AND(I18="No",J18<>"Not applicable"),"Screen says not triggered - confirm or mark Not applicable. ","")&IF(AND(G18<>"",J18<>"Done",J18<>"Not applicable",G18<=TODAY()),"Duty already in force. ","")&IF(AND(O18<>"",G18<>"",J18<>"Done",J18<>"Not applicable",O18>G18),"Target date is after the duty applies. ","")&IF(AND(N18="High",L18="",J18<>"Done",J18<>"Not applicable"),"High priority with no owner. ","")&IF(AND(J18="Done",K18=""),"Done but no evidence location. ","")&IF(AND(J18="Not applicable",M18=""),"Say why it is not applicable. ","")) | R18: =IF(AND(A18<>"",N18="High",J18<>"Done",J18<>"Not applicable"),COUNTIFS($A$6:A18,"<>",$N$6:N18,"High",$J$6:J18,"<>Done",$J$6:J18,"<>Not applicable"),"")
A19: NOT-05 | B19: Notice | C19: s.5(3) | D19: Give the Data Principal the option to access the notice in English or any language specified in the Eighth Schedule to the Constitution. Decide and document which languages you offer and why - take advice on this point. | E19: Data Fiduciary | F19: 3 | G19: =IF(F19="","",INDEX(Timeline!$C$8:$C$10,F19)) -> 46520 | H19: DF | I19: =IF(H19="","",IF(H19="ALL","Yes",IF(IFERROR(INDEX('Applicability Screen'!$E$8:$E$20,MATCH(H19,'Applicability Screen'!$G$8:$G$20,0)),"")="","Answer screen",INDEX('Applicability Screen'!$E$8:$E$20,MATCH(H19,'Applicability Screen'!$G$8:$G$20,0))))) -> Answer screen | P19: =IF(OR(O19="",J19="Done",J19="Not applicable"),"",IF(O19<TODAY(),"OVERDUE","")) | Q19: =IF(AND(A19="",D19=""),"",IF(AND(I19="No",J19<>"Not applicable"),"Screen says not triggered - confirm or mark Not applicable. ","")&IF(AND(G19<>"",J19<>"Done",J19<>"Not applicable",G19<=TODAY()),"Duty already in force. ","")&IF(AND(O19<>"",G19<>"",J19<>"Done",J19<>"Not applicable",O19>G19),"Target date is after the duty applies. ","")&IF(AND(N19="High",L19="",J19<>"Done",J19<>"Not applicable"),"High priority with no owner. ","")&IF(AND(J19="Done",K19=""),"Done but no evidence location. ","")&IF(AND(J19="Not applicable",M19=""),"Say why it is not applicable. ","")) | R19: =IF(AND(A19<>"",N19="High",J19<>"Done",J19<>"Not applicable"),COUNTIFS($A$6:A19,"<>",$N$6:N19,"High",$J$6:J19,"<>Done",$J$6:J19,"<>Not applicable"),"")
A20: NOT-06 | B20: Notice | C20: s.5(2) | D20: Where consent was given before this provision commenced: as soon as reasonably practicable, give a notice of the personal data and purpose processed, how to withdraw consent and use the grievance route, and how to complain to the Board. You may continue processing until the Data Principal withdraws consent. | E20: Data Fiduciary | F20: 3 | G20: =IF(F20="","",INDEX(Timeline!$C$8:$C$10,F20)) -> 46520 | H20: DF | I20: =IF(H20="","",IF(H20="ALL","Yes",IF(IFERROR(INDEX('Applicability Screen'!$E$8:$E$20,MATCH(H20,'Applicability Screen'!$G$8:$G$20,0)),"")="","Answer screen",INDEX('Applicability Screen'!$E$8:$E$20,MATCH(H20,'Applicability Screen'!$G$8:$G$20,0))))) -> Answer screen | P20: =IF(OR(O20="",J20="Done",J20="Not applicable"),"",IF(O20<TODAY(),"OVERDUE","")) | Q20: =IF(AND(A20="",D20=""),"",IF(AND(I20="No",J20<>"Not applicable"),"Screen says not triggered - confirm or mark Not applicable. ","")&IF(AND(G20<>"",J20<>"Done",J20<>"Not applicable",G20<=TODAY()),"Duty already in force. ","")&IF(AND(O20<>"",G20<>"",J20<>"Done",J20<>"Not applicable",O20>G20),"Target date is after the duty applies. ","")&IF(AND(N20="High",L20="",J20<>"Done",J20<>"Not applicable"),"High priority with no owner. ","")&IF(AND(J20="Done",K20=""),"Done but no evidence location. ","")&IF(AND(J20="Not applicable",M20=""),"Say why it is not applicable. ","")) | R20: =IF(AND(A20<>"",N20="High",J20<>"Done",J20<>"Not applicable"),COUNTIFS($A$6:A20,"<>",$N$6:N20,"High",$J$6:J20,"<>Done",$J$6:J20,"<>Not applicable"),"")
A21: CON-01 | B21: Consent and withdrawal | C21: s.6(1) | D21: Consent must be free, specific, informed, unconditional and unambiguous, given by a clear affirmative action, for the specified purpose, and limited to the personal data necessary for that purpose. (The Act's illustration: a telemedicine app's consent does not extend to the phone's contact list.) | E21: Data Fiduciary | F21: 3 | G21: =IF(F21="","",INDEX(Timeline!$C$8:$C$10,F21)) -> 46520 | H21: DF | I21: =IF(H21="","",IF(H21="ALL","Yes",IF(IFERROR(INDEX('Applicability Screen'!$E$8:$E$20,MATCH(H21,'Applicability Screen'!$G$8:$G$20,0)),"")="","Answer screen",INDEX('Applicability Screen'!$E$8:$E$20,MATCH(H21,'Applicability Screen'!$G$8:$G$20,0))))) -> Answer screen | P21: =IF(OR(O21="",J21="Done",J21="Not applicable"),"",IF(O21<TODAY(),"OVERDUE","")) | Q21: =IF(AND(A21="",D21=""),"",IF(AND(I21="No",J21<>"Not applicable"),"Screen says not triggered - confirm or mark Not applicable. ","")&IF(AND(G21<>"",J21<>"Done",J21<>"Not applicable",G21<=TODAY()),"Duty already in force. ","")&IF(AND(O21<>"",G21<>"",J21<>"Done",J21<>"Not applicable",O21>G21),"Target date is after the duty applies. ","")&IF(AND(N21="High",L21="",J21<>"Done",J21<>"Not applicable"),"High priority with no owner. ","")&IF(AND(J21="Done",K21=""),"Done but no evidence location. ","")&IF(AND(J21="Not applicable",M21=""),"Say why it is not applicable. ","")) | R21: =IF(AND(A21<>"",N21="High",J21<>"Done",J21<>"Not applicable"),COUNTIFS($A$6:A21,"<>",$N$6:N21,"High",$J$6:J21,"<>Done",$J$6:J21,"<>Not applicable"),"")
A22: CON-02 | B22: Consent and withdrawal | C22: s.6(3) | D22: Present every consent request in clear and plain language, with the option to access it in English or any Eighth Schedule language, and include contact details of the Data Protection Officer (where applicable) or another person you authorise to respond to rights communications. | E22: Data Fiduciary | F22: 3 | G22: =IF(F22="","",INDEX(Timeline!$C$8:$C$10,F22)) -> 46520 | H22: DF | I22: =IF(H22="","",IF(H22="ALL","Yes",IF(IFERROR(INDEX('Applicability Screen'!$E$8:$E$20,MATCH(H22,'Applicability Screen'!$G$8:$G$20,0)),"")="","Answer screen",INDEX('Applicability Screen'!$E$8:$E$20,MATCH(H22,'Applicability Screen'!$G$8:$G$20,0))))) -> Answer screen | P22: =IF(OR(O22="",J22="Done",J22="Not applicable"),"",IF(O22<TODAY(),"OVERDUE","")) | Q22: =IF(AND(A22="",D22=""),"",IF(AND(I22="No",J22<>"Not applicable"),"Screen says not triggered - confirm or mark Not applicable. ","")&IF(AND(G22<>"",J22<>"Done",J22<>"Not applicable",G22<=TODAY()),"Duty already in force. ","")&IF(AND(O22<>"",G22<>"",J22<>"Done",J22<>"Not applicable",O22>G22),"Target date is after the duty applies. ","")&IF(AND(N22="High",L22="",J22<>"Done",J22<>"Not applicable"),"High priority with no owner. ","")&IF(AND(J22="Done",K22=""),"Done but no evidence location. ","")&IF(AND(J22="Not applicable",M22=""),"Say why it is not applicable. ","")) | R22: =IF(AND(A22<>"",N22="High",J22<>"Done",J22<>"Not applicable"),COUNTIFS($A$6:A22,"<>",$N$6:N22,"High",$J$6:J22,"<>Done",$J$6:J22,"<>Not applicable"),"")
A23: CON-03 | B23: Consent and withdrawal | C23: s.6(2) | D23: Review consent wording: any part of a consent that infringes the Act, the Rules or any other law is invalid to that extent. (The Act's illustration: consent to waive the right to complain to the Board is invalid.) | E23: Data Fiduciary | F23: 3 | G23: =IF(F23="","",INDEX(Timeline!$C$8:$C$10,F23)) -> 46520 | H23: DF | I23: =IF(H23="","",IF(H23="ALL","Yes",IF(IFERROR(INDEX('Applicability Screen'!$E$8:$E$20,MATCH(H23,'Applicability Screen'!$G$8:$G$20,0)),"")="","Answer screen",INDEX('Applicability Screen'!$E$8:$E$20,MATCH(H23,'Applicability Screen'!$G$8:$G$20,0))))) -> Answer screen | P23: =IF(OR(O23="",J23="Done",J23="Not applicable"),"",IF(O23<TODAY(),"OVERDUE","")) | Q23: =IF(AND(A23="",D23=""),"",IF(AND(I23="No",J23<>"Not applicable"),"Screen says not triggered - confirm or mark Not applicable. ","")&IF(AND(G23<>"",J23<>"Done",J23<>"Not applicable",G23<=TODAY()),"Duty already in force. ","")&IF(AND(O23<>"",G23<>"",J23<>"Done",J23<>"Not applicable",O23>G23),"Target date is after the duty applies. ","")&IF(AND(N23="High",L23="",J23<>"Done",J23<>"Not applicable"),"High priority with no owner. ","")&IF(AND(J23="Done",K23=""),"Done but no evidence location. ","")&IF(AND(J23="Not applicable",M23=""),"Say why it is not applicable. ","")) | R23: =IF(AND(A23<>"",N23="High",J23<>"Done",J23<>"Not applicable"),COUNTIFS($A$6:A23,"<>",$N$6:N23,"High",$J$6:J23,"<>Done",$J$6:J23,"<>Not applicable"),"")
A24: CON-04 | B24: Consent and withdrawal | C24: s.6(4), r.3(c)(i) | D24: Let Data Principals withdraw consent at any time, with ease comparable to the ease of giving it. Check this in every channel where consent is collected. | E24: Data Fiduciary | F24: 3 | G24: =IF(F24="","",INDEX(Timeline!$C$8:$C$10,F24)) -> 46520 | H24: DF | I24: =IF(H24="","",IF(H24="ALL","Yes",IF(IFERROR(INDEX('Applicability Screen'!$E$8:$E$20,MATCH(H24,'Applicability Screen'!$G$8:$G$20,0)),"")="","Answer screen",INDEX('Applicability Screen'!$E$8:$E$20,MATCH(H24,'Applicability Screen'!$G$8:$G$20,0))))) -> Answer screen | P24: =IF(OR(O24="",J24="Done",J24="Not applicable"),"",IF(O24<TODAY(),"OVERDUE","")) | Q24: =IF(AND(A24="",D24=""),"",IF(AND(I24="No",J24<>"Not applicable"),"Screen says not triggered - confirm or mark Not applicable. ","")&IF(AND(G24<>"",J24<>"Done",J24<>"Not applicable",G24<=TODAY()),"Duty already in force. ","")&IF(AND(O24<>"",G24<>"",J24<>"Done",J24<>"Not applicable",O24>G24),"Target date is after the duty applies. ","")&IF(AND(N24="High",L24="",J24<>"Done",J24<>"Not applicable"),"High priority with no owner. ","")&IF(AND(J24="Done",K24=""),"Done but no evidence location. ","")&IF(AND(J24="Not applicable",M24=""),"Say why it is not applicable. ","")) | R24: =IF(AND(A24<>"",N24="High",J24<>"Done",J24<>"Not applicable"),COUNTIFS($A$6:A24,"<>",$N$6:N24,"High",$J$6:J24,"<>Done",$J$6:J24,"<>Not applicable"),"")
A25: CON-05 | B25: Consent and withdrawal | C25: s.6(5) | D25: Withdrawal does not affect the legality of processing done on consent before it; the consequences of withdrawal are borne by the Data Principal. (The Act's illustration: an e-commerce app may stop new orders but cannot stop processing for goods already ordered and paid for.) | E25: Data Fiduciary | F25: 3 | G25: =IF(F25="","",INDEX(Timeline!$C$8:$C$10,F25)) -> 46520 | H25: DF | I25: =IF(H25="","",IF(H25="ALL","Yes",IF(IFERROR(INDEX('Applicability Screen'!$E$8:$E$20,MATCH(H25,'Applicability Screen'!$G$8:$G$20,0)),"")="","Answer screen",INDEX('Applicability Screen'!$E$8:$E$20,MATCH(H25,'Applicability Screen'!$G$8:$G$20,0))))) -> Answer screen | P25: =IF(OR(O25="",J25="Done",J25="Not applicable"),"",IF(O25<TODAY(),"OVERDUE","")) | Q25: =IF(AND(A25="",D25=""),"",IF(AND(I25="No",J25<>"Not applicable"),"Screen says not triggered - confirm or mark Not applicable. ","")&IF(AND(G25<>"",J25<>"Done",J25<>"Not applicable",G25<=TODAY()),"Duty already in force. ","")&IF(AND(O25<>"",G25<>"",J25<>"Done",J25<>"Not applicable",O25>G25),"Target date is after the duty applies. ","")&IF(AND(N25="High",L25="",J25<>"Done",J25<>"Not applicable"),"High priority with no owner. ","")&IF(AND(J25="Done",K25=""),"Done but no evidence location. ","")&IF(AND(J25="Not applicable",M25=""),"Say why it is not applicable. ","")) | R25: =IF(AND(A25<>"",N25="High",J25<>"Done",J25<>"Not applicable"),COUNTIFS($A$6:A25,"<>",$N$6:N25,"High",$J$6:J25,"<>Done",$J$6:J25,"<>Not applicable"),"")
A26: CON-06 | B26: Consent and withdrawal | C26: s.6(6) | D26: On withdrawal, within a reasonable time stop processing that Data Principal's personal data and make your Data Processors stop - unless processing without consent is required or authorised by the Act, the Rules or other Indian law. | E26: Data Fiduciary (flows to Data Processor via contract) | F26: 3 | G26: =IF(F26="","",INDEX(Timeline!$C$8:$C$10,F26)) -> 46520 | H26: DF | I26: =IF(H26="","",IF(H26="ALL","Yes",IF(IFERROR(INDEX('Applicability Screen'!$E$8:$E$20,MATCH(H26,'Applicability Screen'!$G$8:$G$20,0)),"")="","Answer screen",INDEX('Applicability Screen'!$E$8:$E$20,MATCH(H26,'Applicability Screen'!$G$8:$G$20,0))))) -> Answer screen | P26: =IF(OR(O26="",J26="Done",J26="Not applicable"),"",IF(O26<TODAY(),"OVERDUE","")) | Q26: =IF(AND(A26="",D26=""),"",IF(AND(I26="No",J26<>"Not applicable"),"Screen says not triggered - confirm or mark Not applicable. ","")&IF(AND(G26<>"",J26<>"Done",J26<>"Not applicable",G26<=TODAY()),"Duty already in force. ","")&IF(AND(O26<>"",G26<>"",J26<>"Done",J26<>"Not applicable",O26>G26),"Target date is after the duty applies. ","")&IF(AND(N26="High",L26="",J26<>"Done",J26<>"Not applicable"),"High priority with no owner. ","")&IF(AND(J26="Done",K26=""),"Done but no evidence location. ","")&IF(AND(J26="Not applicable",M26=""),"Say why it is not applicable. ","")) | R26: =IF(AND(A26<>"",N26="High",J26<>"Done",J26<>"Not applicable"),COUNTIFS($A$6:A26,"<>",$N$6:N26,"High",$J$6:J26,"<>Done",$J$6:J26,"<>Not applicable"),"")
A27: CON-07 | B27: Consent and withdrawal | C27: s.6(10) | D27: Keep proof: where consent is the basis and it is questioned in a proceeding, you must prove that notice was given and consent was given in line with the Act and Rules. Keep the notice version shown and the consent record. | E27: Data Fiduciary | F27: 3 | G27: =IF(F27="","",INDEX(Timeline!$C$8:$C$10,F27)) -> 46520 | H27: DF | I27: =IF(H27="","",IF(H27="ALL","Yes",IF(IFERROR(INDEX('Applicability Screen'!$E$8:$E$20,MATCH(H27,'Applicability Screen'!$G$8:$G$20,0)),"")="","Answer screen",INDEX('Applicability Screen'!$E$8:$E$20,MATCH(H27,'Applicability Screen'!$G$8:$G$20,0))))) -> Answer screen | P27: =IF(OR(O27="",J27="Done",J27="Not applicable"),"",IF(O27<TODAY(),"OVERDUE","")) | Q27: =IF(AND(A27="",D27=""),"",IF(AND(I27="No",J27<>"Not applicable"),"Screen says not triggered - confirm or mark Not applicable. ","")&IF(AND(G27<>"",J27<>"Done",J27<>"Not applicable",G27<=TODAY()),"Duty already in force. ","")&IF(AND(O27<>"",G27<>"",J27<>"Done",J27<>"Not applicable",O27>G27),"Target date is after the duty applies. ","")&IF(AND(N27="High",L27="",J27<>"Done",J27<>"Not applicable"),"High priority with no owner. ","")&IF(AND(J27="Done",K27=""),"Done but no evidence location. ","")&IF(AND(J27="Not applicable",M27=""),"Say why it is not applicable. ","")) | R27: =IF(AND(A27<>"",N27="High",J27<>"Done",J27<>"Not applicable"),COUNTIFS($A$6:A27,"<>",$N$6:N27,"High",$J$6:J27,"<>Done",$J$6:J27,"<>Not applicable"),"")
... A48: BRE-04 | B48: Breach intimation | C48: s.8(6), r.7(2)(a) | D48: Intimate the Board without delay with a description of the breach, including its nature, extent, timing and location of occurrence, and the likely impact. | E48: Data Fiduciary | F48: 3 | G48: =IF(F48="","",INDEX(Timeline!$C$8:$C$10,F48)) -> 46520 | H48: DF | I48: =IF(H48="","",IF(H48="ALL","Yes",IF(IFERROR(INDEX('Applicability Screen'!$E$8:$E$20,MATCH(H48,'Applicability Screen'!$G$8:$G$20,0)),"")="","Answer screen",INDEX('Applicability Screen'!$E$8:$E$20,MATCH(H48,'Applicability Screen'!$G$8:$G$20,0))))) -> Answer screen | P48: =IF(OR(O48="",J48="Done",J48="Not applicable"),"",IF(O48<TODAY(),"OVERDUE","")) | Q48: =IF(AND(A48="",D48=""),"",IF(AND(I48="No",J48<>"Not applicable"),"Screen says not triggered - confirm or mark Not applicable. ","")&IF(AND(G48<>"",J48<>"Done",J48<>"Not applicable",G48<=TODAY()),"Duty already in force. ","")&IF(AND(O48<>"",G48<>"",J48<>"Done",J48<>"Not applicable",O48>G48),"Target date is after the duty applies. ","")&IF(AND(N48="High",L48="",J48<>"Done",J48<>"Not applicable"),"High priority with no owner. ","")&IF(AND(J48="Done",K48=""),"Done but no evidence location. ","")&IF(AND(J48="Not applicable",M48=""),"Say why it is not applicable. ","")) | R48: =IF(AND(A48<>"",N48="High",J48<>"Done",J48<>"Not applicable"),COUNTIFS($A$6:A48,"<>",$N$6:N48,"High",$J$6:J48,"<>Done",$J$6:J48,"<>Not applicable"),"")
A49: BRE-05 | B49: Breach intimation | C49: r.7(2)(b) | D49: Within 72 hours of becoming aware (or a longer period the Board allows on a written request), give the Board: updated and detailed information on the description; the broad facts on the events, circumstances and reasons leading to the breach; mitigation measures implemented or proposed; any findings about the person who caused it; remedial measures to prevent recurrence; and a report on the intimations given to affected Data Principals. | E49: Data Fiduciary | F49: 3 | G49: =IF(F49="","",INDEX(Timeline!$C$8:$C$10,F49)) -> 46520 | H49: DF | I49: =IF(H49="","",IF(H49="ALL","Yes",IF(IFERROR(INDEX('Applicability Screen'!$E$8:$E$20,MATCH(H49,'Applicability Screen'!$G$8:$G$20,0)),"")="","Answer screen",INDEX('Applicability Screen'!$E$8:$E$20,MATCH(H49,'Applicability Screen'!$G$8:$G$20,0))))) -> Answer screen | J49: Not started | M49: Example: incident runbook has no 72-hour Board report step | N49: High | O49: 46295 | P49: =IF(OR(O49="",J49="Done",J49="Not applicable"),"",IF(O49<TODAY(),"OVERDUE","")) -> OVERDUE | Q49: =IF(AND(A49="",D49=""),"",IF(AND(I49="No",J49<>"Not applicable"),"Screen says not triggered - confirm or mark Not applicable. ","")&IF(AND(G49<>"",J49<>"Done",J49<>"Not applicable",G49<=TODAY()),"Duty already in force. ","")&IF(AND(O49<>"",G49<>"",J49<>"Done",J49<>"Not applicable",O49>G49),"Target date is after the duty applies. ","")&IF(AND(N49="High",L49="",J49<>"Done",J49<>"Not applicable"),"High priority with no owner. ","")&IF(AND(J49="Done",K49=""),"Done but no evidence location. ","")&IF(AND(J49="Not applicable",M49=""),"Say why it is not applicable. ","")) -> High priority with no owner. | R49: =IF(AND(A49<>"",N49="High",J49<>"Done",J49<>"Not applicable"),COUNTIFS($A$6:A49,"<>",$N$6:N49,"High",$J$6:J49,"<>Done",$J$6:J49,"<>Not applicable"),"") -> 2
A50: BRE-06 | B50: Breach intimation | C50: r.7 (good practice) | D50: Keep a breach log with the time you became aware, decisions taken and evidence of each intimation, so you can show the 72-hour report and Data Principal intimations were made. (Good practice supporting r.7 - not a separate legal duty.) | E50: Data Fiduciary | F50: 3 | G50: =IF(F50="","",INDEX(Timeline!$C$8:$C$10,F50)) -> 46520 | H50: DF | I50: =IF(H50="","",IF(H50="ALL","Yes",IF(IFERROR(INDEX('Applicability Screen'!$E$8:$E$20,MATCH(H50,'Applicability Screen'!$G$8:$G$20,0)),"")="","Answer screen",INDEX('Applicability Screen'!$E$8:$E$20,MATCH(H50,'Applicability Screen'!$G$8:$G$20,0))))) -> Answer screen | P50: =IF(OR(O50="",J50="Done",J50="Not applicable"),"",IF(O50<TODAY(),"OVERDUE","")) | Q50: =IF(AND(A50="",D50=""),"",IF(AND(I50="No",J50<>"Not applicable"),"Screen says not triggered - confirm or mark Not applicable. ","")&IF(AND(G50<>"",J50<>"Done",J50<>"Not applicable",G50<=TODAY()),"Duty already in force. ","")&IF(AND(O50<>"",G50<>"",J50<>"Done",J50<>"Not applicable",O50>G50),"Target date is after the duty applies. ","")&IF(AND(N50="High",L50="",J50<>"Done",J50<>"Not applicable"),"High priority with no owner. ","")&IF(AND(J50="Done",K50=""),"Done but no evidence location. ","")&IF(AND(J50="Not applicable",M50=""),"Say why it is not applicable. ","")) | R50: =IF(AND(A50<>"",N50="High",J50<>"Done",J50<>"Not applicable"),COUNTIFS($A$6:A50,"<>",$N$6:N50,"High",$J$6:J50,"<>Done",$J$6:J50,"<>Not applicable"),"")
A51: RET-01 | B51: Retention and erasure | C51: s.8(7)(a) | D51: Erase personal data when the Data Principal withdraws consent or as soon as it is reasonable to assume the specified purpose is no longer served - whichever is earlier - unless retention is necessary to comply with a law in force (the Act's illustration: a bank keeping identity records for the period banking law requires). | E51: Data Fiduciary | F51: 3 | G51: =IF(F51="","",INDEX(Timeline!$C$8:$C$10,F51)) -> 46520 | H51: DF | I51: =IF(H51="","",IF(H51="ALL","Yes",IF(IFERROR(INDEX('Applicability Screen'!$E$8:$E$20,MATCH(H51,'Applicability Screen'!$G$8:$G$20,0)),"")="","Answer screen",INDEX('Applicability Screen'!$E$8:$E$20,MATCH(H51,'Applicability Screen'!$G$8:$G$20,0))))) -> Answer screen | P51: =IF(OR(O51="",J51="Done",J51="Not applicable"),"",IF(O51<TODAY(),"OVERDUE","")) | Q51: =IF(AND(A51="",D51=""),"",IF(AND(I51="No",J51<>"Not applicable"),"Screen says not triggered - confirm or mark Not applicable. ","")&IF(AND(G51<>"",J51<>"Done",J51<>"Not applicable",G51<=TODAY()),"Duty already in force. ","")&IF(AND(O51<>"",G51<>"",J51<>"Done",J51<>"Not applicable",O51>G51),"Target date is after the duty applies. ","")&IF(AND(N51="High",L51="",J51<>"Done",J51<>"Not applicable"),"High priority with no owner. ","")&IF(AND(J51="Done",K51=""),"Done but no evidence location. ","")&IF(AND(J51="Not applicable",M51=""),"Say why it is not applicable. ","")) | R51: =IF(AND(A51<>"",N51="High",J51<>"Done",J51<>"Not applicable"),COUNTIFS($A$6:A51,"<>",$N$6:N51,"High",$J$6:J51,"<>Done",$J$6:J51,"<>Not applicable"),"")
A52: RET-02 | B52: Retention and erasure | C52: s.8(7)(b) | D52: Make your Data Processor erase any personal data you made available to it for processing (same triggers and exception as RET-01). | E52: Data Fiduciary (flows to Data Processor via contract) | F52: 3 | G52: =IF(F52="","",INDEX(Timeline!$C$8:$C$10,F52)) -> 46520 | H52: DF | I52: =IF(H52="","",IF(H52="ALL","Yes",IF(IFERROR(INDEX('Applicability Screen'!$E$8:$E$20,MATCH(H52,'Applicability Screen'!$G$8:$G$20,0)),"")="","Answer screen",INDEX('Applicability Screen'!$E$8:$E$20,MATCH(H52,'Applicability Screen'!$G$8:$G$20,0))))) -> Answer screen | P52: =IF(OR(O52="",J52="Done",J52="Not applicable"),"",IF(O52<TODAY(),"OVERDUE","")) | Q52: =IF(AND(A52="",D52=""),"",IF(AND(I52="No",J52<>"Not applicable"),"Screen says not triggered - confirm or mark Not applicable. ","")&IF(AND(G52<>"",J52<>"Done",J52<>"Not applicable",G52<=TODAY()),"Duty already in force. ","")&IF(AND(O52<>"",G52<>"",J52<>"Done",J52<>"Not applicable",O52>G52),"Target date is after the duty applies. ","")&IF(AND(N52="High",L52="",J52<>"Done",J52<>"Not applicable"),"High priority with no owner. ","")&IF(AND(J52="Done",K52=""),"Done but no evidence location. ","")&IF(AND(J52="Not applicable",M52=""),"Say why it is not applicable. ","")) | R52: =IF(AND(A52<>"",N52="High",J52<>"Done",J52<>"Not applicable"),COUNTIFS($A$6:A52,"<>",$N$6:N52,"High",$J$6:J52,"<>Done",$J$6:J52,"<>Not applicable"),"")
A53: RET-03 | B53: Retention and erasure | C53: s.8(8), r.8(1), Third Schedule | D53: Third Schedule classes: erase personal data if the Data Principal has neither approached you for the specified purpose nor exercised her rights for three years from her last approach or exercise, or from the commencement of the Rules, whichever is latest - unless law requires retention. Excluded purposes: enabling access to her user account, and to virtual tokens issued by you, stored on your platform and usable for money, goods or services. The Rules commence in phases - confirm with counsel which date 'commencement' means here. | E53: Data Fiduciary | F53: 3 | G53: =IF(F53="","",INDEX(Timeline!$C$8:$C$10,F53)) -> 46520 | H53: THIRD | I53: =IF(H53="","",IF(H53="ALL","Yes",IF(IFERROR(INDEX('Applicability Screen'!$E$8:$E$20,MATCH(H53,'Applicability Screen'!$G$8:$G$20,0)),"")="","Answer screen",INDEX('Applicability Screen'!$E$8:$E$20,MATCH(H53,'Applicability Screen'!$G$8:$G$20,0))))) -> Answer screen | P53: =IF(OR(O53="",J53="Done",J53="Not applicable"),"",IF(O53<TODAY(),"OVERDUE","")) | Q53: =IF(AND(A53="",D53=""),"",IF(AND(I53="No",J53<>"Not applicable"),"Screen says not triggered - confirm or mark Not applicable. ","")&IF(AND(G53<>"",J53<>"Done",J53<>"Not applicable",G53<=TODAY()),"Duty already in force. ","")&IF(AND(O53<>"",G53<>"",J53<>"Done",J53<>"Not applicable",O53>G53),"Target date is after the duty applies. ","")&IF(AND(N53="High",L53="",J53<>"Done",J53<>"Not applicable"),"High priority with no owner. ","")&IF(AND(J53="Done",K53=""),"Done but no evidence location. ","")&IF(AND(J53="Not applicable",M53=""),"Say why it is not applicable. ","")) | R53: =IF(AND(A53<>"",N53="High",J53<>"Done",J53<>"Not applicable"),COUNTIFS($A$6:A53,"<>",$N$6:N53,"High",$J$6:J53,"<>Done",$J$6:J53,"<>Not applicable"),"")
A54: RET-04 | B54: Retention and erasure | C54: r.8(2) | D54: Third Schedule classes: at least 48 hours before erasure under r.8, inform the Data Principal that her data will be erased unless she logs into her user account, otherwise contacts you for the specified purpose, or exercises her rights. | E54: Data Fiduciary | F54: 3 | G54: =IF(F54="","",INDEX(Timeline!$C$8:$C$10,F54)) -> 46520 | H54: THIRD | I54: =IF(H54="","",IF(H54="ALL","Yes",IF(IFERROR(INDEX('Applicability Screen'!$E$8:$E$20,MATCH(H54,'Applicability Screen'!$G$8:$G$20,0)),"")="","Answer screen",INDEX('Applicability Screen'!$E$8:$E$20,MATCH(H54,'Applicability Screen'!$G$8:$G$20,0))))) -> Answer screen | P54: =IF(OR(O54="",J54="Done",J54="Not applicable"),"",IF(O54<TODAY(),"OVERDUE","")) | Q54: =IF(AND(A54="",D54=""),"",IF(AND(I54="No",J54<>"Not applicable"),"Screen says not triggered - confirm or mark Not applicable. ","")&IF(AND(G54<>"",J54<>"Done",J54<>"Not applicable",G54<=TODAY()),"Duty already in force. ","")&IF(AND(O54<>"",G54<>"",J54<>"Done",J54<>"Not applicable",O54>G54),"Target date is after the duty applies. ","")&IF(AND(N54="High",L54="",J54<>"Done",J54<>"Not applicable"),"High priority with no owner. ","")&IF(AND(J54="Done",K54=""),"Done but no evidence location. ","")&IF(AND(J54="Not applicable",M54=""),"Say why it is not applicable. ","")) | R54: =IF(AND(A54<>"",N54="High",J54<>"Done",J54<>"Not applicable"),COUNTIFS($A$6:A54,"<>",$N$6:N54,"High",$J$6:J54,"<>Done",$J$6:J54,"<>Not applicable"),"")
A55: RET-05 | B55: Retention and erasure | C55: r.8(3), Seventh Schedule | D55: Retain personal data, associated traffic data and other logs of processing (by you or your Data Processors) for at least one year from the date of processing, for the Seventh Schedule purposes; then erase them unless further retention is required by another law or notified by the Government. (The Rules' illustration: this applies even if the user deletes her account.) | E55: Data Fiduciary (flows to Data Processor via contract) | F55: 3 | G55: =IF(F55="","",INDEX(Timeline!$C$8:$C$10,F55)) -> 46520 | H55: DF | I55: =IF(H55="","",IF(H55="ALL","Yes",IF(IFERROR(INDEX('Applicability Screen'!$E$8:$E$20,MATCH(H55,'Applicability Screen'!$G$8:$G$20,0)),"")="","Answer screen",INDEX('Applicability Screen'!$E$8:$E$20,MATCH(H55,'Applicability Screen'!$G$8:$G$20,0))))) -> Answer screen | P55: =IF(OR(O55="",J55="Done",J55="Not applicable"),"",IF(O55<TODAY(),"OVERDUE","")) | Q55: =IF(AND(A55="",D55=""),"",IF(AND(I55="No",J55<>"Not applicable"),"Screen says not triggered - confirm or mark Not applicable. ","")&IF(AND(G55<>"",J55<>"Done",J55<>"Not applicable",G55<=TODAY()),"Duty already in force. ","")&IF(AND(O55<>"",G55<>"",J55<>"Done",J55<>"Not applicable",O55>G55),"Target date is after the duty applies. ","")&IF(AND(N55="High",L55="",J55<>"Done",J55<>"Not applicable"),"High priority with no owner. ","")&IF(AND(J55="Done",K55=""),"Done but no evidence location. ","")&IF(AND(J55="Not applicable",M55=""),"Say why it is not applicable. ","")) | R55: =IF(AND(A55<>"",N55="High",J55<>"Done",J55<>"Not applicable"),COUNTIFS($A$6:A55,"<>",$N$6:N55,"High",$J$6:J55,"<>Done",$J$6:J55,"<>Not applicable"),"")
A56: RET-06 | B56: Retention and erasure | C56: s.8(7), r.6(1)(e), r.8(3) (good practice) | D56: Keep one retention schedule per data category that reconciles erasure (s.8(7)), the one-year minimums (r.6(1)(e), r.8(3)) and retention periods set by other laws. (Good practice - not a separate legal duty.) | E56: Data Fiduciary | F56: 3 | G56: =IF(F56="","",INDEX(Timeline!$C$8:$C$10,F56)) -> 46520 | H56: DF | I56: =IF(H56="","",IF(H56="ALL","Yes",IF(IFERROR(INDEX('Applicability Screen'!$E$8:$E$20,MATCH(H56,'Applicability Screen'!$G$8:$G$20,0)),"")="","Answer screen",INDEX('Applicability Screen'!$E$8:$E$20,MATCH(H56,'Applicability Screen'!$G$8:$G$20,0))))) -> Answer screen | P56: =IF(OR(O56="",J56="Done",J56="Not applicable"),"",IF(O56<TODAY(),"OVERDUE","")) | Q56: =IF(AND(A56="",D56=""),"",IF(AND(I56="No",J56<>"Not applicable"),"Screen says not triggered - confirm or mark Not applicable. ","")&IF(AND(G56<>"",J56<>"Done",J56<>"Not applicable",G56<=TODAY()),"Duty already in force. ","")&IF(AND(O56<>"",G56<>"",J56<>"Done",J56<>"Not applicable",O56>G56),"Target date is after the duty applies. ","")&IF(AND(N56="High",L56="",J56<>"Done",J56<>"Not applicable"),"High priority with no owner. ","")&IF(AND(J56="Done",K56=""),"Done but no evidence location. ","")&IF(AND(J56="Not applicable",M56=""),"Say why it is not applicable. ","")) | R56: =IF(AND(A56<>"",N56="High",J56<>"Done",J56<>"Not applicable"),COUNTIFS($A$6:A56,"<>",$N$6:N56,"High",$J$6:J56,"<>Done",$J$6:J56,"<>Not applicable"),"")
A57: CGR-01 | B57: Contact and grievance | C57: s.8(9), r.9 | D57: Prominently publish on your website or app the business contact information of your Data Protection Officer (if applicable) or a person able to answer, on your behalf, Data Principals' questions about processing of their personal data. | E57: Data Fiduciary | F57: 3 | G57: =IF(F57="","",INDEX(Timeline!$C$8:$C$10,F57)) -> 46520 | H57: DF | I57: =IF(H57="","",IF(H57="ALL","Yes",IF(IFERROR(INDEX('Applicability Screen'!$E$8:$E$20,MATCH(H57,'Applicability Screen'!$G$8:$G$20,0)),"")="","Answer screen",INDEX('Applicability Screen'!$E$8:$E$20,MATCH(H57,'Applicability Screen'!$G$8:$G$20,0))))) -> Answer screen | J57: Done | L57: Customer Care Lead | N57: Medium | O57: 46266 | P57: =IF(OR(O57="",J57="Done",J57="Not applicable"),"",IF(O57<TODAY(),"OVERDUE","")) | Q57: =IF(AND(A57="",D57=""),"",IF(AND(I57="No",J57<>"Not applicable"),"Screen says not triggered - confirm or mark Not applicable. ","")&IF(AND(G57<>"",J57<>"Done",J57<>"Not applicable",G57<=TODAY()),"Duty already in force. ","")&IF(AND(O57<>"",G57<>"",J57<>"Done",J57<>"Not applicable",O57>G57),"Target date is after the duty applies. ","")&IF(AND(N57="High",L57="",J57<>"Done",J57<>"Not applicable"),"High priority with no owner. ","")&IF(AND(J57="Done",K57=""),"Done but no evidence location. ","")&IF(AND(J57="Not applicable",M57=""),"Say why it is not applicable. ","")) -> Done but no evidence location. | R57: =IF(AND(A57<>"",N57="High",J57<>"Done",J57<>"Not applicable"),COUNTIFS($A$6:A57,"<>",$N$6:N57,"High",$J$6:J57,"<>Done",$J$6:J57,"<>Not applicable"),"")
A58: CGR-02 | B58: Contact and grievance | C58: r.9 | D58: Mention that same contact information in every response to a communication by which a Data Principal exercises her rights under the Act. | E58: Data Fiduciary | F58: 3 | G58: =IF(F58="","",INDEX(Timeline!$C$8:$C$10,F58)) -> 46520 | H58: DF | I58: =IF(H58="","",IF(H58="ALL","Yes",IF(IFERROR(INDEX('Applicability Screen'!$E$8:$E$20,MATCH(H58,'Applicability Screen'!$G$8:$G$20,0)),"")="","Answer screen",INDEX('Applicability Screen'!$E$8:$E$20,MATCH(H58,'Applicability Screen'!$G$8:$G$20,0))))) -> Answer screen | P58: =IF(OR(O58="",J58="Done",J58="Not applicable"),"",IF(O58<TODAY(),"OVERDUE","")) | Q58: =IF(AND(A58="",D58=""),"",IF(AND(I58="No",J58<>"Not applicable"),"Screen says not triggered - confirm or mark Not applicable. ","")&IF(AND(G58<>"",J58<>"Done",J58<>"Not applicable",G58<=TODAY()),"Duty already in force. ","")&IF(AND(O58<>"",G58<>"",J58<>"Done",J58<>"Not applicable",O58>G58),"Target date is after the duty applies. ","")&IF(AND(N58="High",L58="",J58<>"Done",J58<>"Not applicable"),"High priority with no owner. ","")&IF(AND(J58="Done",K58=""),"Done but no evidence location. ","")&IF(AND(J58="Not applicable",M58=""),"Say why it is not applicable. ","")) | R58: =IF(AND(A58<>"",N58="High",J58<>"Done",J58<>"Not applicable"),COUNTIFS($A$6:A58,"<>",$N$6:N58,"High",$J$6:J58,"<>Done",$J$6:J58,"<>Not applicable"),"")
A59: CGR-03 | B59: Contact and grievance | C59: s.8(10), s.13(1) | D59: Establish an effective grievance redressal mechanism: Data Principals must have readily available means to raise grievances about your acts or omissions on your obligations or on the exercise of their rights. | E59: Data Fiduciary and Consent Manager | F59: 3 | G59: =IF(F59="","",INDEX(Timeline!$C$8:$C$10,F59)) -> 46520 | H59: DF | I59: =IF(H59="","",IF(H59="ALL","Yes",IF(IFERROR(INDEX('Applicability Screen'!$E$8:$E$20,MATCH(H59,'Applicability Screen'!$G$8:$G$20,0)),"")="","Answer screen",INDEX('Applicability Screen'!$E$8:$E$20,MATCH(H59,'Applicability Screen'!$G$8:$G$20,0))))) -> Answer screen | P59: =IF(OR(O59="",J59="Done",J59="Not applicable"),"",IF(O59<TODAY(),"OVERDUE","")) | Q59: =IF(AND(A59="",D59=""),"",IF(AND(I59="No",J59<>"Not applicable"),"Screen says not triggered - confirm or mark Not applicable. ","")&IF(AND(G59<>"",J59<>"Done",J59<>"Not applicable",G59<=TODAY()),"Duty already in force. ","")&IF(AND(O59<>"",G59<>"",J59<>"Done",J59<>"Not applicable",O59>G59),"Target date is after the duty applies. ","")&IF(AND(N59="High",L59="",J59<>"Done",J59<>"Not applicable"),"High priority with no owner. ","")&IF(AND(J59="Done",K59=""),"Done but no evidence location. ","")&IF(AND(J59="Not applicable",M59=""),"Say why it is not applicable. ","")) | R59: =IF(AND(A59<>"",N59="High",J59<>"Done",J59<>"Not applicable"),COUNTIFS($A$6:A59,"<>",$N$6:N59,"High",$J$6:J59,"<>Done",$J$6:J59,"<>Not applicable"),"")
A60: CGR-04 | B60: Contact and grievance | C60: s.13(2), r.14(3) | D60: Prominently publish on your website or app the period within which you will respond to grievances - a reasonable period not exceeding ninety days - and implement technical and organisational measures so responses are made within it. | E60: Data Fiduciary and Consent Manager | F60: 3 | G60: =IF(F60="","",INDEX(Timeline!$C$8:$C$10,F60)) -> 46520 | H60: DF | I60: =IF(H60="","",IF(H60="ALL","Yes",IF(IFERROR(INDEX('Applicability Screen'!$E$8:$E$20,MATCH(H60,'Applicability Screen'!$G$8:$G$20,0)),"")="","Answer screen",INDEX('Applicability Screen'!$E$8:$E$20,MATCH(H60,'Applicability Screen'!$G$8:$G$20,0))))) -> Answer screen | P60: =IF(OR(O60="",J60="Done",J60="Not applicable"),"",IF(O60<TODAY(),"OVERDUE","")) | Q60: =IF(AND(A60="",D60=""),"",IF(AND(I60="No",J60<>"Not applicable"),"Screen says not triggered - confirm or mark Not applicable. ","")&IF(AND(G60<>"",J60<>"Done",J60<>"Not applicable",G60<=TODAY()),"Duty already in force. ","")&IF(AND(O60<>"",G60<>"",J60<>"Done",J60<>"Not applicable",O60>G60),"Target date is after the duty applies. ","")&IF(AND(N60="High",L60="",J60<>"Done",J60<>"Not applicable"),"High priority with no owner. ","")&IF(AND(J60="Done",K60=""),"Done but no evidence location. ","")&IF(AND(J60="Not applicable",M60=""),"Say why it is not applicable. ","")) | R60: =IF(AND(A60<>"",N60="High",J60<>"Done",J60<>"Not applicable"),COUNTIFS($A$6:A60,"<>",$N$6:N60,"High",$J$6:J60,"<>Done",$J$6:J60,"<>Not applicable"),"")
A61: CGR-05 | B61: Contact and grievance | C61: s.13(3) | D61: Data Principals must exhaust your grievance route before approaching the Board, so your grievance records are likely to be the first evidence in a complaint. Keep each grievance, response and date. | E61: Data Fiduciary and Consent Manager | F61: 3 | G61: =IF(F61="","",INDEX(Timeline!$C$8:$C$10,F61)) -> 46520 | H61: DF | I61: =IF(H61="","",IF(H61="ALL","Yes",IF(IFERROR(INDEX('Applicability Screen'!$E$8:$E$20,MATCH(H61,'Applicability Screen'!$G$8:$G$20,0)),"")="","Answer screen",INDEX('Applicability Screen'!$E$8:$E$20,MATCH(H61,'Applicability Screen'!$G$8:$G$20,0))))) -> Answer screen | P61: =IF(OR(O61="",J61="Done",J61="Not applicable"),"",IF(O61<TODAY(),"OVERDUE","")) | Q61: =IF(AND(A61="",D61=""),"",IF(AND(I61="No",J61<>"Not applicable"),"Screen says not triggered - confirm or mark Not applicable. ","")&IF(AND(G61<>"",J61<>"Done",J61<>"Not applicable",G61<=TODAY()),"Duty already in force. ","")&IF(AND(O61<>"",G61<>"",J61<>"Done",J61<>"Not applicable",O61>G61),"Target date is after the duty applies. ","")&IF(AND(N61="High",L61="",J61<>"Done",J61<>"Not applicable"),"High priority with no owner. ","")&IF(AND(J61="Done",K61=""),"Done but no evidence location. ","")&IF(AND(J61="Not applicable",M61=""),"Say why it is not applicable. ","")) | R61: =IF(AND(A61<>"",N61="High",J61<>"Done",J61<>"Not applicable"),COUNTIFS($A$6:A61,"<>",$N$6:N61,"High",$J$6:J61,"<>Done",$J$6:J61,"<>Not applicable"),"")
A62: PRC-01 | B62: Data Processors and contracts | C62: s.8(2) | D62: Engage, appoint, use or involve a Data Processor for any activity related to offering goods or services to Data Principals only under a valid contract. Keep an inventory of processors and contracts. | E62: Data Fiduciary | F62: 3 | G62: =IF(F62="","",INDEX(Timeline!$C$8:$C$10,F62)) -> 46520 | H62: DF | I62: =IF(H62="","",IF(H62="ALL","Yes",IF(IFERROR(INDEX('Applicability Screen'!$E$8:$E$20,MATCH(H62,'Applicability Screen'!$G$8:$G$20,0)),"")="","Answer screen",INDEX('Applicability Screen'!$E$8:$E$20,MATCH(H62,'Applicability Screen'!$G$8:$G$20,0))))) -> Answer screen | P62: =IF(OR(O62="",J62="Done",J62="Not applicable"),"",IF(O62<TODAY(),"OVERDUE","")) | Q62: =IF(AND(A62="",D62=""),"",IF(AND(I62="No",J62<>"Not applicable"),"Screen says not triggered - confirm or mark Not applicable. ","")&IF(AND(G62<>"",J62<>"Done",J62<>"Not applicable",G62<=TODAY()),"Duty already in force. ","")&IF(AND(O62<>"",G62<>"",J62<>"Done",J62<>"Not applicable",O62>G62),"Target date is after the duty applies. ","")&IF(AND(N62="High",L62="",J62<>"Done",J62<>"Not applicable"),"High priority with no owner. ","")&IF(AND(J62="Done",K62=""),"Done but no evidence location. ","")&IF(AND(J62="Not applicable",M62=""),"Say why it is not applicable. ","")) | R62: =IF(AND(A62<>"",N62="High",J62<>"Done",J62<>"Not applicable"),COUNTIFS($A$6:A62,"<>",$N$6:N62,"High",$J$6:J62,"<>Done",$J$6:J62,"<>Not applicable"),"")
A63: PRC-02 | B63: Data Processors and contracts | C63: r.6(1)(f) | D63: Each Data Processor contract contains an appropriate provision for taking reasonable security safeguards. | E63: Data Fiduciary (flows to Data Processor via contract) | F63: 3 | G63: =IF(F63="","",INDEX(Timeline!$C$8:$C$10,F63)) -> 46520 | H63: DF | I63: =IF(H63="","",IF(H63="ALL","Yes",IF(IFERROR(INDEX('Applicability Screen'!$E$8:$E$20,MATCH(H63,'Applicability Screen'!$G$8:$G$20,0)),"")="","Answer screen",INDEX('Applicability Screen'!$E$8:$E$20,MATCH(H63,'Applicability Screen'!$G$8:$G$20,0))))) -> Answer screen | P63: =IF(OR(O63="",J63="Done",J63="Not applicable"),"",IF(O63<TODAY(),"OVERDUE","")) | Q63: =IF(AND(A63="",D63=""),"",IF(AND(I63="No",J63<>"Not applicable"),"Screen says not triggered - confirm or mark Not applicable. ","")&IF(AND(G63<>"",J63<>"Done",J63<>"Not applicable",G63<=TODAY()),"Duty already in force. ","")&IF(AND(O63<>"",G63<>"",J63<>"Done",J63<>"Not applicable",O63>G63),"Target date is after the duty applies. ","")&IF(AND(N63="High",L63="",J63<>"Done",J63<>"Not applicable"),"High priority with no owner. ","")&IF(AND(J63="Done",K63=""),"Done but no evidence location. ","")&IF(AND(J63="Not applicable",M63=""),"Say why it is not applicable. ","")) | R63: =IF(AND(A63<>"",N63="High",J63<>"Done",J63<>"Not applicable"),COUNTIFS($A$6:A63,"<>",$N$6:N63,"High",$J$6:J63,"<>Done",$J$6:J63,"<>Not applicable"),"")
A64: PRC-03 | B64: Data Processors and contracts | C64: s.6(6), s.8(7)(b) | D64: Contracts let you make processors stop processing when consent is withdrawn and erase personal data you made available to them. | E64: Data Fiduciary (flows to Data Processor via contract) | F64: 3 | G64: =IF(F64="","",INDEX(Timeline!$C$8:$C$10,F64)) -> 46520 | H64: DF | I64: =IF(H64="","",IF(H64="ALL","Yes",IF(IFERROR(INDEX('Applicability Screen'!$E$8:$E$20,MATCH(H64,'Applicability Screen'!$G$8:$G$20,0)),"")="","Answer screen",INDEX('Applicability Screen'!$E$8:$E$20,MATCH(H64,'Applicability Screen'!$G$8:$G$20,0))))) -> Answer screen | P64: =IF(OR(O64="",J64="Done",J64="Not applicable"),"",IF(O64<TODAY(),"OVERDUE","")) | Q64: =IF(AND(A64="",D64=""),"",IF(AND(I64="No",J64<>"Not applicable"),"Screen says not triggered - confirm or mark Not applicable. ","")&IF(AND(G64<>"",J64<>"Done",J64<>"Not applicable",G64<=TODAY()),"Duty already in force. ","")&IF(AND(O64<>"",G64<>"",J64<>"Done",J64<>"Not applicable",O64>G64),"Target date is after the duty applies. ","")&IF(AND(N64="High",L64="",J64<>"Done",J64<>"Not applicable"),"High priority with no owner. ","")&IF(AND(J64="Done",K64=""),"Done but no evidence location. ","")&IF(AND(J64="Not applicable",M64=""),"Say why it is not applicable. ","")) | R64: =IF(AND(A64<>"",N64="High",J64<>"Done",J64<>"Not applicable"),COUNTIFS($A$6:A64,"<>",$N$6:N64,"High",$J$6:J64,"<>Done",$J$6:J64,"<>Not applicable"),"")
A65: PRC-04 | B65: Data Processors and contracts | C65: r.6(1)(b)-(c), r.8(3) | D65: Contracts or oversight cover processor access control and logging, and retention of personal data and processing logs for at least one year (the Rules' illustration: a Data Fiduciary must ensure its cloud provider also retains data and logs for one year). | E65: Data Fiduciary (flows to Data Processor via contract) | F65: 3 | G65: =IF(F65="","",INDEX(Timeline!$C$8:$C$10,F65)) -> 46520 | H65: DF | I65: =IF(H65="","",IF(H65="ALL","Yes",IF(IFERROR(INDEX('Applicability Screen'!$E$8:$E$20,MATCH(H65,'Applicability Screen'!$G$8:$G$20,0)),"")="","Answer screen",INDEX('Applicability Screen'!$E$8:$E$20,MATCH(H65,'Applicability Screen'!$G$8:$G$20,0))))) -> Answer screen | P65: =IF(OR(O65="",J65="Done",J65="Not applicable"),"",IF(O65<TODAY(),"OVERDUE","")) | Q65: =IF(AND(A65="",D65=""),"",IF(AND(I65="No",J65<>"Not applicable"),"Screen says not triggered - confirm or mark Not applicable. ","")&IF(AND(G65<>"",J65<>"Done",J65<>"Not applicable",G65<=TODAY()),"Duty already in force. ","")&IF(AND(O65<>"",G65<>"",J65<>"Done",J65<>"Not applicable",O65>G65),"Target date is after the duty applies. ","")&IF(AND(N65="High",L65="",J65<>"Done",J65<>"Not applicable"),"High priority with no owner. ","")&IF(AND(J65="Done",K65=""),"Done but no evidence location. ","")&IF(AND(J65="Not applicable",M65=""),"Say why it is not applicable. ","")) | R65: =IF(AND(A65<>"",N65="High",J65<>"Done",J65<>"Not applicable"),COUNTIFS($A$6:A65,"<>",$N$6:N65,"High",$J$6:J65,"<>Done",$J$6:J65,"<>Not applicable"),"")
A66: PRC-05 | B66: Data Processors and contracts | C66: s.8(1), s.8(5) (good practice) | D66: Because you stay responsible for processing done on your behalf, set due diligence before onboarding and periodic oversight of processors. (Good practice to evidence s.8(1) and s.8(5).) | E66: Data Fiduciary | F66: 3 | G66: =IF(F66="","",INDEX(Timeline!$C$8:$C$10,F66)) -> 46520 | H66: DF | I66: =IF(H66="","",IF(H66="ALL","Yes",IF(IFERROR(INDEX('Applicability Screen'!$E$8:$E$20,MATCH(H66,'Applicability Screen'!$G$8:$G$20,0)),"")="","Answer screen",INDEX('Applicability Screen'!$E$8:$E$20,MATCH(H66,'Applicability Screen'!$G$8:$G$20,0))))) -> Answer screen | P66: =IF(OR(O66="",J66="Done",J66="Not applicable"),"",IF(O66<TODAY(),"OVERDUE","")) | Q66: =IF(AND(A66="",D66=""),"",IF(AND(I66="No",J66<>"Not applicable"),"Screen says not triggered - confirm or mark Not applicable. ","")&IF(AND(G66<>"",J66<>"Done",J66<>"Not applicable",G66<=TODAY()),"Duty already in force. ","")&IF(AND(O66<>"",G66<>"",J66<>"Done",J66<>"Not applicable",O66>G66),"Target date is after the duty applies. ","")&IF(AND(N66="High",L66="",J66<>"Done",J66<>"Not applicable"),"High priority with no owner. ","")&IF(AND(J66="Done",K66=""),"Done but no evidence location. ","")&IF(AND(J66="Not applicable",M66=""),"Say why it is not applicable. ","")) | R66: =IF(AND(A66<>"",N66="High",J66<>"Done",J66<>"Not applicable"),COUNTIFS($A$6:A66,"<>",$N$6:N66,"High",$J$6:J66,"<>Done",$J$6:J66,"<>Not applicable"),"")
A67: PRC-06 | B67: Data Processors and contracts | C67: s.8(1)-(2), s.8(5)-(7), r.6, r.7, r.8(3) | D67: If you are a Data Processor: the Act places these duties on the Data Fiduciary, which will pass them to you by contract - security safeguards, stopping and erasing on instruction, one-year log retention, and prompt notice of breaches so it can meet r.7. Prepare a standard position or addendum. | E67: Data Processor (via contract) | F67: 3 | G67: =IF(F67="","",INDEX(Timeline!$C$8:$C$10,F67)) -> 46520 | H67: PROC | I67: =IF(H67="","",IF(H67="ALL","Yes",IF(IFERROR(INDEX('Applicability Screen'!$E$8:$E$20,MATCH(H67,'Applicability Screen'!$G$8:$G$20,0)),"")="","Answer screen",INDEX('Applicability Screen'!$E$8:$E$20,MATCH(H67,'Applicability Screen'!$G$8:$G$20,0))))) -> Answer screen | P67: =IF(OR(O67="",J67="Done",J67="Not applicable"),"",IF(O67<TODAY(),"OVERDUE","")) | Q67: =IF(AND(A67="",D67=""),"",IF(AND(I67="No",J67<>"Not applicable"),"Screen says not triggered - confirm or mark Not applicable. ","")&IF(AND(G67<>"",J67<>"Done",J67<>"Not applicable",G67<=TODAY()),"Duty already in force. ","")&IF(AND(O67<>"",G67<>"",J67<>"Done",J67<>"Not applicable",O67>G67),"Target date is after the duty applies. ","")&IF(AND(N67="High",L67="",J67<>"Done",J67<>"Not applicable"),"High priority with no owner. ","")&IF(AND(J67="Done",K67=""),"Done but no evidence location. ","")&IF(AND(J67="Not applicable",M67=""),"Say why it is not applicable. ","")) | R67: =IF(AND(A67<>"",N67="High",J67<>"Done",J67<>"Not applicable"),COUNTIFS($A$6:A67,"<>",$N$6:N67,"High",$J$6:J67,"<>Done",$J$6:J67,"<>Not applicable"),"")
A68: CHD-01 | B68: Children and persons with disability | C68: s.2(f), Fourth Schedule Part B item 6 | D68: A child is an individual who has not completed 18 years. Decide how you determine whether a user is a child. Processing to confirm that a Data Principal is not a child, and for r.10 due diligence, is a listed purpose exempt from s.9(1) and s.9(3) - restricted to the extent necessary. | E68: Data Fiduciary | F68: 3 | G68: =IF(F68="","",INDEX(Timeline!$C$8:$C$10,F68)) -> 46520 | H68: CHILD | I68: =IF(H68="","",IF(H68="ALL","Yes",IF(IFERROR(INDEX('Applicability Screen'!$E$8:$E$20,MATCH(H68,'Applicability Screen'!$G$8:$G$20,0)),"")="","Answer screen",INDEX('Applicability Screen'!$E$8:$E$20,MATCH(H68,'Applicability Screen'!$G$8:$G$20,0))))) -> Answer screen | P68: =IF(OR(O68="",J68="Done",J68="Not applicable"),"",IF(O68<TODAY(),"OVERDUE","")) | Q68: =IF(AND(A68="",D68=""),"",IF(AND(I68="No",J68<>"Not applicable"),"Screen says not triggered - confirm or mark Not applicable. ","")&IF(AND(G68<>"",J68<>"Done",J68<>"Not applicable",G68<=TODAY()),"Duty already in force. ","")&IF(AND(O68<>"",G68<>"",J68<>"Done",J68<>"Not applicable",O68>G68),"Target date is after the duty applies. ","")&IF(AND(N68="High",L68="",J68<>"Done",J68<>"Not applicable"),"High priority with no owner. ","")&IF(AND(J68="Done",K68=""),"Done but no evidence location. ","")&IF(AND(J68="Not applicable",M68=""),"Say why it is not applicable. ","")) | R68: =IF(AND(A68<>"",N68="High",J68<>"Done",J68<>"Not applicable"),COUNTIFS($A$6:A68,"<>",$N$6:N68,"High",$J$6:J68,"<>Done",$J$6:J68,"<>Not applicable"),"")
A69: CHD-02 | B69: Children and persons with disability | C69: s.9(1), r.10(1) | D69: Before processing any personal data of a child, obtain verifiable consent of the parent, using appropriate technical and organisational measures. | E69: Data Fiduciary | F69: 3 | G69: =IF(F69="","",INDEX(Timeline!$C$8:$C$10,F69)) -> 46520 | H69: CHILD | I69: =IF(H69="","",IF(H69="ALL","Yes",IF(IFERROR(INDEX('Applicability Screen'!$E$8:$E$20,MATCH(H69,'Applicability Screen'!$G$8:$G$20,0)),"")="","Answer screen",INDEX('Applicability Screen'!$E$8:$E$20,MATCH(H69,'Applicability Screen'!$G$8:$G$20,0))))) -> Answer screen | P69: =IF(OR(O69="",J69="Done",J69="Not applicable"),"",IF(O69<TODAY(),"OVERDUE","")) | Q69: =IF(AND(A69="",D69=""),"",IF(AND(I69="No",J69<>"Not applicable"),"Screen says not triggered - confirm or mark Not applicable. ","")&IF(AND(G69<>"",J69<>"Done",J69<>"Not applicable",G69<=TODAY()),"Duty already in force. ","")&IF(AND(O69<>"",G69<>"",J69<>"Done",J69<>"Not applicable",O69>G69),"Target date is after the duty applies. ","")&IF(AND(N69="High",L69="",J69<>"Done",J69<>"Not applicable"),"High priority with no owner. ","")&IF(AND(J69="Done",K69=""),"Done but no evidence location. ","")&IF(AND(J69="Not applicable",M69=""),"Say why it is not applicable. ","")) | R69: =IF(AND(A69<>"",N69="High",J69<>"Done",J69<>"Not applicable"),COUNTIFS($A$6:A69,"<>",$N$6:N69,"High",$J$6:J69,"<>Done",$J$6:J69,"<>Not applicable"),"")
... A104: REC-03 | B104: Records and information requests | C104: s.6(10), r.6(1)(e), r.7, r.8(3), r.13, r.14(3) (good practice) | D104: Keep one register of the records the Act and Rules make you keep or prove: notice and consent proof (s.6(10)); security logs for one year (r.6(1)(e)); processing data and logs for at least one year (r.8(3)); breach intimations (r.7); grievances and responses (r.14(3)); SDF DPIA and audit reports (r.13). (Good practice - consolidates existing duties.) | E104: Data Fiduciary | F104: 3 | G104: =IF(F104="","",INDEX(Timeline!$C$8:$C$10,F104)) -> 46520 | H104: DF | I104: =IF(H104="","",IF(H104="ALL","Yes",IF(IFERROR(INDEX('Applicability Screen'!$E$8:$E$20,MATCH(H104,'Applicability Screen'!$G$8:$G$20,0)),"")="","Answer screen",INDEX('Applicability Screen'!$E$8:$E$20,MATCH(H104,'Applicability Screen'!$G$8:$G$20,0))))) -> Answer screen | P104: =IF(OR(O104="",J104="Done",J104="Not applicable"),"",IF(O104<TODAY(),"OVERDUE","")) | Q104: =IF(AND(A104="",D104=""),"",IF(AND(I104="No",J104<>"Not applicable"),"Screen says not triggered - confirm or mark Not applicable. ","")&IF(AND(G104<>"",J104<>"Done",J104<>"Not applicable",G104<=TODAY()),"Duty already in force. ","")&IF(AND(O104<>"",G104<>"",J104<>"Done",J104<>"Not applicable",O104>G104),"Target date is after the duty applies. ","")&IF(AND(N104="High",L104="",J104<>"Done",J104<>"Not applicable"),"High priority with no owner. ","")&IF(AND(J104="Done",K104=""),"Done but no evidence location. ","")&IF(AND(J104="Not applicable",M104=""),"Say why it is not applicable. ","")) | R104: =IF(AND(A104<>"",N104="High",J104<>"Done",J104<>"Not applicable"),COUNTIFS($A$6:A104,"<>",$N$6:N104,"High",$J$6:J104,"<>Done",$J$6:J104,"<>Not applicable"),"")
G105: =IF(F105="","",INDEX(Timeline!$C$8:$C$10,F105)) | I105: =IF(H105="","",IF(H105="ALL","Yes",IF(IFERROR(INDEX('Applicability Screen'!$E$8:$E$20,MATCH(H105,'Applicability Screen'!$G$8:$G$20,0)),"")="","Answer screen",INDEX('Applicability Screen'!$E$8:$E$20,MATCH(H105,'Applicability Screen'!$G$8:$G$20,0))))) | P105: =IF(OR(O105="",J105="Done",J105="Not applicable"),"",IF(O105<TODAY(),"OVERDUE","")) | Q105: =IF(AND(A105="",D105=""),"",IF(AND(I105="No",J105<>"Not applicable"),"Screen says not triggered - confirm or mark Not applicable. ","")&IF(AND(G105<>"",J105<>"Done",J105<>"Not applicable",G105<=TODAY()),"Duty already in force. ","")&IF(AND(O105<>"",G105<>"",J105<>"Done",J105<>"Not applicable",O105>G105),"Target date is after the duty applies. ","")&IF(AND(N105="High",L105="",J105<>"Done",J105<>"Not applicable"),"High priority with no owner. ","")&IF(AND(J105="Done",K105=""),"Done but no evidence location. ","")&IF(AND(J105="Not applicable",M105=""),"Say why it is not applicable. ","")) | R105: =IF(AND(A105<>"",N105="High",J105<>"Done",J105<>"Not applicable"),COUNTIFS($A$6:A105,"<>",$N$6:N105,"High",$J$6:J105,"<>Done",$J$6:J105,"<>Not applicable"),"")
G106: =IF(F106="","",INDEX(Timeline!$C$8:$C$10,F106)) | I106: =IF(H106="","",IF(H106="ALL","Yes",IF(IFERROR(INDEX('Applicability Screen'!$E$8:$E$20,MATCH(H106,'Applicability Screen'!$G$8:$G$20,0)),"")="","Answer screen",INDEX('Applicability Screen'!$E$8:$E$20,MATCH(H106,'Applicability Screen'!$G$8:$G$20,0))))) | P106: =IF(OR(O106="",J106="Done",J106="Not applicable"),"",IF(O106<TODAY(),"OVERDUE","")) | Q106: =IF(AND(A106="",D106=""),"",IF(AND(I106="No",J106<>"Not applicable"),"Screen says not triggered - confirm or mark Not applicable. ","")&IF(AND(G106<>"",J106<>"Done",J106<>"Not applicable",G106<=TODAY()),"Duty already in force. ","")&IF(AND(O106<>"",G106<>"",J106<>"Done",J106<>"Not applicable",O106>G106),"Target date is after the duty applies. ","")&IF(AND(N106="High",L106="",J106<>"Done",J106<>"Not applicable"),"High priority with no owner. ","")&IF(AND(J106="Done",K106=""),"Done but no evidence location. ","")&IF(AND(J106="Not applicable",M106=""),"Say why it is not applicable. ","")) | R106: =IF(AND(A106<>"",N106="High",J106<>"Done",J106<>"Not applicable"),COUNTIFS($A$6:A106,"<>",$N$6:N106,"High",$J$6:J106,"<>Done",$J$6:J106,"<>Not applicable"),"")
G107: =IF(F107="","",INDEX(Timeline!$C$8:$C$10,F107)) | I107: =IF(H107="","",IF(H107="ALL","Yes",IF(IFERROR(INDEX('Applicability Screen'!$E$8:$E$20,MATCH(H107,'Applicability Screen'!$G$8:$G$20,0)),"")="","Answer screen",INDEX('Applicability Screen'!$E$8:$E$20,MATCH(H107,'Applicability Screen'!$G$8:$G$20,0))))) | P107: =IF(OR(O107="",J107="Done",J107="Not applicable"),"",IF(O107<TODAY(),"OVERDUE","")) | Q107: =IF(AND(A107="",D107=""),"",IF(AND(I107="No",J107<>"Not applicable"),"Screen says not triggered - confirm or mark Not applicable. ","")&IF(AND(G107<>"",J107<>"Done",J107<>"Not applicable",G107<=TODAY()),"Duty already in force. ","")&IF(AND(O107<>"",G107<>"",J107<>"Done",J107<>"Not applicable",O107>G107),"Target date is after the duty applies. ","")&IF(AND(N107="High",L107="",J107<>"Done",J107<>"Not applicable"),"High priority with no owner. ","")&IF(AND(J107="Done",K107=""),"Done but no evidence location. ","")&IF(AND(J107="Not applicable",M107=""),"Say why it is not applicable. ","")) | R107: =IF(AND(A107<>"",N107="High",J107<>"Done",J107<>"Not applicable"),COUNTIFS($A$6:A107,"<>",$N$6:N107,"High",$J$6:J107,"<>Done",$J$6:J107,"<>Not applicable"),"")
G108: =IF(F108="","",INDEX(Timeline!$C$8:$C$10,F108)) | I108: =IF(H108="","",IF(H108="ALL","Yes",IF(IFERROR(INDEX('Applicability Screen'!$E$8:$E$20,MATCH(H108,'Applicability Screen'!$G$8:$G$20,0)),"")="","Answer screen",INDEX('Applicability Screen'!$E$8:$E$20,MATCH(H108,'Applicability Screen'!$G$8:$G$20,0))))) | P108: =IF(OR(O108="",J108="Done",J108="Not applicable"),"",IF(O108<TODAY(),"OVERDUE","")) | Q108: =IF(AND(A108="",D108=""),"",IF(AND(I108="No",J108<>"Not applicable"),"Screen says not triggered - confirm or mark Not applicable. ","")&IF(AND(G108<>"",J108<>"Done",J108<>"Not applicable",G108<=TODAY()),"Duty already in force. ","")&IF(AND(O108<>"",G108<>"",J108<>"Done",J108<>"Not applicable",O108>G108),"Target date is after the duty applies. ","")&IF(AND(N108="High",L108="",J108<>"Done",J108<>"Not applicable"),"High priority with no owner. ","")&IF(AND(J108="Done",K108=""),"Done but no evidence location. ","")&IF(AND(J108="Not applicable",M108=""),"Say why it is not applicable. ","")) | R108: =IF(AND(A108<>"",N108="High",J108<>"Done",J108<>"Not applicable"),COUNTIFS($A$6:A108,"<>",$N$6:N108,"High",$J$6:J108,"<>Done",$J$6:J108,"<>Not applicable"),"")
G109: =IF(F109="","",INDEX(Timeline!$C$8:$C$10,F109)) | I109: =IF(H109="","",IF(H109="ALL","Yes",IF(IFERROR(INDEX('Applicability Screen'!$E$8:$E$20,MATCH(H109,'Applicability Screen'!$G$8:$G$20,0)),"")="","Answer screen",INDEX('Applicability Screen'!$E$8:$E$20,MATCH(H109,'Applicability Screen'!$G$8:$G$20,0))))) | P109: =IF(OR(O109="",J109="Done",J109="Not applicable"),"",IF(O109<TODAY(),"OVERDUE","")) | Q109: =IF(AND(A109="",D109=""),"",IF(AND(I109="No",J109<>"Not applicable"),"Screen says not triggered - confirm or mark Not applicable. ","")&IF(AND(G109<>"",J109<>"Done",J109<>"Not applicable",G109<=TODAY()),"Duty already in force. ","")&IF(AND(O109<>"",G109<>"",J109<>"Done",J109<>"Not applicable",O109>G109),"Target date is after the duty applies. ","")&IF(AND(N109="High",L109="",J109<>"Done",J109<>"Not applicable"),"High priority with no owner. ","")&IF(AND(J109="Done",K109=""),"Done but no evidence location. ","")&IF(AND(J109="Not applicable",M109=""),"Say why it is not applicable. ","")) | R109: =IF(AND(A109<>"",N109="High",J109<>"Done",J109<>"Not applicable"),COUNTIFS($A$6:A109,"<>",$N$6:N109,"High",$J$6:J109,"<>Done",$J$6:J109,"<>Not applicable"),"")
G110: =IF(F110="","",INDEX(Timeline!$C$8:$C$10,F110)) | I110: =IF(H110="","",IF(H110="ALL","Yes",IF(IFERROR(INDEX('Applicability Screen'!$E$8:$E$20,MATCH(H110,'Applicability Screen'!$G$8:$G$20,0)),"")="","Answer screen",INDEX('Applicability Screen'!$E$8:$E$20,MATCH(H110,'Applicability Screen'!$G$8:$G$20,0))))) | P110: =IF(OR(O110="",J110="Done",J110="Not applicable"),"",IF(O110<TODAY(),"OVERDUE","")) | Q110: =IF(AND(A110="",D110=""),"",IF(AND(I110="No",J110<>"Not applicable"),"Screen says not triggered - confirm or mark Not applicable. ","")&IF(AND(G110<>"",J110<>"Done",J110<>"Not applicable",G110<=TODAY()),"Duty already in force. ","")&IF(AND(O110<>"",G110<>"",J110<>"Done",J110<>"Not applicable",O110>G110),"Target date is after the duty applies. ","")&IF(AND(N110="High",L110="",J110<>"Done",J110<>"Not applicable"),"High priority with no owner. ","")&IF(AND(J110="Done",K110=""),"Done but no evidence location. ","")&IF(AND(J110="Not applicable",M110=""),"Say why it is not applicable. ","")) | R110: =IF(AND(A110<>"",N110="High",J110<>"Done",J110<>"Not applicable"),COUNTIFS($A$6:A110,"<>",$N$6:N110,"High",$J$6:J110,"<>Done",$J$6:J110,"<>Not applicable"),"")
G111: =IF(F111="","",INDEX(Timeline!$C$8:$C$10,F111)) | I111: =IF(H111="","",IF(H111="ALL","Yes",IF(IFERROR(INDEX('Applicability Screen'!$E$8:$E$20,MATCH(H111,'Applicability Screen'!$G$8:$G$20,0)),"")="","Answer screen",INDEX('Applicability Screen'!$E$8:$E$20,MATCH(H111,'Applicability Screen'!$G$8:$G$20,0))))) | P111: =IF(OR(O111="",J111="Done",J111="Not applicable"),"",IF(O111<TODAY(),"OVERDUE","")) | Q111: =IF(AND(A111="",D111=""),"",IF(AND(I111="No",J111<>"Not applicable"),"Screen says not triggered - confirm or mark Not applicable. ","")&IF(AND(G111<>"",J111<>"Done",J111<>"Not applicable",G111<=TODAY()),"Duty already in force. ","")&IF(AND(O111<>"",G111<>"",J111<>"Done",J111<>"Not applicable",O111>G111),"Target date is after the duty applies. ","")&IF(AND(N111="High",L111="",J111<>"Done",J111<>"Not applicable"),"High priority with no owner. ","")&IF(AND(J111="Done",K111=""),"Done but no evidence location. ","")&IF(AND(J111="Not applicable",M111=""),"Say why it is not applicable. ","")) | R111: =IF(AND(A111<>"",N111="High",J111<>"Done",J111<>"Not applicable"),COUNTIFS($A$6:A111,"<>",$N$6:N111,"High",$J$6:J111,"<>Done",$J$6:J111,"<>Not applicable"),"")
G112: =IF(F112="","",INDEX(Timeline!$C$8:$C$10,F112)) | I112: =IF(H112="","",IF(H112="ALL","Yes",IF(IFERROR(INDEX('Applicability Screen'!$E$8:$E$20,MATCH(H112,'Applicability Screen'!$G$8:$G$20,0)),"")="","Answer screen",INDEX('Applicability Screen'!$E$8:$E$20,MATCH(H112,'Applicability Screen'!$G$8:$G$20,0))))) | P112: =IF(OR(O112="",J112="Done",J112="Not applicable"),"",IF(O112<TODAY(),"OVERDUE","")) | Q112: =IF(AND(A112="",D112=""),"",IF(AND(I112="No",J112<>"Not applicable"),"Screen says not triggered - confirm or mark Not applicable. ","")&IF(AND(G112<>"",J112<>"Done",J112<>"Not applicable",G112<=TODAY()),"Duty already in force. ","")&IF(AND(O112<>"",G112<>"",J112<>"Done",J112<>"Not applicable",O112>G112),"Target date is after the duty applies. ","")&IF(AND(N112="High",L112="",J112<>"Done",J112<>"Not applicable"),"High priority with no owner. ","")&IF(AND(J112="Done",K112=""),"Done but no evidence location. ","")&IF(AND(J112="Not applicable",M112=""),"Say why it is not applicable. ","")) | R112: =IF(AND(A112<>"",N112="High",J112<>"Done",J112<>"Not applicable"),COUNTIFS($A$6:A112,"<>",$N$6:N112,"High",$J$6:J112,"<>Done",$J$6:J112,"<>Not applicable"),"")
G113: =IF(F113="","",INDEX(Timeline!$C$8:$C$10,F113)) | I113: =IF(H113="","",IF(H113="ALL","Yes",IF(IFERROR(INDEX('Applicability Screen'!$E$8:$E$20,MATCH(H113,'Applicability Screen'!$G$8:$G$20,0)),"")="","Answer screen",INDEX('Applicability Screen'!$E$8:$E$20,MATCH(H113,'Applicability Screen'!$G$8:$G$20,0))))) | P113: =IF(OR(O113="",J113="Done",J113="Not applicable"),"",IF(O113<TODAY(),"OVERDUE","")) | Q113: =IF(AND(A113="",D113=""),"",IF(AND(I113="No",J113<>"Not applicable"),"Screen says not triggered - confirm or mark Not applicable. ","")&IF(AND(G113<>"",J113<>"Done",J113<>"Not applicable",G113<=TODAY()),"Duty already in force. ","")&IF(AND(O113<>"",G113<>"",J113<>"Done",J113<>"Not applicable",O113>G113),"Target date is after the duty applies. ","")&IF(AND(N113="High",L113="",J113<>"Done",J113<>"Not applicable"),"High priority with no owner. ","")&IF(AND(J113="Done",K113=""),"Done but no evidence location. ","")&IF(AND(J113="Not applicable",M113=""),"Say why it is not applicable. ","")) | R113: =IF(AND(A113<>"",N113="High",J113<>"Done",J113<>"Not applicable"),COUNTIFS($A$6:A113,"<>",$N$6:N113,"High",$J$6:J113,"<>Done",$J$6:J113,"<>Not applicable"),"")
G114: =IF(F114="","",INDEX(Timeline!$C$8:$C$10,F114)) | I114: =IF(H114="","",IF(H114="ALL","Yes",IF(IFERROR(INDEX('Applicability Screen'!$E$8:$E$20,MATCH(H114,'Applicability Screen'!$G$8:$G$20,0)),"")="","Answer screen",INDEX('Applicability Screen'!$E$8:$E$20,MATCH(H114,'Applicability Screen'!$G$8:$G$20,0))))) | P114: =IF(OR(O114="",J114="Done",J114="Not applicable"),"",IF(O114<TODAY(),"OVERDUE","")) | Q114: =IF(AND(A114="",D114=""),"",IF(AND(I114="No",J114<>"Not applicable"),"Screen says not triggered - confirm or mark Not applicable. ","")&IF(AND(G114<>"",J114<>"Done",J114<>"Not applicable",G114<=TODAY()),"Duty already in force. ","")&IF(AND(O114<>"",G114<>"",J114<>"Done",J114<>"Not applicable",O114>G114),"Target date is after the duty applies. ","")&IF(AND(N114="High",L114="",J114<>"Done",J114<>"Not applicable"),"High priority with no owner. ","")&IF(AND(J114="Done",K114=""),"Done but no evidence location. ","")&IF(AND(J114="Not applicable",M114=""),"Say why it is not applicable. ","")) | R114: =IF(AND(A114<>"",N114="High",J114<>"Done",J114<>"Not applicable"),COUNTIFS($A$6:A114,"<>",$N$6:N114,"High",$J$6:J114,"<>Done",$J$6:J114,"<>Not applicable"),"")
G115: =IF(F115="","",INDEX(Timeline!$C$8:$C$10,F115)) | I115: =IF(H115="","",IF(H115="ALL","Yes",IF(IFERROR(INDEX('Applicability Screen'!$E$8:$E$20,MATCH(H115,'Applicability Screen'!$G$8:$G$20,0)),"")="","Answer screen",INDEX('Applicability Screen'!$E$8:$E$20,MATCH(H115,'Applicability Screen'!$G$8:$G$20,0))))) | P115: =IF(OR(O115="",J115="Done",J115="Not applicable"),"",IF(O115<TODAY(),"OVERDUE","")) | Q115: =IF(AND(A115="",D115=""),"",IF(AND(I115="No",J115<>"Not applicable"),"Screen says not triggered - confirm or mark Not applicable. ","")&IF(AND(G115<>"",J115<>"Done",J115<>"Not applicable",G115<=TODAY()),"Duty already in force. ","")&IF(AND(O115<>"",G115<>"",J115<>"Done",J115<>"Not applicable",O115>G115),"Target date is after the duty applies. ","")&IF(AND(N115="High",L115="",J115<>"Done",J115<>"Not applicable"),"High priority with no owner. ","")&IF(AND(J115="Done",K115=""),"Done but no evidence location. ","")&IF(AND(J115="Not applicable",M115=""),"Say why it is not applicable. ","")) | R115: =IF(AND(A115<>"",N115="High",J115<>"Done",J115<>"Not applicable"),COUNTIFS($A$6:A115,"<>",$N$6:N115,"High",$J$6:J115,"<>Done",$J$6:J115,"<>Not applicable"),"")
G116: =IF(F116="","",INDEX(Timeline!$C$8:$C$10,F116)) | I116: =IF(H116="","",IF(H116="ALL","Yes",IF(IFERROR(INDEX('Applicability Screen'!$E$8:$E$20,MATCH(H116,'Applicability Screen'!$G$8:$G$20,0)),"")="","Answer screen",INDEX('Applicability Screen'!$E$8:$E$20,MATCH(H116,'Applicability Screen'!$G$8:$G$20,0))))) | P116: =IF(OR(O116="",J116="Done",J116="Not applicable"),"",IF(O116<TODAY(),"OVERDUE","")) | Q116: =IF(AND(A116="",D116=""),"",IF(AND(I116="No",J116<>"Not applicable"),"Screen says not triggered - confirm or mark Not applicable. ","")&IF(AND(G116<>"",J116<>"Done",J116<>"Not applicable",G116<=TODAY()),"Duty already in force. ","")&IF(AND(O116<>"",G116<>"",J116<>"Done",J116<>"Not applicable",O116>G116),"Target date is after the duty applies. ","")&IF(AND(N116="High",L116="",J116<>"Done",J116<>"Not applicable"),"High priority with no owner. ","")&IF(AND(J116="Done",K116=""),"Done but no evidence location. ","")&IF(AND(J116="Not applicable",M116=""),"Say why it is not applicable. ","")) | R116: =IF(AND(A116<>"",N116="High",J116<>"Done",J116<>"Not applicable"),COUNTIFS($A$6:A116,"<>",$N$6:N116,"High",$J$6:J116,"<>Done",$J$6:J116,"<>Not applicable"),"")
... G119: =IF(F119="","",INDEX(Timeline!$C$8:$C$10,F119)) | I119: =IF(H119="","",IF(H119="ALL","Yes",IF(IFERROR(INDEX('Applicability Screen'!$E$8:$E$20,MATCH(H119,'Applicability Screen'!$G$8:$G$20,0)),"")="","Answer screen",INDEX('Applicability Screen'!$E$8:$E$20,MATCH(H119,'Applicability Screen'!$G$8:$G$20,0))))) | P119: =IF(OR(O119="",J119="Done",J119="Not applicable"),"",IF(O119<TODAY(),"OVERDUE","")) | Q119: =IF(AND(A119="",D119=""),"",IF(AND(I119="No",J119<>"Not applicable"),"Screen says not triggered - confirm or mark Not applicable. ","")&IF(AND(G119<>"",J119<>"Done",J119<>"Not applicable",G119<=TODAY()),"Duty already in force. ","")&IF(AND(O119<>"",G119<>"",J119<>"Done",J119<>"Not applicable",O119>G119),"Target date is after the duty applies. ","")&IF(AND(N119="High",L119="",J119<>"Done",J119<>"Not applicable"),"High priority with no owner. ","")&IF(AND(J119="Done",K119=""),"Done but no evidence location. ","")&IF(AND(J119="Not applicable",M119=""),"Say why it is not applicable. ","")) | R119: =IF(AND(A119<>"",N119="High",J119<>"Done",J119<>"Not applicable"),COUNTIFS($A$6:A119,"<>",$N$6:N119,"High",$J$6:J119,"<>Done",$J$6:J119,"<>Not applicable"),"")

Sheet Timeline
B1: Commencement timeline (verified dates only)
B2: By John Bommeraveni Joseph | linkedin.com/in/john-bj | Free every weekday: GRC Made Simple Daily
B5: Date the phases are counted from | C5: 45974 | D5: Default 13 Nov 2025 = date printed on both Gazette notifications (Nos. 757 and 760). Their e-Gazette upload IDs and digital signatures carry 14 Nov 2025, and the Rules say 'after the date of publication', so some advisers count from 14 Nov. Planning to the earlier date is the safer choice.
B7: Phase | C7: Comes into force | D7: Act provisions (G.S.R. 843(E)) | E7: Rules provisions (G.S.R. 846(E), rule 1) | F7: Days from today | G7: Exact day
B8: Phase 1 - on publication | C8: =C5 -> 45974 | D8: s.1(2), s.2, ss.18-26 (Data Protection Board), s.35, ss.38-43, s.44(1) and s.44(3) | E8: Rules 1, 2 and 17-21 (definitions; Board appointments, service terms, meetings, digital office, staff) | F8: =C8-TODAY() -> -348 | G8: Confirm the exact day with counsel (13th vs 14th reading)
B9: Phase 2 - one year | C9: =EDATE(C5,12) -> 46339 | D9: s.6(9) (Consent Manager registration) and s.27(1)(d) (Board inquiry into breach of registration conditions) | E9: Rule 4 (Consent Manager registration and obligations, First Schedule) | F9: =C9-TODAY() -> 17 | G9: Confirm the exact day with counsel (13th vs 14th reading)
B10: Phase 3 - eighteen months | C10: =EDATE(C5,18) -> 46520 | D10: ss.3-5, s.6(1)-(8) and (10), ss.7-17, s.27 except (1)(d), ss.28-34 (inquiry, appeals, penalties), s.36, s.37, s.44(2) (omits s.43A of the IT Act) | E10: Rules 3, 5-16, 22 and 23 (notice, State processing, security, breach, retention, contact, children, SDF, rights, transfer, research, appeals, information calls) | F10: =C10-TODAY() -> 198 | G10: Confirm the exact day with counsel (13th vs 14th reading)
B12: Key dates and instruments
B13: Date | C13: Event | D13: Instrument / reference | E13: What it does | G13: Verification
B14: 45149 | C14: DPDP Act receives assent and is published | D14: Act No. 22 of 2023; Gazette of India Extraordinary, Part II Sec 1, No. 25 | E14: Enacts the Act; s.1(2) lets the Government bring provisions into force on different dates. | G14: Verified - official Gazette text
B15: 45660 | C15: Draft DPDP Rules published for consultation | D15: G.S.R. 02(E) (recited in the preamble of G.S.R. 846(E)) | E15: Invited objections and suggestions for 45 days. | G15: Verified - recital in G.S.R. 846(E)
B16: 45974 | C16: Act commencement notification | D16: G.S.R. 843(E), Gazette No. 757, dated 13 Nov 2025 (e-Gazette CG-DL-E-14112025-267647) | E16: Brings the Act into force in three phases (table above). | G16: Verified - official Gazette text
B17: 45974 | C17: DPDP Rules, 2025 notified | D17: G.S.R. 846(E), Gazette No. 760, dated 13 Nov 2025 (e-Gazette CG-DL-E-14112025-267650) | E17: Makes the Rules; rule 1(2)-(4) sets their phased commencement. | G17: Verified - official Gazette text
B18: 45975 | C18: MeitY press release on the Rules | D18: PIB release, 14 Nov 2025 | E18: Government summary of the Rules (supporting only - the Gazette text governs). | G18: Verified - PIB page
B19: =C9 -> 46339 | C19: Phase 2 begins | D19: G.S.R. 843(E) clause (b); rule 1(3) | E19: Consent Manager registration and obligations apply. | G19: Computed from the verified text
B20: =C10 -> 46520 | C20: Phase 3 begins - main obligations | D20: G.S.R. 843(E) clause (c); rule 1(4) | E20: Most Data Fiduciary, SDF, rights, penalty and transfer provisions apply. | G20: Computed from the verified text
B21: 5/6 Oct 2026 | C21: Reported: Digital Personal Data Protection (Removal of Difficulties) Order, 2026 | D21: Reported as S.O. 5458(E) | E21: Reported to make two wording corrections: s.9(1) 'child or of a person with disability' and s.10(2)(c)(ii) 'data audit'. Reported to add no new duty or date. | G21: VERIFY - seen only in secondary sources; not found on egazette.gov.in or meity.gov.in
B22: Jan 2026 | C22: Reported: proposal to shorten the 18-month period | D22: No Gazette notification found | E22: Secondary trackers report a proposal to compress the timeline. No notification found as at 27 Oct 2026 - the notified 18-month phase stands. | G22: VERIFY - check the Gazette before relying either way
B24: Only dates that could be read in, or computed from, the official Gazette texts are shown without a VERIFY mark. 'Days from today' recalculates each time the file opens.

Sheet Penalties
B1: Penalty Schedule (s.33 and the Schedule to the Act)
B2: By John Bommeraveni Joseph | linkedin.com/in/john-bj | Free every weekday: GRC Made Simple Daily
B5: Sl. | C5: Breach (our summary) | D5: Provision breached | E5: Maximum penalty (as in the Schedule) | F5: Maximum in rupees | G5: Checklist area
B6: 1 | C6: Failure to take reasonable security safeguards to prevent personal data breach | D6: s.8(5) | E6: May extend to 250 crore rupees | F6: 2500000000 | G6: Security safeguards
B7: 2 | C7: Failure to give the Board or an affected Data Principal intimation of a personal data breach | D7: s.8(6) | E7: May extend to 200 crore rupees | F7: 2000000000 | G7: Breach intimation
B8: 3 | C8: Breach of the additional obligations relating to children | D8: s.9 | E8: May extend to 200 crore rupees | F8: 2000000000 | G8: Children and persons with disability
B9: 4 | C9: Breach of the additional obligations of a Significant Data Fiduciary | D9: s.10 | E9: May extend to 150 crore rupees | F9: 1500000000 | G9: Significant Data Fiduciary
B10: 5 | C10: Breach of the duties of a Data Principal | D10: s.15 | E10: May extend to ten thousand rupees | F10: 10000 | G10: Applies to the Data Principal
B11: 6 | C11: Breach of any term of a voluntary undertaking accepted by the Board | D11: s.32 | E11: Up to the extent applicable to the breach for which the s.28 proceedings were instituted | F11: n/a | G11: Any
B12: 7 | C12: Breach of any other provision of the Act or the Rules | D12: Any other provision | E12: May extend to 50 crore rupees | F12: 500000000 | G12: All other areas
C14: How penalties work
C15: s.33(1): the Board may impose a monetary penalty only if, on concluding an inquiry, it determines the breach is significant, and only after giving the person an opportunity of being heard. The amounts above are maximums.
C16: s.33(2): in setting the amount the Board must consider the nature, gravity and duration of the breach; the type and nature of the personal data affected; whether it is repetitive; any gain made or loss avoided; whether and how quickly and effectively the person mitigated it; whether the penalty is proportionate and effective as a deterrent; and its likely impact on the person.
C17: s.32: the Board may accept a voluntary undertaking at any stage of a proceeding; accepting it bars proceedings on its contents, but failing to honour it is treated as a breach of the Act.
C18: s.37: after a Data Fiduciary has been penalised in two or more instances, the Board may refer the case to the Central Government, which may, after a hearing, direct that public access to information enabling its services in India be blocked.
C19: s.34: penalties are credited to the Consolidated Fund of India. Sections 28-34 and 37 come into force in Phase 3 (see Timeline).

Sheet Sources
B1: Sources and notification references
B2: By John Bommeraveni Joseph | linkedin.com/in/john-bj | Free every weekday: GRC Made Simple Daily
B5: Source | C5: Link
B6: The Digital Personal Data Protection Act, 2023 (No. 22 of 2023) - Gazette of India Extraordinary, Part II Section 1, No. 25, 11 August 2023 (MeitY copy). Checked 27 Oct 2026, SHA-256 4deb2398...7a7d15. | C6: https://www.meity.gov.in/static/uploads/2024/06/2bf1f0e9f04e6fb4f8fef35e82c42aa5.pdf
B7: Digital Personal Data Protection Rules, 2025 - G.S.R. 846(E), 13 November 2025, Gazette of India Extraordinary, Part II Section 3(i), No. 760, F. No. AA-11038/1/2025-CL&ES (MeitY copy). | C7: https://www.meity.gov.in/static/uploads/2025/11/53450e6e5dc0bfa85ebd78686cadad39.pdf
B8: Same Rules - e-Gazette copy CG-DL-E-14112025-267650 (byte-identical to the MeitY copy, SHA-256 eabc7d05...51f5aa08). | C8: https://egazette.gov.in/WriteReadData/2025/267650.pdf
B9: Act commencement notification - G.S.R. 843(E), 13 November 2025, Gazette No. 757, e-Gazette CG-DL-E-14112025-267647 (SHA-256 6df25cd8...0998e5). | C9: https://egazette.gov.in/WriteReadData/2025/267647.pdf
B10: Press Information Bureau (MeitY) - 'Government notifies DPDP Rules to empower citizens and protect privacy', 14 Nov 2025. Supporting summary only; the Gazette text governs. | C10: https://www.pib.gov.in/PressReleasePage.aspx?PRID=2190014
B11: VERIFY - Digital Personal Data Protection (Removal of Difficulties) Order, 2026, reported as S.O. 5458(E) dated 5 Oct 2026. Secondary report only; no official copy found on egazette.gov.in or meity.gov.in on 27 Oct 2026. | C11: https://www.scconline.com/blog/post/2026/10/15/dpdp-removal-of-difficulties-order-2026/
B13: How this was checked: each row was written from the Gazette texts above, read in full on 27 Oct 2026. Summaries are our own words. Where a point could not be settled from the official texts it is marked VERIFY in red. Not covered: other Indian laws and sector rules, and any instrument published after 27 Oct 2026.
B15: Template by John Bommeraveni Joseph - ISO/IEC 27001, 42001 and 27701 Lead Auditor. Follow on LinkedIn for the free weekday newsletter GRC Made Simple Daily: linkedin.com/in/john-bj

Sheet Lists
B1: Lists (drop-down values)
B2: By John Bommeraveni Joseph | linkedin.com/in/john-bj | Free every weekday: GRC Made Simple Daily
A5: Status | B5: Priority | C5: Answer | D5: Area
A6: Not started | B6: High | C6: Yes | D6: Applicability and roles
A7: In progress | B7: Medium | C7: No | D7: Notice
A8: Done | B8: Low | C8: Not sure | D8: Consent and withdrawal
A9: Not applicable | D9: Legitimate uses
D10: Governance and data accuracy
D11: Security safeguards
D12: Breach intimation
D13: Retention and erasure
D14: Contact and grievance
D15: Data Processors and contracts
D16: Children and persons with disability
D17: Significant Data Fiduciary
D18: Data Principal rights
D19: Consent Managers
D20: Cross-border transfer
D21: Records and information requests
